Workbook

Sheet Spread Monitor
A1: Bond spread variation since 14.07.2026
A2: Anchor date | B2: 46217 | C2: Blue on yellow = the only cell to edit. Everything else is a formula.
A3: Bonds priced | B3: =COUNT($S$7:$S$850)&" of "&COUNTA($A$7:$A$850) | C3: Paste additional ISINs at the bottom of column A - formulas already run to row 850.
A4: Data | B4: Bloomberg BDP (add-in must be connected). Press F9 / Ctrl+Alt+F9 to refresh.
A6: ISIN | B6: Company | C6: Company description | D6: SYZ view | E6: Sector | F6: Country | G6: Ccy | H6: Rating | I6: Classification | J6: Structure | K6: Coupon | L6: Maturity | M6: Den. (k) | N6: Price | O6: YTW (%) | P6: Mod. dur. | Q6: Spread today (bp) | R6: ="Spread on "&TEXT($B$2,"dd.mm.yyyy")&" (bp)" | S6: ="Spread change since "&TEXT($B$2,"dd.mm.yyyy")&" (bp)" | T6: ="YTW on "&TEXT($B$2,"dd.mm.yyyy")&" (%)" | U6: ="YTW change since "&TEXT($B$2,"dd.mm.yyyy")&" (%)" | V6: Rank widening | W6: Rank tightening | X6: Key widening | Y6: Key tightening
A7: USN15516AB83 | B7: =IF($A7="","",PROPER(_xll.BDP($A7&" Corp","NAME"))) | C7: =IF($A7="","",IFERROR(INDEX(Company_desc!$B$2:$B$1144,MATCH($A7,Company_desc!$A$2:$A$1144,0)),IFERROR(INDEX(SYZ_static!$Q$2:$Q$806,MATCH($A7,SYZ_static!$A$2:$A$806,0)),""))) | D7: =IF($A7="","",IFERROR(INDEX(SYZ_static!$B$2:$B$806,MATCH($A7,SYZ_static!$A$2:$A$806,0)),"")) | E7: =IF($A7="","",_xll.BDP($A7&" Corp","INDUSTRY_SECTOR")) | F7: =IF($A7="","",PROPER(_xll.BDP($A7&" Corp","COUNTRY_FULL_NAME"))) | G7: =IF($A7="","",_xll.BDP($A7&" Corp","CRNCY")) | H7: =IF($A7="","",IFERROR(INDEX(SYZ_static!$T$2:$T$806,MATCH($A7,SYZ_static!$A$2:$A$806,0)),_xll.BDP($A7&" Corp","RTG_SP"))) | I7: =IF($A7="","",IFERROR(INDEX(SYZ_static!$S$2:$S$806,MATCH($A7,SYZ_static!$A$2:$A$806,0)),"")) | J7: =IF($A7="","",_xll.BDP($A7&" Corp","PAYMENT_RANK")) | K7: =IF($A7="","",_xll.BDP($A7&" Corp","CPN")) | L7: =IF($A7="","",_xll.BDP($A7&" Corp","MATURITY")) | M7: =IF($A7="","",IFERROR(_xll.BDP($A7&" Corp","MIN_PIECE")/1000,"")) | N7: =IF($A7="","",_xll.BDP($A7&" Corp","PX_LAST")) | O7: =IF($A7="","",_xll.BDP($A7&" Corp","YAS_BOND_YLD","YAS_YLD_FLAG=15")) | P7: =IF($A7="","",_xll.BDP($A7&" Corp","YAS_MOD_DUR")) | Q7: =IF($A7="","",_xll.BDP($A7&" Corp","YAS_OAS_SPRD")) | R7: =IF($A7="","",_xll.BDP($A7&" Corp","YAS_OAS_SPRD","SETTLE_DT",$B$2)) | S7: =IF($A7="","",IF(OR(NOT(ISNUMBER($Q7)),NOT(ISNUMBER($R7))),"",$Q7-$R7)) | T7: =IF($A7="","",_xll.BDP($A7&" Corp","YAS_BOND_YLD","YAS_YLD_FLAG=15","SETTLE_DT",$B$2)) | U7: =IF($A7="","",IF(OR(NOT(ISNUMBER($O7)),NOT(ISNUMBER($T7))),"",$O7-$T7)) | V7: =IF(NOT(ISNUMBER($S7)),"",COUNTIFS($G$7:$G$850,$G7,$S$7:$S$850,">"&$S7)+COUNTIFS($G$7:$G7,$G7,$S$7:$S7,$S7)) | W7: =IF(NOT(ISNUMBER($S7)),"",COUNTIFS($G$7:$G$850,$G7,$S$7:$S$850,"<"&$S7)+COUNTIFS($G$7:$G7,$G7,$S$7:$S7,$S7)) | X7: =IF($V7="","",$G7&"|"&$V7) | Y7: =IF($W7="","",$G7&"|"&$W7)
A8: USN15516AG70 | B8: =IF($A8="","",PROPER(_xll.BDP($A8&" Corp","NAME"))) | C8: =IF($A8="","",IFERROR(INDEX(Company_desc!$B$2:$B$1144,MATCH($A8,Company_desc!$A$2:$A$1144,0)),IFERROR(INDEX(SYZ_static!$Q$2:$Q$806,MATCH($A8,SYZ_static!$A$2:$A$806,0)),""))) | D8: =IF($A8="","",IFERROR(INDEX(SYZ_static!$B$2:$B$806,MATCH($A8,SYZ_static!$A$2:$A$806,0)),"")) | E8: =IF($A8="","",_xll.BDP($A8&" Corp","INDUSTRY_SECTOR")) | F8: =IF($A8="","",PROPER(_xll.BDP($A8&" Corp","COUNTRY_FULL_NAME"))) | G8: =IF($A8="","",_xll.BDP($A8&" Corp","CRNCY")) | H8: =IF($A8="","",IFERROR(INDEX(SYZ_static!$T$2:$T$806,MATCH($A8,SYZ_static!$A$2:$A$806,0)),_xll.BDP($A8&" Corp","RTG_SP"))) | I8: =IF($A8="","",IFERROR(INDEX(SYZ_static!$S$2:$S$806,MATCH($A8,SYZ_static!$A$2:$A$806,0)),"")) | J8: =IF($A8="","",_xll.BDP($A8&" Corp","PAYMENT_RANK")) | K8: =IF($A8="","",_xll.BDP($A8&" Corp","CPN")) | L8: =IF($A8="","",_xll.BDP($A8&" Corp","MATURITY")) | M8: =IF($A8="","",IFERROR(_xll.BDP($A8&" Corp","MIN_PIECE")/1000,"")) | N8: =IF($A8="","",_xll.BDP($A8&" Corp","PX_LAST")) | O8: =IF($A8="","",_xll.BDP($A8&" Corp","YAS_BOND_YLD","YAS_YLD_FLAG=15")) | P8: =IF($A8="","",_xll.BDP($A8&" Corp","YAS_MOD_DUR")) | Q8: =IF($A8="","",_xll.BDP($A8&" Corp","YAS_OAS_SPRD")) | R8: =IF($A8="","",_xll.BDP($A8&" Corp","YAS_OAS_SPRD","SETTLE_DT",$B$2)) | S8: =IF($A8="","",IF(OR(NOT(ISNUMBER($Q8)),NOT(ISNUMBER($R8))),"",$Q8-$R8)) | T8: =IF($A8="","",_xll.BDP($A8&" Corp","YAS_BOND_YLD","YAS_YLD_FLAG=15","SETTLE_DT",$B$2)) | U8: =IF($A8="","",IF(OR(NOT(ISNUMBER($O8)),NOT(ISNUMBER($T8))),"",$O8-$T8)) | V8: =IF(NOT(ISNUMBER($S8)),"",COUNTIFS($G$7:$G$850,$G8,$S$7:$S$850,">"&$S8)+COUNTIFS($G$7:$G8,$G8,$S$7:$S8,$S8)) | W8: =IF(NOT(ISNUMBER($S8)),"",COUNTIFS($G$7:$G$850,$G8,$S$7:$S$850,"<"&$S8)+COUNTIFS($G$7:$G8,$G8,$S$7:$S8,$S8)) | X8: =IF($V8="","",$G8&"|"&$V8) | Y8: =IF($W8="","",$G8&"|"&$W8)
A9: USU60050AA61 | B9: =IF($A9="","",PROPER(_xll.BDP($A9&" Corp","NAME"))) | C9: =IF($A9="","",IFERROR(INDEX(Company_desc!$B$2:$B$1144,MATCH($A9,Company_desc!$A$2:$A$1144,0)),IFERROR(INDEX(SYZ_static!$Q$2:$Q$806,MATCH($A9,SYZ_static!$A$2:$A$806,0)),""))) | D9: =IF($A9="","",IFERROR(INDEX(SYZ_static!$B$2:$B$806,MATCH($A9,SYZ_static!$A$2:$A$806,0)),"")) | E9: =IF($A9="","",_xll.BDP($A9&" Corp","INDUSTRY_SECTOR")) | F9: =IF($A9="","",PROPER(_xll.BDP($A9&" Corp","COUNTRY_FULL_NAME"))) | G9: =IF($A9="","",_xll.BDP($A9&" Corp","CRNCY")) | H9: =IF($A9="","",IFERROR(INDEX(SYZ_static!$T$2:$T$806,MATCH($A9,SYZ_static!$A$2:$A$806,0)),_xll.BDP($A9&" Corp","RTG_SP"))) | I9: =IF($A9="","",IFERROR(INDEX(SYZ_static!$S$2:$S$806,MATCH($A9,SYZ_static!$A$2:$A$806,0)),"")) | J9: =IF($A9="","",_xll.BDP($A9&" Corp","PAYMENT_RANK")) | K9: =IF($A9="","",_xll.BDP($A9&" Corp","CPN")) | L9: =IF($A9="","",_xll.BDP($A9&" Corp","MATURITY")) | M9: =IF($A9="","",IFERROR(_xll.BDP($A9&" Corp","MIN_PIECE")/1000,"")) | N9: =IF($A9="","",_xll.BDP($A9&" Corp","PX_LAST")) | O9: =IF($A9="","",_xll.BDP($A9&" Corp","YAS_BOND_YLD","YAS_YLD_FLAG=15")) | P9: =IF($A9="","",_xll.BDP($A9&" Corp","YAS_MOD_DUR")) | Q9: =IF($A9="","",_xll.BDP($A9&" Corp","YAS_OAS_SPRD")) | R9: =IF($A9="","",_xll.BDP($A9&" Corp","YAS_OAS_SPRD","SETTLE_DT",$B$2)) | S9: =IF($A9="","",IF(OR(NOT(ISNUMBER($Q9)),NOT(ISNUMBER($R9))),"",$Q9-$R9)) | T9: =IF($A9="","",_xll.BDP($A9&" Corp","YAS_BOND_YLD","YAS_YLD_FLAG=15","SETTLE_DT",$B$2)) | U9: =IF($A9="","",IF(OR(NOT(ISNUMBER($O9)),NOT(ISNUMBER($T9))),"",$O9-$T9)) | V9: =IF(NOT(ISNUMBER($S9)),"",COUNTIFS($G$7:$G$850,$G9,$S$7:$S$850,">"&$S9)+COUNTIFS($G$7:$G9,$G9,$S$7:$S9,$S9)) | W9: =IF(NOT(ISNUMBER($S9)),"",COUNTIFS($G$7:$G$850,$G9,$S$7:$S$850,"<"&$S9)+COUNTIFS($G$7:$G9,$G9,$S$7:$S9,$S9)) | X9: =IF($V9="","",$G9&"|"&$V9) | Y9: =IF($W9="","",$G9&"|"&$W9)
A10: USU1065PAA94 | B10: =IF($A10="","",PROPER(_xll.BDP($A10&" Corp","NAME"))) | C10: =IF($A10="","",IFERROR(INDEX(Company_desc!$B$2:$B$1144,MATCH($A10,Company_desc!$A$2:$A$1144,0)),IFERROR(INDEX(SYZ_static!$Q$2:$Q$806,MATCH($A10,SYZ_static!$A$2:$A$806,0)),""))) | D10: =IF($A10="","",IFERROR(INDEX(SYZ_static!$B$2:$B$806,MATCH($A10,SYZ_static!$A$2:$A$806,0)),"")) | E10: =IF($A10="","",_xll.BDP($A10&" Corp","INDUSTRY_SECTOR")) | F10: =IF($A10="","",PROPER(_xll.BDP($A10&" Corp","COUNTRY_FULL_NAME"))) | G10: =IF($A10="","",_xll.BDP($A10&" Corp","CRNCY")) | H10: =IF($A10="","",IFERROR(INDEX(SYZ_static!$T$2:$T$806,MATCH($A10,SYZ_static!$A$2:$A$806,0)),_xll.BDP($A10&" Corp","RTG_SP"))) | I10: =IF($A10="","",IFERROR(INDEX(SYZ_static!$S$2:$S$806,MATCH($A10,SYZ_static!$A$2:$A$806,0)),"")) | J10: =IF($A10="","",_xll.BDP($A10&" Corp","PAYMENT_RANK")) | K10: =IF($A10="","",_xll.BDP($A10&" Corp","CPN")) | L10: =IF($A10="","",_xll.BDP($A10&" Corp","MATURITY")) | M10: =IF($A10="","",IFERROR(_xll.BDP($A10&" Corp","MIN_PIECE")/1000,"")) | N10: =IF($A10="","",_xll.BDP($A10&" Corp","PX_LAST")) | O10: =IF($A10="","",_xll.BDP($A10&" Corp","YAS_BOND_YLD","YAS_YLD_FLAG=15")) | P10: =IF($A10="","",_xll.BDP($A10&" Corp","YAS_MOD_DUR")) | Q10: =IF($A10="","",_xll.BDP($A10&" Corp","YAS_OAS_SPRD")) | R10: =IF($A10="","",_xll.BDP($A10&" Corp","YAS_OAS_SPRD","SETTLE_DT",$B$2)) | S10: =IF($A10="","",IF(OR(NOT(ISNUMBER($Q10)),NOT(ISNUMBER($R10))),"",$Q10-$R10)) | T10: =IF($A10="","",_xll.BDP($A10&" Corp","YAS_BOND_YLD","YAS_YLD_FLAG=15","SETTLE_DT",$B$2)) | U10: =IF($A10="","",IF(OR(NOT(ISNUMBER($O10)),NOT(ISNUMBER($T10))),"",$O10-$T10)) | V10: =IF(NOT(ISNUMBER($S10)),"",COUNTIFS($G$7:$G$850,$G10,$S$7:$S$850,">"&$S10)+COUNTIFS($G$7:$G10,$G10,$S$7:$S10,$S10)) | W10: =IF(NOT(ISNUMBER($S10)),"",COUNTIFS($G$7:$G$850,$G10,$S$7:$S$850,"<"&$S10)+COUNTIFS($G$7:$G10,$G10,$S$7:$S10,$S10)) | X10: =IF($V10="","",$G10&"|"&$V10) | Y10: =IF($W10="","",$G10&"|"&$W10)
A11: US80386WAD74 | B11: =IF($A11="","",PROPER(_xll.BDP($A11&" Corp","NAME"))) | C11: =IF($A11="","",IFERROR(INDEX(Company_desc!$B$2:$B$1144,MATCH($A11,Company_desc!$A$2:$A$1144,0)),IFERROR(INDEX(SYZ_static!$Q$2:$Q$806,MATCH($A11,SYZ_static!$A$2:$A$806,0)),""))) | D11: =IF($A11="","",IFERROR(INDEX(SYZ_static!$B$2:$B$806,MATCH($A11,SYZ_static!$A$2:$A$806,0)),"")) | E11: =IF($A11="","",_xll.BDP($A11&" Corp","INDUSTRY_SECTOR")) | F11: =IF($A11="","",PROPER(_xll.BDP($A11&" Corp","COUNTRY_FULL_NAME"))) | G11: =IF($A11="","",_xll.BDP($A11&" Corp","CRNCY")) | H11: =IF($A11="","",IFERROR(INDEX(SYZ_static!$T$2:$T$806,MATCH($A11,SYZ_static!$A$2:$A$806,0)),_xll.BDP($A11&" Corp","RTG_SP"))) | I11: =IF($A11="","",IFERROR(INDEX(SYZ_static!$S$2:$S$806,MATCH($A11,SYZ_static!$A$2:$A$806,0)),"")) | J11: =IF($A11="","",_xll.BDP($A11&" Corp","PAYMENT_RANK")) | K11: =IF($A11="","",_xll.BDP($A11&" Corp","CPN")) | L11: =IF($A11="","",_xll.BDP($A11&" Corp","MATURITY")) | M11: =IF($A11="","",IFERROR(_xll.BDP($A11&" Corp","MIN_PIECE")/1000,"")) | N11: =IF($A11="","",_xll.BDP($A11&" Corp","PX_LAST")) | O11: =IF($A11="","",_xll.BDP($A11&" Corp","YAS_BOND_YLD","YAS_YLD_FLAG=15")) | P11: =IF($A11="","",_xll.BDP($A11&" Corp","YAS_MOD_DUR")) | Q11: =IF($A11="","",_xll.BDP($A11&" Corp","YAS_OAS_SPRD")) | R11: =IF($A11="","",_xll.BDP($A11&" Corp","YAS_OAS_SPRD","SETTLE_DT",$B$2)) | S11: =IF($A11="","",IF(OR(NOT(ISNUMBER($Q11)),NOT(ISNUMBER($R11))),"",$Q11-$R11)) | T11: =IF($A11="","",_xll.BDP($A11&" Corp","YAS_BOND_YLD","YAS_YLD_FLAG=15","SETTLE_DT",$B$2)) | U11: =IF($A11="","",IF(OR(NOT(ISNUMBER($O11)),NOT(ISNUMBER($T11))),"",$O11-$T11)) | V11: =IF(NOT(ISNUMBER($S11)),"",COUNTIFS($G$7:$G$850,$G11,$S$7:$S$850,">"&$S11)+COUNTIFS($G$7:$G11,$G11,$S$7:$S11,$S11)) | W11: =IF(NOT(ISNUMBER($S11)),"",COUNTIFS($G$7:$G$850,$G11,$S$7:$S$850,"<"&$S11)+COUNTIFS($G$7:$G11,$G11,$S$7:$S11,$S11)) | X11: =IF($V11="","",$G11&"|"&$V11) | Y11: =IF($W11="","",$G11&"|"&$W11)
A12: USG2583XAB76 | B12: =IF($A12="","",PROPER(_xll.BDP($A12&" Corp","NAME"))) | C12: =IF($A12="","",IFERROR(INDEX(Company_desc!$B$2:$B$1144,MATCH($A12,Company_desc!$A$2:$A$1144,0)),IFERROR(INDEX(SYZ_static!$Q$2:$Q$806,MATCH($A12,SYZ_static!$A$2:$A$806,0)),""))) | D12: =IF($A12="","",IFERROR(INDEX(SYZ_static!$B$2:$B$806,MATCH($A12,SYZ_static!$A$2:$A$806,0)),"")) | E12: =IF($A12="","",_xll.BDP($A12&" Corp","INDUSTRY_SECTOR")) | F12: =IF($A12="","",PROPER(_xll.BDP($A12&" Corp","COUNTRY_FULL_NAME"))) | G12: =IF($A12="","",_xll.BDP($A12&" Corp","CRNCY")) | H12: =IF($A12="","",IFERROR(INDEX(SYZ_static!$T$2:$T$806,MATCH($A12,SYZ_static!$A$2:$A$806,0)),_xll.BDP($A12&" Corp","RTG_SP"))) | I12: =IF($A12="","",IFERROR(INDEX(SYZ_static!$S$2:$S$806,MATCH($A12,SYZ_static!$A$2:$A$806,0)),"")) | J12: =IF($A12="","",_xll.BDP($A12&" Corp","PAYMENT_RANK")) | K12: =IF($A12="","",_xll.BDP($A12&" Corp","CPN")) | L12: =IF($A12="","",_xll.BDP($A12&" Corp","MATURITY")) | M12: =IF($A12="","",IFERROR(_xll.BDP($A12&" Corp","MIN_PIECE")/1000,"")) | N12: =IF($A12="","",_xll.BDP($A12&" Corp","PX_LAST")) | O12: =IF($A12="","",_xll.BDP($A12&" Corp","YAS_BOND_YLD","YAS_YLD_FLAG=15")) | P12: =IF($A12="","",_xll.BDP($A12&" Corp","YAS_MOD_DUR")) | Q12: =IF($A12="","",_xll.BDP($A12&" Corp","YAS_OAS_SPRD")) | R12: =IF($A12="","",_xll.BDP($A12&" Corp","YAS_OAS_SPRD","SETTLE_DT",$B$2)) | S12: =IF($A12="","",IF(OR(NOT(ISNUMBER($Q12)),NOT(ISNUMBER($R12))),"",$Q12-$R12)) | T12: =IF($A12="","",_xll.BDP($A12&" Corp","YAS_BOND_YLD","YAS_YLD_FLAG=15","SETTLE_DT",$B$2)) | U12: =IF($A12="","",IF(OR(NOT(ISNUMBER($O12)),NOT(ISNUMBER($T12))),"",$O12-$T12)) | V12: =IF(NOT(ISNUMBER($S12)),"",COUNTIFS($G$7:$G$850,$G12,$S$7:$S$850,">"&$S12)+COUNTIFS($G$7:$G12,$G12,$S$7:$S12,$S12)) | W12: =IF(NOT(ISNUMBER($S12)),"",COUNTIFS($G$7:$G$850,$G12,$S$7:$S$850,"<"&$S12)+COUNTIFS($G$7:$G12,$G12,$S$7:$S12,$S12)) | X12: =IF($V12="","",$G12&"|"&$V12) | Y12: =IF($W12="","",$G12&"|"&$W12)
A13: USE0R75RAB28 | B13: =IF($A13="","",PROPER(_xll.BDP($A13&" Corp","NAME"))) | C13: =IF($A13="","",IFERROR(INDEX(Company_desc!$B$2:$B$1144,MATCH($A13,Company_desc!$A$2:$A$1144,0)),IFERROR(INDEX(SYZ_static!$Q$2:$Q$806,MATCH($A13,SYZ_static!$A$2:$A$806,0)),""))) | D13: =IF($A13="","",IFERROR(INDEX(SYZ_static!$B$2:$B$806,MATCH($A13,SYZ_static!$A$2:$A$806,0)),"")) | E13: =IF($A13="","",_xll.BDP($A13&" Corp","INDUSTRY_SECTOR")) | F13: =IF($A13="","",PROPER(_xll.BDP($A13&" Corp","COUNTRY_FULL_NAME"))) | G13: =IF($A13="","",_xll.BDP($A13&" Corp","CRNCY")) | H13: =IF($A13="","",IFERROR(INDEX(SYZ_static!$T$2:$T$806,MATCH($A13,SYZ_static!$A$2:$A$806,0)),_xll.BDP($A13&" Corp","RTG_SP"))) | I13: =IF($A13="","",IFERROR(INDEX(SYZ_static!$S$2:$S$806,MATCH($A13,SYZ_static!$A$2:$A$806,0)),"")) | J13: =IF($A13="","",_xll.BDP($A13&" Corp","PAYMENT_RANK")) | K13: =IF($A13="","",_xll.BDP($A13&" Corp","CPN")) | L13: =IF($A13="","",_xll.BDP($A13&" Corp","MATURITY")) | M13: =IF($A13="","",IFERROR(_xll.BDP($A13&" Corp","MIN_PIECE")/1000,"")) | N13: =IF($A13="","",_xll.BDP($A13&" Corp","PX_LAST")) | O13: =IF($A13="","",_xll.BDP($A13&" Corp","YAS_BOND_YLD","YAS_YLD_FLAG=15")) | P13: =IF($A13="","",_xll.BDP($A13&" Corp","YAS_MOD_DUR")) | Q13: =IF($A13="","",_xll.BDP($A13&" Corp","YAS_OAS_SPRD")) | R13: =IF($A13="","",_xll.BDP($A13&" Corp","YAS_OAS_SPRD","SETTLE_DT",$B$2)) | S13: =IF($A13="","",IF(OR(NOT(ISNUMBER($Q13)),NOT(ISNUMBER($R13))),"",$Q13-$R13)) | T13: =IF($A13="","",_xll.BDP($A13&" Corp","YAS_BOND_YLD","YAS_YLD_FLAG=15","SETTLE_DT",$B$2)) | U13: =IF($A13="","",IF(OR(NOT(ISNUMBER($O13)),NOT(ISNUMBER($T13))),"",$O13-$T13)) | V13: =IF(NOT(ISNUMBER($S13)),"",COUNTIFS($G$7:$G$850,$G13,$S$7:$S$850,">"&$S13)+COUNTIFS($G$7:$G13,$G13,$S$7:$S13,$S13)) | W13: =IF(NOT(ISNUMBER($S13)),"",COUNTIFS($G$7:$G$850,$G13,$S$7:$S$850,"<"&$S13)+COUNTIFS($G$7:$G13,$G13,$S$7:$S13,$S13)) | X13: =IF($V13="","",$G13&"|"&$V13) | Y13: =IF($W13="","",$G13&"|"&$W13)
A14: USU8035UAC63 | B14: =IF($A14="","",PROPER(_xll.BDP($A14&" Corp","NAME"))) | C14: =IF($A14="","",IFERROR(INDEX(Company_desc!$B$2:$B$1144,MATCH($A14,Company_desc!$A$2:$A$1144,0)),IFERROR(INDEX(SYZ_static!$Q$2:$Q$806,MATCH($A14,SYZ_static!$A$2:$A$806,0)),""))) | D14: =IF($A14="","",IFERROR(INDEX(SYZ_static!$B$2:$B$806,MATCH($A14,SYZ_static!$A$2:$A$806,0)),"")) | E14: =IF($A14="","",_xll.BDP($A14&" Corp","INDUSTRY_SECTOR")) | F14: =IF($A14="","",PROPER(_xll.BDP($A14&" Corp","COUNTRY_FULL_NAME"))) | G14: =IF($A14="","",_xll.BDP($A14&" Corp","CRNCY")) | H14: =IF($A14="","",IFERROR(INDEX(SYZ_static!$T$2:$T$806,MATCH($A14,SYZ_static!$A$2:$A$806,0)),_xll.BDP($A14&" Corp","RTG_SP"))) | I14: =IF($A14="","",IFERROR(INDEX(SYZ_static!$S$2:$S$806,MATCH($A14,SYZ_static!$A$2:$A$806,0)),"")) | J14: =IF($A14="","",_xll.BDP($A14&" Corp","PAYMENT_RANK")) | K14: =IF($A14="","",_xll.BDP($A14&" Corp","CPN")) | L14: =IF($A14="","",_xll.BDP($A14&" Corp","MATURITY")) | M14: =IF($A14="","",IFERROR(_xll.BDP($A14&" Corp","MIN_PIECE")/1000,"")) | N14: =IF($A14="","",_xll.BDP($A14&" Corp","PX_LAST")) | O14: =IF($A14="","",_xll.BDP($A14&" Corp","YAS_BOND_YLD","YAS_YLD_FLAG=15")) | P14: =IF($A14="","",_xll.BDP($A14&" Corp","YAS_MOD_DUR")) | Q14: =IF($A14="","",_xll.BDP($A14&" Corp","YAS_OAS_SPRD")) | R14: =IF($A14="","",_xll.BDP($A14&" Corp","YAS_OAS_SPRD","SETTLE_DT",$B$2)) | S14: =IF($A14="","",IF(OR(NOT(ISNUMBER($Q14)),NOT(ISNUMBER($R14))),"",$Q14-$R14)) | T14: =IF($A14="","",_xll.BDP($A14&" Corp","YAS_BOND_YLD","YAS_YLD_FLAG=15","SETTLE_DT",$B$2)) | U14: =IF($A14="","",IF(OR(NOT(ISNUMBER($O14)),NOT(ISNUMBER($T14))),"",$O14-$T14)) | V14: =IF(NOT(ISNUMBER($S14)),"",COUNTIFS($G$7:$G$850,$G14,$S$7:$S$850,">"&$S14)+COUNTIFS($G$7:$G14,$G14,$S$7:$S14,$S14)) | W14: =IF(NOT(ISNUMBER($S14)),"",COUNTIFS($G$7:$G$850,$G14,$S$7:$S$850,"<"&$S14)+COUNTIFS($G$7:$G14,$G14,$S$7:$S14,$S14)) | X14: =IF($V14="","",$G14&"|"&$V14) | Y14: =IF($W14="","",$G14&"|"&$W14)
A15: CH0333827506 | B15: =IF($A15="","",PROPER(_xll.BDP($A15&" Corp","NAME"))) | C15: =IF($A15="","",IFERROR(INDEX(Company_desc!$B$2:$B$1144,MATCH($A15,Company_desc!$A$2:$A$1144,0)),IFERROR(INDEX(SYZ_static!$Q$2:$Q$806,MATCH($A15,SYZ_static!$A$2:$A$806,0)),""))) | D15: =IF($A15="","",IFERROR(INDEX(SYZ_static!$B$2:$B$806,MATCH($A15,SYZ_static!$A$2:$A$806,0)),"")) | E15: =IF($A15="","",_xll.BDP($A15&" Corp","INDUSTRY_SECTOR")) | F15: =IF($A15="","",PROPER(_xll.BDP($A15&" Corp","COUNTRY_FULL_NAME"))) | G15: =IF($A15="","",_xll.BDP($A15&" Corp","CRNCY")) | H15: =IF($A15="","",IFERROR(INDEX(SYZ_static!$T$2:$T$806,MATCH($A15,SYZ_static!$A$2:$A$806,0)),_xll.BDP($A15&" Corp","RTG_SP"))) | I15: =IF($A15="","",IFERROR(INDEX(SYZ_static!$S$2:$S$806,MATCH($A15,SYZ_static!$A$2:$A$806,0)),"")) | J15: =IF($A15="","",_xll.BDP($A15&" Corp","PAYMENT_RANK")) | K15: =IF($A15="","",_xll.BDP($A15&" Corp","CPN")) | L15: =IF($A15="","",_xll.BDP($A15&" Corp","MATURITY")) | M15: =IF($A15="","",IFERROR(_xll.BDP($A15&" Corp","MIN_PIECE")/1000,"")) | N15: =IF($A15="","",_xll.BDP($A15&" Corp","PX_LAST")) | O15: =IF($A15="","",_xll.BDP($A15&" Corp","YAS_BOND_YLD","YAS_YLD_FLAG=15")) | P15: =IF($A15="","",_xll.BDP($A15&" Corp","YAS_MOD_DUR")) | Q15: =IF($A15="","",_xll.BDP($A15&" Corp","YAS_OAS_SPRD")) | R15: =IF($A15="","",_xll.BDP($A15&" Corp","YAS_OAS_SPRD","SETTLE_DT",$B$2)) | S15: =IF($A15="","",IF(OR(NOT(ISNUMBER($Q15)),NOT(ISNUMBER($R15))),"",$Q15-$R15)) | T15: =IF($A15="","",_xll.BDP($A15&" Corp","YAS_BOND_YLD","YAS_YLD_FLAG=15","SETTLE_DT",$B$2)) | U15: =IF($A15="","",IF(OR(NOT(ISNUMBER($O15)),NOT(ISNUMBER($T15))),"",$O15-$T15)) | V15: =IF(NOT(ISNUMBER($S15)),"",COUNTIFS($G$7:$G$850,$G15,$S$7:$S$850,">"&$S15)+COUNTIFS($G$7:$G15,$G15,$S$7:$S15,$S15)) | W15: =IF(NOT(ISNUMBER($S15)),"",COUNTIFS($G$7:$G$850,$G15,$S$7:$S$850,"<"&$S15)+COUNTIFS($G$7:$G15,$G15,$S$7:$S15,$S15)) | X15: =IF($V15="","",$G15&"|"&$V15) | Y15: =IF($W15="","",$G15&"|"&$W15)
A16: USU8215LAA27 | B16: =IF($A16="","",PROPER(_xll.BDP($A16&" Corp","NAME"))) | C16: =IF($A16="","",IFERROR(INDEX(Company_desc!$B$2:$B$1144,MATCH($A16,Company_desc!$A$2:$A$1144,0)),IFERROR(INDEX(SYZ_static!$Q$2:$Q$806,MATCH($A16,SYZ_static!$A$2:$A$806,0)),""))) | D16: =IF($A16="","",IFERROR(INDEX(SYZ_static!$B$2:$B$806,MATCH($A16,SYZ_static!$A$2:$A$806,0)),"")) | E16: =IF($A16="","",_xll.BDP($A16&" Corp","INDUSTRY_SECTOR")) | F16: =IF($A16="","",PROPER(_xll.BDP($A16&" Corp","COUNTRY_FULL_NAME"))) | G16: =IF($A16="","",_xll.BDP($A16&" Corp","CRNCY")) | H16: =IF($A16="","",IFERROR(INDEX(SYZ_static!$T$2:$T$806,MATCH($A16,SYZ_static!$A$2:$A$806,0)),_xll.BDP($A16&" Corp","RTG_SP"))) | I16: =IF($A16="","",IFERROR(INDEX(SYZ_static!$S$2:$S$806,MATCH($A16,SYZ_static!$A$2:$A$806,0)),"")) | J16: =IF($A16="","",_xll.BDP($A16&" Corp","PAYMENT_RANK")) | K16: =IF($A16="","",_xll.BDP($A16&" Corp","CPN")) | L16: =IF($A16="","",_xll.BDP($A16&" Corp","MATURITY")) | M16: =IF($A16="","",IFERROR(_xll.BDP($A16&" Corp","MIN_PIECE")/1000,"")) | N16: =IF($A16="","",_xll.BDP($A16&" Corp","PX_LAST")) | O16: =IF($A16="","",_xll.BDP($A16&" Corp","YAS_BOND_YLD","YAS_YLD_FLAG=15")) | P16: =IF($A16="","",_xll.BDP($A16&" Corp","YAS_MOD_DUR")) | Q16: =IF($A16="","",_xll.BDP($A16&" Corp","YAS_OAS_SPRD")) | R16: =IF($A16="","",_xll.BDP($A16&" Corp","YAS_OAS_SPRD","SETTLE_DT",$B$2)) | S16: =IF($A16="","",IF(OR(NOT(ISNUMBER($Q16)),NOT(ISNUMBER($R16))),"",$Q16-$R16)) | T16: =IF($A16="","",_xll.BDP($A16&" Corp","YAS_BOND_YLD","YAS_YLD_FLAG=15","SETTLE_DT",$B$2)) | U16: =IF($A16="","",IF(OR(NOT(ISNUMBER($O16)),NOT(ISNUMBER($T16))),"",$O16-$T16)) | V16: =IF(NOT(ISNUMBER($S16)),"",COUNTIFS($G$7:$G$850,$G16,$S$7:$S$850,">"&$S16)+COUNTIFS($G$7:$G16,$G16,$S$7:$S16,$S16)) | W16: =IF(NOT(ISNUMBER($S16)),"",COUNTIFS($G$7:$G$850,$G16,$S$7:$S$850,"<"&$S16)+COUNTIFS($G$7:$G16,$G16,$S$7:$S16,$S16)) | X16: =IF($V16="","",$G16&"|"&$V16) | Y16: =IF($W16="","",$G16&"|"&$W16)
A17: FR001400QC85 | B17: =IF($A17="","",PROPER(_xll.BDP($A17&" Corp","NAME"))) | C17: =IF($A17="","",IFERROR(INDEX(Company_desc!$B$2:$B$1144,MATCH($A17,Company_desc!$A$2:$A$1144,0)),IFERROR(INDEX(SYZ_static!$Q$2:$Q$806,MATCH($A17,SYZ_static!$A$2:$A$806,0)),""))) | D17: =IF($A17="","",IFERROR(INDEX(SYZ_static!$B$2:$B$806,MATCH($A17,SYZ_static!$A$2:$A$806,0)),"")) | E17: =IF($A17="","",_xll.BDP($A17&" Corp","INDUSTRY_SECTOR")) | F17: =IF($A17="","",PROPER(_xll.BDP($A17&" Corp","COUNTRY_FULL_NAME"))) | G17: =IF($A17="","",_xll.BDP($A17&" Corp","CRNCY")) | H17: =IF($A17="","",IFERROR(INDEX(SYZ_static!$T$2:$T$806,MATCH($A17,SYZ_static!$A$2:$A$806,0)),_xll.BDP($A17&" Corp","RTG_SP"))) | I17: =IF($A17="","",IFERROR(INDEX(SYZ_static!$S$2:$S$806,MATCH($A17,SYZ_static!$A$2:$A$806,0)),"")) | J17: =IF($A17="","",_xll.BDP($A17&" Corp","PAYMENT_RANK")) | K17: =IF($A17="","",_xll.BDP($A17&" Corp","CPN")) | L17: =IF($A17="","",_xll.BDP($A17&" Corp","MATURITY")) | M17: =IF($A17="","",IFERROR(_xll.BDP($A17&" Corp","MIN_PIECE")/1000,"")) | N17: =IF($A17="","",_xll.BDP($A17&" Corp","PX_LAST")) | O17: =IF($A17="","",_xll.BDP($A17&" Corp","YAS_BOND_YLD","YAS_YLD_FLAG=15")) | P17: =IF($A17="","",_xll.BDP($A17&" Corp","YAS_MOD_DUR")) | Q17: =IF($A17="","",_xll.BDP($A17&" Corp","YAS_OAS_SPRD")) | R17: =IF($A17="","",_xll.BDP($A17&" Corp","YAS_OAS_SPRD","SETTLE_DT",$B$2)) | S17: =IF($A17="","",IF(OR(NOT(ISNUMBER($Q17)),NOT(ISNUMBER($R17))),"",$Q17-$R17)) | T17: =IF($A17="","",_xll.BDP($A17&" Corp","YAS_BOND_YLD","YAS_YLD_FLAG=15","SETTLE_DT",$B$2)) | U17: =IF($A17="","",IF(OR(NOT(ISNUMBER($O17)),NOT(ISNUMBER($T17))),"",$O17-$T17)) | V17: =IF(NOT(ISNUMBER($S17)),"",COUNTIFS($G$7:$G$850,$G17,$S$7:$S$850,">"&$S17)+COUNTIFS($G$7:$G17,$G17,$S$7:$S17,$S17)) | W17: =IF(NOT(ISNUMBER($S17)),"",COUNTIFS($G$7:$G$850,$G17,$S$7:$S$850,"<"&$S17)+COUNTIFS($G$7:$G17,$G17,$S$7:$S17,$S17)) | X17: =IF($V17="","",$G17&"|"&$V17) | Y17: =IF($W17="","",$G17&"|"&$W17)
A18: FR001400HZE3 | B18: =IF($A18="","",PROPER(_xll.BDP($A18&" Corp","NAME"))) | C18: =IF($A18="","",IFERROR(INDEX(Company_desc!$B$2:$B$1144,MATCH($A18,Company_desc!$A$2:$A$1144,0)),IFERROR(INDEX(SYZ_static!$Q$2:$Q$806,MATCH($A18,SYZ_static!$A$2:$A$806,0)),""))) | D18: =IF($A18="","",IFERROR(INDEX(SYZ_static!$B$2:$B$806,MATCH($A18,SYZ_static!$A$2:$A$806,0)),"")) | E18: =IF($A18="","",_xll.BDP($A18&" Corp","INDUSTRY_SECTOR")) | F18: =IF($A18="","",PROPER(_xll.BDP($A18&" Corp","COUNTRY_FULL_NAME"))) | G18: =IF($A18="","",_xll.BDP($A18&" Corp","CRNCY")) | H18: =IF($A18="","",IFERROR(INDEX(SYZ_static!$T$2:$T$806,MATCH($A18,SYZ_static!$A$2:$A$806,0)),_xll.BDP($A18&" Corp","RTG_SP"))) | I18: =IF($A18="","",IFERROR(INDEX(SYZ_static!$S$2:$S$806,MATCH($A18,SYZ_static!$A$2:$A$806,0)),"")) | J18: =IF($A18="","",_xll.BDP($A18&" Corp","PAYMENT_RANK")) | K18: =IF($A18="","",_xll.BDP($A18&" Corp","CPN")) | L18: =IF($A18="","",_xll.BDP($A18&" Corp","MATURITY")) | M18: =IF($A18="","",IFERROR(_xll.BDP($A18&" Corp","MIN_PIECE")/1000,"")) | N18: =IF($A18="","",_xll.BDP($A18&" Corp","PX_LAST")) | O18: =IF($A18="","",_xll.BDP($A18&" Corp","YAS_BOND_YLD","YAS_YLD_FLAG=15")) | P18: =IF($A18="","",_xll.BDP($A18&" Corp","YAS_MOD_DUR")) | Q18: =IF($A18="","",_xll.BDP($A18&" Corp","YAS_OAS_SPRD")) | R18: =IF($A18="","",_xll.BDP($A18&" Corp","YAS_OAS_SPRD","SETTLE_DT",$B$2)) | S18: =IF($A18="","",IF(OR(NOT(ISNUMBER($Q18)),NOT(ISNUMBER($R18))),"",$Q18-$R18)) | T18: =IF($A18="","",_xll.BDP($A18&" Corp","YAS_BOND_YLD","YAS_YLD_FLAG=15","SETTLE_DT",$B$2)) | U18: =IF($A18="","",IF(OR(NOT(ISNUMBER($O18)),NOT(ISNUMBER($T18))),"",$O18-$T18)) | V18: =IF(NOT(ISNUMBER($S18)),"",COUNTIFS($G$7:$G$850,$G18,$S$7:$S$850,">"&$S18)+COUNTIFS($G$7:$G18,$G18,$S$7:$S18,$S18)) | W18: =IF(NOT(ISNUMBER($S18)),"",COUNTIFS($G$7:$G$850,$G18,$S$7:$S$850,"<"&$S18)+COUNTIFS($G$7:$G18,$G18,$S$7:$S18,$S18)) | X18: =IF($V18="","",$G18&"|"&$V18) | Y18: =IF($W18="","",$G18&"|"&$W18)
... A769: US04636NAR44 | B769: =IF($A769="","",PROPER(_xll.BDP($A769&" Corp","NAME"))) | C769: =IF($A769="","",IFERROR(INDEX(Company_desc!$B$2:$B$1144,MATCH($A769,Company_desc!$A$2:$A$1144,0)),IFERROR(INDEX(SYZ_static!$Q$2:$Q$806,MATCH($A769,SYZ_static!$A$2:$A$806,0)),""))) | D769: =IF($A769="","",IFERROR(INDEX(SYZ_static!$B$2:$B$806,MATCH($A769,SYZ_static!$A$2:$A$806,0)),"")) | E769: =IF($A769="","",_xll.BDP($A769&" Corp","INDUSTRY_SECTOR")) | F769: =IF($A769="","",PROPER(_xll.BDP($A769&" Corp","COUNTRY_FULL_NAME"))) | G769: =IF($A769="","",_xll.BDP($A769&" Corp","CRNCY")) | H769: =IF($A769="","",IFERROR(INDEX(SYZ_static!$T$2:$T$806,MATCH($A769,SYZ_static!$A$2:$A$806,0)),_xll.BDP($A769&" Corp","RTG_SP"))) | I769: =IF($A769="","",IFERROR(INDEX(SYZ_static!$S$2:$S$806,MATCH($A769,SYZ_static!$A$2:$A$806,0)),"")) | J769: =IF($A769="","",_xll.BDP($A769&" Corp","PAYMENT_RANK")) | K769: =IF($A769="","",_xll.BDP($A769&" Corp","CPN")) | L769: =IF($A769="","",_xll.BDP($A769&" Corp","MATURITY")) | M769: =IF($A769="","",IFERROR(_xll.BDP($A769&" Corp","MIN_PIECE")/1000,"")) | N769: =IF($A769="","",_xll.BDP($A769&" Corp","PX_LAST")) | O769: =IF($A769="","",_xll.BDP($A769&" Corp","YAS_BOND_YLD","YAS_YLD_FLAG=15")) | P769: =IF($A769="","",_xll.BDP($A769&" Corp","YAS_MOD_DUR")) | Q769: =IF($A769="","",_xll.BDP($A769&" Corp","YAS_OAS_SPRD")) | R769: =IF($A769="","",_xll.BDP($A769&" Corp","YAS_OAS_SPRD","SETTLE_DT",$B$2)) | S769: =IF($A769="","",IF(OR(NOT(ISNUMBER($Q769)),NOT(ISNUMBER($R769))),"",$Q769-$R769)) | T769: =IF($A769="","",_xll.BDP($A769&" Corp","YAS_BOND_YLD","YAS_YLD_FLAG=15","SETTLE_DT",$B$2)) | U769: =IF($A769="","",IF(OR(NOT(ISNUMBER($O769)),NOT(ISNUMBER($T769))),"",$O769-$T769)) | V769: =IF(NOT(ISNUMBER($S769)),"",COUNTIFS($G$7:$G$850,$G769,$S$7:$S$850,">"&$S769)+COUNTIFS($G$7:$G769,$G769,$S$7:$S769,$S769)) | W769: =IF(NOT(ISNUMBER($S769)),"",COUNTIFS($G$7:$G$850,$G769,$S$7:$S$850,"<"&$S769)+COUNTIFS($G$7:$G769,$G769,$S$7:$S769,$S769)) | X769: =IF($V769="","",$G769&"|"&$V769) | Y769: =IF($W769="","",$G769&"|"&$W769)
B770: =IF($A770="","",PROPER(_xll.BDP($A770&" Corp","NAME"))) | C770: =IF($A770="","",IFERROR(INDEX(Company_desc!$B$2:$B$1144,MATCH($A770,Company_desc!$A$2:$A$1144,0)),IFERROR(INDEX(SYZ_static!$Q$2:$Q$806,MATCH($A770,SYZ_static!$A$2:$A$806,0)),""))) | D770: =IF($A770="","",IFERROR(INDEX(SYZ_static!$B$2:$B$806,MATCH($A770,SYZ_static!$A$2:$A$806,0)),"")) | E770: =IF($A770="","",_xll.BDP($A770&" Corp","INDUSTRY_SECTOR")) | F770: =IF($A770="","",PROPER(_xll.BDP($A770&" Corp","COUNTRY_FULL_NAME"))) | G770: =IF($A770="","",_xll.BDP($A770&" Corp","CRNCY")) | H770: =IF($A770="","",IFERROR(INDEX(SYZ_static!$T$2:$T$806,MATCH($A770,SYZ_static!$A$2:$A$806,0)),_xll.BDP($A770&" Corp","RTG_SP"))) | I770: =IF($A770="","",IFERROR(INDEX(SYZ_static!$S$2:$S$806,MATCH($A770,SYZ_static!$A$2:$A$806,0)),"")) | J770: =IF($A770="","",_xll.BDP($A770&" Corp","PAYMENT_RANK")) | K770: =IF($A770="","",_xll.BDP($A770&" Corp","CPN")) | L770: =IF($A770="","",_xll.BDP($A770&" Corp","MATURITY")) | M770: =IF($A770="","",IFERROR(_xll.BDP($A770&" Corp","MIN_PIECE")/1000,"")) | N770: =IF($A770="","",_xll.BDP($A770&" Corp","PX_LAST")) | O770: =IF($A770="","",_xll.BDP($A770&" Corp","YAS_BOND_YLD","YAS_YLD_FLAG=15")) | P770: =IF($A770="","",_xll.BDP($A770&" Corp","YAS_MOD_DUR")) | Q770: =IF($A770="","",_xll.BDP($A770&" Corp","YAS_OAS_SPRD")) | R770: =IF($A770="","",_xll.BDP($A770&" Corp","YAS_OAS_SPRD","SETTLE_DT",$B$2)) | S770: =IF($A770="","",IF(OR(NOT(ISNUMBER($Q770)),NOT(ISNUMBER($R770))),"",$Q770-$R770)) | T770: =IF($A770="","",_xll.BDP($A770&" Corp","YAS_BOND_YLD","YAS_YLD_FLAG=15","SETTLE_DT",$B$2)) | U770: =IF($A770="","",IF(OR(NOT(ISNUMBER($O770)),NOT(ISNUMBER($T770))),"",$O770-$T770)) | V770: =IF(NOT(ISNUMBER($S770)),"",COUNTIFS($G$7:$G$850,$G770,$S$7:$S$850,">"&$S770)+COUNTIFS($G$7:$G770,$G770,$S$7:$S770,$S770)) | W770: =IF(NOT(ISNUMBER($S770)),"",COUNTIFS($G$7:$G$850,$G770,$S$7:$S$850,"<"&$S770)+COUNTIFS($G$7:$G770,$G770,$S$7:$S770,$S770)) | X770: =IF($V770="","",$G770&"|"&$V770) | Y770: =IF($W770="","",$G770&"|"&$W770)
B771: =IF($A771="","",PROPER(_xll.BDP($A771&" Corp","NAME"))) | C771: =IF($A771="","",IFERROR(INDEX(Company_desc!$B$2:$B$1144,MATCH($A771,Company_desc!$A$2:$A$1144,0)),IFERROR(INDEX(SYZ_static!$Q$2:$Q$806,MATCH($A771,SYZ_static!$A$2:$A$806,0)),""))) | D771: =IF($A771="","",IFERROR(INDEX(SYZ_static!$B$2:$B$806,MATCH($A771,SYZ_static!$A$2:$A$806,0)),"")) | E771: =IF($A771="","",_xll.BDP($A771&" Corp","INDUSTRY_SECTOR")) | F771: =IF($A771="","",PROPER(_xll.BDP($A771&" Corp","COUNTRY_FULL_NAME"))) | G771: =IF($A771="","",_xll.BDP($A771&" Corp","CRNCY")) | H771: =IF($A771="","",IFERROR(INDEX(SYZ_static!$T$2:$T$806,MATCH($A771,SYZ_static!$A$2:$A$806,0)),_xll.BDP($A771&" Corp","RTG_SP"))) | I771: =IF($A771="","",IFERROR(INDEX(SYZ_static!$S$2:$S$806,MATCH($A771,SYZ_static!$A$2:$A$806,0)),"")) | J771: =IF($A771="","",_xll.BDP($A771&" Corp","PAYMENT_RANK")) | K771: =IF($A771="","",_xll.BDP($A771&" Corp","CPN")) | L771: =IF($A771="","",_xll.BDP($A771&" Corp","MATURITY")) | M771: =IF($A771="","",IFERROR(_xll.BDP($A771&" Corp","MIN_PIECE")/1000,"")) | N771: =IF($A771="","",_xll.BDP($A771&" Corp","PX_LAST")) | O771: =IF($A771="","",_xll.BDP($A771&" Corp","YAS_BOND_YLD","YAS_YLD_FLAG=15")) | P771: =IF($A771="","",_xll.BDP($A771&" Corp","YAS_MOD_DUR")) | Q771: =IF($A771="","",_xll.BDP($A771&" Corp","YAS_OAS_SPRD")) | R771: =IF($A771="","",_xll.BDP($A771&" Corp","YAS_OAS_SPRD","SETTLE_DT",$B$2)) | S771: =IF($A771="","",IF(OR(NOT(ISNUMBER($Q771)),NOT(ISNUMBER($R771))),"",$Q771-$R771)) | T771: =IF($A771="","",_xll.BDP($A771&" Corp","YAS_BOND_YLD","YAS_YLD_FLAG=15","SETTLE_DT",$B$2)) | U771: =IF($A771="","",IF(OR(NOT(ISNUMBER($O771)),NOT(ISNUMBER($T771))),"",$O771-$T771)) | V771: =IF(NOT(ISNUMBER($S771)),"",COUNTIFS($G$7:$G$850,$G771,$S$7:$S$850,">"&$S771)+COUNTIFS($G$7:$G771,$G771,$S$7:$S771,$S771)) | W771: =IF(NOT(ISNUMBER($S771)),"",COUNTIFS($G$7:$G$850,$G771,$S$7:$S$850,"<"&$S771)+COUNTIFS($G$7:$G771,$G771,$S$7:$S771,$S771)) | X771: =IF($V771="","",$G771&"|"&$V771) | Y771: =IF($W771="","",$G771&"|"&$W771)
B772: =IF($A772="","",PROPER(_xll.BDP($A772&" Corp","NAME"))) | C772: =IF($A772="","",IFERROR(INDEX(Company_desc!$B$2:$B$1144,MATCH($A772,Company_desc!$A$2:$A$1144,0)),IFERROR(INDEX(SYZ_static!$Q$2:$Q$806,MATCH($A772,SYZ_static!$A$2:$A$806,0)),""))) | D772: =IF($A772="","",IFERROR(INDEX(SYZ_static!$B$2:$B$806,MATCH($A772,SYZ_static!$A$2:$A$806,0)),"")) | E772: =IF($A772="","",_xll.BDP($A772&" Corp","INDUSTRY_SECTOR")) | F772: =IF($A772="","",PROPER(_xll.BDP($A772&" Corp","COUNTRY_FULL_NAME"))) | G772: =IF($A772="","",_xll.BDP($A772&" Corp","CRNCY")) | H772: =IF($A772="","",IFERROR(INDEX(SYZ_static!$T$2:$T$806,MATCH($A772,SYZ_static!$A$2:$A$806,0)),_xll.BDP($A772&" Corp","RTG_SP"))) | I772: =IF($A772="","",IFERROR(INDEX(SYZ_static!$S$2:$S$806,MATCH($A772,SYZ_static!$A$2:$A$806,0)),"")) | J772: =IF($A772="","",_xll.BDP($A772&" Corp","PAYMENT_RANK")) | K772: =IF($A772="","",_xll.BDP($A772&" Corp","CPN")) | L772: =IF($A772="","",_xll.BDP($A772&" Corp","MATURITY")) | M772: =IF($A772="","",IFERROR(_xll.BDP($A772&" Corp","MIN_PIECE")/1000,"")) | N772: =IF($A772="","",_xll.BDP($A772&" Corp","PX_LAST")) | O772: =IF($A772="","",_xll.BDP($A772&" Corp","YAS_BOND_YLD","YAS_YLD_FLAG=15")) | P772: =IF($A772="","",_xll.BDP($A772&" Corp","YAS_MOD_DUR")) | Q772: =IF($A772="","",_xll.BDP($A772&" Corp","YAS_OAS_SPRD")) | R772: =IF($A772="","",_xll.BDP($A772&" Corp","YAS_OAS_SPRD","SETTLE_DT",$B$2)) | S772: =IF($A772="","",IF(OR(NOT(ISNUMBER($Q772)),NOT(ISNUMBER($R772))),"",$Q772-$R772)) | T772: =IF($A772="","",_xll.BDP($A772&" Corp","YAS_BOND_YLD","YAS_YLD_FLAG=15","SETTLE_DT",$B$2)) | U772: =IF($A772="","",IF(OR(NOT(ISNUMBER($O772)),NOT(ISNUMBER($T772))),"",$O772-$T772)) | V772: =IF(NOT(ISNUMBER($S772)),"",COUNTIFS($G$7:$G$850,$G772,$S$7:$S$850,">"&$S772)+COUNTIFS($G$7:$G772,$G772,$S$7:$S772,$S772)) | W772: =IF(NOT(ISNUMBER($S772)),"",COUNTIFS($G$7:$G$850,$G772,$S$7:$S$850,"<"&$S772)+COUNTIFS($G$7:$G772,$G772,$S$7:$S772,$S772)) | X772: =IF($V772="","",$G772&"|"&$V772) | Y772: =IF($W772="","",$G772&"|"&$W772)
B773: =IF($A773="","",PROPER(_xll.BDP($A773&" Corp","NAME"))) | C773: =IF($A773="","",IFERROR(INDEX(Company_desc!$B$2:$B$1144,MATCH($A773,Company_desc!$A$2:$A$1144,0)),IFERROR(INDEX(SYZ_static!$Q$2:$Q$806,MATCH($A773,SYZ_static!$A$2:$A$806,0)),""))) | D773: =IF($A773="","",IFERROR(INDEX(SYZ_static!$B$2:$B$806,MATCH($A773,SYZ_static!$A$2:$A$806,0)),"")) | E773: =IF($A773="","",_xll.BDP($A773&" Corp","INDUSTRY_SECTOR")) | F773: =IF($A773="","",PROPER(_xll.BDP($A773&" Corp","COUNTRY_FULL_NAME"))) | G773: =IF($A773="","",_xll.BDP($A773&" Corp","CRNCY")) | H773: =IF($A773="","",IFERROR(INDEX(SYZ_static!$T$2:$T$806,MATCH($A773,SYZ_static!$A$2:$A$806,0)),_xll.BDP($A773&" Corp","RTG_SP"))) | I773: =IF($A773="","",IFERROR(INDEX(SYZ_static!$S$2:$S$806,MATCH($A773,SYZ_static!$A$2:$A$806,0)),"")) | J773: =IF($A773="","",_xll.BDP($A773&" Corp","PAYMENT_RANK")) | K773: =IF($A773="","",_xll.BDP($A773&" Corp","CPN")) | L773: =IF($A773="","",_xll.BDP($A773&" Corp","MATURITY")) | M773: =IF($A773="","",IFERROR(_xll.BDP($A773&" Corp","MIN_PIECE")/1000,"")) | N773: =IF($A773="","",_xll.BDP($A773&" Corp","PX_LAST")) | O773: =IF($A773="","",_xll.BDP($A773&" Corp","YAS_BOND_YLD","YAS_YLD_FLAG=15")) | P773: =IF($A773="","",_xll.BDP($A773&" Corp","YAS_MOD_DUR")) | Q773: =IF($A773="","",_xll.BDP($A773&" Corp","YAS_OAS_SPRD")) | R773: =IF($A773="","",_xll.BDP($A773&" Corp","YAS_OAS_SPRD","SETTLE_DT",$B$2)) | S773: =IF($A773="","",IF(OR(NOT(ISNUMBER($Q773)),NOT(ISNUMBER($R773))),"",$Q773-$R773)) | T773: =IF($A773="","",_xll.BDP($A773&" Corp","YAS_BOND_YLD","YAS_YLD_FLAG=15","SETTLE_DT",$B$2)) | U773: =IF($A773="","",IF(OR(NOT(ISNUMBER($O773)),NOT(ISNUMBER($T773))),"",$O773-$T773)) | V773: =IF(NOT(ISNUMBER($S773)),"",COUNTIFS($G$7:$G$850,$G773,$S$7:$S$850,">"&$S773)+COUNTIFS($G$7:$G773,$G773,$S$7:$S773,$S773)) | W773: =IF(NOT(ISNUMBER($S773)),"",COUNTIFS($G$7:$G$850,$G773,$S$7:$S$850,"<"&$S773)+COUNTIFS($G$7:$G773,$G773,$S$7:$S773,$S773)) | X773: =IF($V773="","",$G773&"|"&$V773) | Y773: =IF($W773="","",$G773&"|"&$W773)
B774: =IF($A774="","",PROPER(_xll.BDP($A774&" Corp","NAME"))) | C774: =IF($A774="","",IFERROR(INDEX(Company_desc!$B$2:$B$1144,MATCH($A774,Company_desc!$A$2:$A$1144,0)),IFERROR(INDEX(SYZ_static!$Q$2:$Q$806,MATCH($A774,SYZ_static!$A$2:$A$806,0)),""))) | D774: =IF($A774="","",IFERROR(INDEX(SYZ_static!$B$2:$B$806,MATCH($A774,SYZ_static!$A$2:$A$806,0)),"")) | E774: =IF($A774="","",_xll.BDP($A774&" Corp","INDUSTRY_SECTOR")) | F774: =IF($A774="","",PROPER(_xll.BDP($A774&" Corp","COUNTRY_FULL_NAME"))) | G774: =IF($A774="","",_xll.BDP($A774&" Corp","CRNCY")) | H774: =IF($A774="","",IFERROR(INDEX(SYZ_static!$T$2:$T$806,MATCH($A774,SYZ_static!$A$2:$A$806,0)),_xll.BDP($A774&" Corp","RTG_SP"))) | I774: =IF($A774="","",IFERROR(INDEX(SYZ_static!$S$2:$S$806,MATCH($A774,SYZ_static!$A$2:$A$806,0)),"")) | J774: =IF($A774="","",_xll.BDP($A774&" Corp","PAYMENT_RANK")) | K774: =IF($A774="","",_xll.BDP($A774&" Corp","CPN")) | L774: =IF($A774="","",_xll.BDP($A774&" Corp","MATURITY")) | M774: =IF($A774="","",IFERROR(_xll.BDP($A774&" Corp","MIN_PIECE")/1000,"")) | N774: =IF($A774="","",_xll.BDP($A774&" Corp","PX_LAST")) | O774: =IF($A774="","",_xll.BDP($A774&" Corp","YAS_BOND_YLD","YAS_YLD_FLAG=15")) | P774: =IF($A774="","",_xll.BDP($A774&" Corp","YAS_MOD_DUR")) | Q774: =IF($A774="","",_xll.BDP($A774&" Corp","YAS_OAS_SPRD")) | R774: =IF($A774="","",_xll.BDP($A774&" Corp","YAS_OAS_SPRD","SETTLE_DT",$B$2)) | S774: =IF($A774="","",IF(OR(NOT(ISNUMBER($Q774)),NOT(ISNUMBER($R774))),"",$Q774-$R774)) | T774: =IF($A774="","",_xll.BDP($A774&" Corp","YAS_BOND_YLD","YAS_YLD_FLAG=15","SETTLE_DT",$B$2)) | U774: =IF($A774="","",IF(OR(NOT(ISNUMBER($O774)),NOT(ISNUMBER($T774))),"",$O774-$T774)) | V774: =IF(NOT(ISNUMBER($S774)),"",COUNTIFS($G$7:$G$850,$G774,$S$7:$S$850,">"&$S774)+COUNTIFS($G$7:$G774,$G774,$S$7:$S774,$S774)) | W774: =IF(NOT(ISNUMBER($S774)),"",COUNTIFS($G$7:$G$850,$G774,$S$7:$S$850,"<"&$S774)+COUNTIFS($G$7:$G774,$G774,$S$7:$S774,$S774)) | X774: =IF($V774="","",$G774&"|"&$V774) | Y774: =IF($W774="","",$G774&"|"&$W774)
B775: =IF($A775="","",PROPER(_xll.BDP($A775&" Corp","NAME"))) | C775: =IF($A775="","",IFERROR(INDEX(Company_desc!$B$2:$B$1144,MATCH($A775,Company_desc!$A$2:$A$1144,0)),IFERROR(INDEX(SYZ_static!$Q$2:$Q$806,MATCH($A775,SYZ_static!$A$2:$A$806,0)),""))) | D775: =IF($A775="","",IFERROR(INDEX(SYZ_static!$B$2:$B$806,MATCH($A775,SYZ_static!$A$2:$A$806,0)),"")) | E775: =IF($A775="","",_xll.BDP($A775&" Corp","INDUSTRY_SECTOR")) | F775: =IF($A775="","",PROPER(_xll.BDP($A775&" Corp","COUNTRY_FULL_NAME"))) | G775: =IF($A775="","",_xll.BDP($A775&" Corp","CRNCY")) | H775: =IF($A775="","",IFERROR(INDEX(SYZ_static!$T$2:$T$806,MATCH($A775,SYZ_static!$A$2:$A$806,0)),_xll.BDP($A775&" Corp","RTG_SP"))) | I775: =IF($A775="","",IFERROR(INDEX(SYZ_static!$S$2:$S$806,MATCH($A775,SYZ_static!$A$2:$A$806,0)),"")) | J775: =IF($A775="","",_xll.BDP($A775&" Corp","PAYMENT_RANK")) | K775: =IF($A775="","",_xll.BDP($A775&" Corp","CPN")) | L775: =IF($A775="","",_xll.BDP($A775&" Corp","MATURITY")) | M775: =IF($A775="","",IFERROR(_xll.BDP($A775&" Corp","MIN_PIECE")/1000,"")) | N775: =IF($A775="","",_xll.BDP($A775&" Corp","PX_LAST")) | O775: =IF($A775="","",_xll.BDP($A775&" Corp","YAS_BOND_YLD","YAS_YLD_FLAG=15")) | P775: =IF($A775="","",_xll.BDP($A775&" Corp","YAS_MOD_DUR")) | Q775: =IF($A775="","",_xll.BDP($A775&" Corp","YAS_OAS_SPRD")) | R775: =IF($A775="","",_xll.BDP($A775&" Corp","YAS_OAS_SPRD","SETTLE_DT",$B$2)) | S775: =IF($A775="","",IF(OR(NOT(ISNUMBER($Q775)),NOT(ISNUMBER($R775))),"",$Q775-$R775)) | T775: =IF($A775="","",_xll.BDP($A775&" Corp","YAS_BOND_YLD","YAS_YLD_FLAG=15","SETTLE_DT",$B$2)) | U775: =IF($A775="","",IF(OR(NOT(ISNUMBER($O775)),NOT(ISNUMBER($T775))),"",$O775-$T775)) | V775: =IF(NOT(ISNUMBER($S775)),"",COUNTIFS($G$7:$G$850,$G775,$S$7:$S$850,">"&$S775)+COUNTIFS($G$7:$G775,$G775,$S$7:$S775,$S775)) | W775: =IF(NOT(ISNUMBER($S775)),"",COUNTIFS($G$7:$G$850,$G775,$S$7:$S$850,"<"&$S775)+COUNTIFS($G$7:$G775,$G775,$S$7:$S775,$S775)) | X775: =IF($V775="","",$G775&"|"&$V775) | Y775: =IF($W775="","",$G775&"|"&$W775)
B776: =IF($A776="","",PROPER(_xll.BDP($A776&" Corp","NAME"))) | C776: =IF($A776="","",IFERROR(INDEX(Company_desc!$B$2:$B$1144,MATCH($A776,Company_desc!$A$2:$A$1144,0)),IFERROR(INDEX(SYZ_static!$Q$2:$Q$806,MATCH($A776,SYZ_static!$A$2:$A$806,0)),""))) | D776: =IF($A776="","",IFERROR(INDEX(SYZ_static!$B$2:$B$806,MATCH($A776,SYZ_static!$A$2:$A$806,0)),"")) | E776: =IF($A776="","",_xll.BDP($A776&" Corp","INDUSTRY_SECTOR")) | F776: =IF($A776="","",PROPER(_xll.BDP($A776&" Corp","COUNTRY_FULL_NAME"))) | G776: =IF($A776="","",_xll.BDP($A776&" Corp","CRNCY")) | H776: =IF($A776="","",IFERROR(INDEX(SYZ_static!$T$2:$T$806,MATCH($A776,SYZ_static!$A$2:$A$806,0)),_xll.BDP($A776&" Corp","RTG_SP"))) | I776: =IF($A776="","",IFERROR(INDEX(SYZ_static!$S$2:$S$806,MATCH($A776,SYZ_static!$A$2:$A$806,0)),"")) | J776: =IF($A776="","",_xll.BDP($A776&" Corp","PAYMENT_RANK")) | K776: =IF($A776="","",_xll.BDP($A776&" Corp","CPN")) | L776: =IF($A776="","",_xll.BDP($A776&" Corp","MATURITY")) | M776: =IF($A776="","",IFERROR(_xll.BDP($A776&" Corp","MIN_PIECE")/1000,"")) | N776: =IF($A776="","",_xll.BDP($A776&" Corp","PX_LAST")) | O776: =IF($A776="","",_xll.BDP($A776&" Corp","YAS_BOND_YLD","YAS_YLD_FLAG=15")) | P776: =IF($A776="","",_xll.BDP($A776&" Corp","YAS_MOD_DUR")) | Q776: =IF($A776="","",_xll.BDP($A776&" Corp","YAS_OAS_SPRD")) | R776: =IF($A776="","",_xll.BDP($A776&" Corp","YAS_OAS_SPRD","SETTLE_DT",$B$2)) | S776: =IF($A776="","",IF(OR(NOT(ISNUMBER($Q776)),NOT(ISNUMBER($R776))),"",$Q776-$R776)) | T776: =IF($A776="","",_xll.BDP($A776&" Corp","YAS_BOND_YLD","YAS_YLD_FLAG=15","SETTLE_DT",$B$2)) | U776: =IF($A776="","",IF(OR(NOT(ISNUMBER($O776)),NOT(ISNUMBER($T776))),"",$O776-$T776)) | V776: =IF(NOT(ISNUMBER($S776)),"",COUNTIFS($G$7:$G$850,$G776,$S$7:$S$850,">"&$S776)+COUNTIFS($G$7:$G776,$G776,$S$7:$S776,$S776)) | W776: =IF(NOT(ISNUMBER($S776)),"",COUNTIFS($G$7:$G$850,$G776,$S$7:$S$850,"<"&$S776)+COUNTIFS($G$7:$G776,$G776,$S$7:$S776,$S776)) | X776: =IF($V776="","",$G776&"|"&$V776) | Y776: =IF($W776="","",$G776&"|"&$W776)
B777: =IF($A777="","",PROPER(_xll.BDP($A777&" Corp","NAME"))) | C777: =IF($A777="","",IFERROR(INDEX(Company_desc!$B$2:$B$1144,MATCH($A777,Company_desc!$A$2:$A$1144,0)),IFERROR(INDEX(SYZ_static!$Q$2:$Q$806,MATCH($A777,SYZ_static!$A$2:$A$806,0)),""))) | D777: =IF($A777="","",IFERROR(INDEX(SYZ_static!$B$2:$B$806,MATCH($A777,SYZ_static!$A$2:$A$806,0)),"")) | E777: =IF($A777="","",_xll.BDP($A777&" Corp","INDUSTRY_SECTOR")) | F777: =IF($A777="","",PROPER(_xll.BDP($A777&" Corp","COUNTRY_FULL_NAME"))) | G777: =IF($A777="","",_xll.BDP($A777&" Corp","CRNCY")) | H777: =IF($A777="","",IFERROR(INDEX(SYZ_static!$T$2:$T$806,MATCH($A777,SYZ_static!$A$2:$A$806,0)),_xll.BDP($A777&" Corp","RTG_SP"))) | I777: =IF($A777="","",IFERROR(INDEX(SYZ_static!$S$2:$S$806,MATCH($A777,SYZ_static!$A$2:$A$806,0)),"")) | J777: =IF($A777="","",_xll.BDP($A777&" Corp","PAYMENT_RANK")) | K777: =IF($A777="","",_xll.BDP($A777&" Corp","CPN")) | L777: =IF($A777="","",_xll.BDP($A777&" Corp","MATURITY")) | M777: =IF($A777="","",IFERROR(_xll.BDP($A777&" Corp","MIN_PIECE")/1000,"")) | N777: =IF($A777="","",_xll.BDP($A777&" Corp","PX_LAST")) | O777: =IF($A777="","",_xll.BDP($A777&" Corp","YAS_BOND_YLD","YAS_YLD_FLAG=15")) | P777: =IF($A777="","",_xll.BDP($A777&" Corp","YAS_MOD_DUR")) | Q777: =IF($A777="","",_xll.BDP($A777&" Corp","YAS_OAS_SPRD")) | R777: =IF($A777="","",_xll.BDP($A777&" Corp","YAS_OAS_SPRD","SETTLE_DT",$B$2)) | S777: =IF($A777="","",IF(OR(NOT(ISNUMBER($Q777)),NOT(ISNUMBER($R777))),"",$Q777-$R777)) | T777: =IF($A777="","",_xll.BDP($A777&" Corp","YAS_BOND_YLD","YAS_YLD_FLAG=15","SETTLE_DT",$B$2)) | U777: =IF($A777="","",IF(OR(NOT(ISNUMBER($O777)),NOT(ISNUMBER($T777))),"",$O777-$T777)) | V777: =IF(NOT(ISNUMBER($S777)),"",COUNTIFS($G$7:$G$850,$G777,$S$7:$S$850,">"&$S777)+COUNTIFS($G$7:$G777,$G777,$S$7:$S777,$S777)) | W777: =IF(NOT(ISNUMBER($S777)),"",COUNTIFS($G$7:$G$850,$G777,$S$7:$S$850,"<"&$S777)+COUNTIFS($G$7:$G777,$G777,$S$7:$S777,$S777)) | X777: =IF($V777="","",$G777&"|"&$V777) | Y777: =IF($W777="","",$G777&"|"&$W777)
B778: =IF($A778="","",PROPER(_xll.BDP($A778&" Corp","NAME"))) | C778: =IF($A778="","",IFERROR(INDEX(Company_desc!$B$2:$B$1144,MATCH($A778,Company_desc!$A$2:$A$1144,0)),IFERROR(INDEX(SYZ_static!$Q$2:$Q$806,MATCH($A778,SYZ_static!$A$2:$A$806,0)),""))) | D778: =IF($A778="","",IFERROR(INDEX(SYZ_static!$B$2:$B$806,MATCH($A778,SYZ_static!$A$2:$A$806,0)),"")) | E778: =IF($A778="","",_xll.BDP($A778&" Corp","INDUSTRY_SECTOR")) | F778: =IF($A778="","",PROPER(_xll.BDP($A778&" Corp","COUNTRY_FULL_NAME"))) | G778: =IF($A778="","",_xll.BDP($A778&" Corp","CRNCY")) | H778: =IF($A778="","",IFERROR(INDEX(SYZ_static!$T$2:$T$806,MATCH($A778,SYZ_static!$A$2:$A$806,0)),_xll.BDP($A778&" Corp","RTG_SP"))) | I778: =IF($A778="","",IFERROR(INDEX(SYZ_static!$S$2:$S$806,MATCH($A778,SYZ_static!$A$2:$A$806,0)),"")) | J778: =IF($A778="","",_xll.BDP($A778&" Corp","PAYMENT_RANK")) | K778: =IF($A778="","",_xll.BDP($A778&" Corp","CPN")) | L778: =IF($A778="","",_xll.BDP($A778&" Corp","MATURITY")) | M778: =IF($A778="","",IFERROR(_xll.BDP($A778&" Corp","MIN_PIECE")/1000,"")) | N778: =IF($A778="","",_xll.BDP($A778&" Corp","PX_LAST")) | O778: =IF($A778="","",_xll.BDP($A778&" Corp","YAS_BOND_YLD","YAS_YLD_FLAG=15")) | P778: =IF($A778="","",_xll.BDP($A778&" Corp","YAS_MOD_DUR")) | Q778: =IF($A778="","",_xll.BDP($A778&" Corp","YAS_OAS_SPRD")) | R778: =IF($A778="","",_xll.BDP($A778&" Corp","YAS_OAS_SPRD","SETTLE_DT",$B$2)) | S778: =IF($A778="","",IF(OR(NOT(ISNUMBER($Q778)),NOT(ISNUMBER($R778))),"",$Q778-$R778)) | T778: =IF($A778="","",_xll.BDP($A778&" Corp","YAS_BOND_YLD","YAS_YLD_FLAG=15","SETTLE_DT",$B$2)) | U778: =IF($A778="","",IF(OR(NOT(ISNUMBER($O778)),NOT(ISNUMBER($T778))),"",$O778-$T778)) | V778: =IF(NOT(ISNUMBER($S778)),"",COUNTIFS($G$7:$G$850,$G778,$S$7:$S$850,">"&$S778)+COUNTIFS($G$7:$G778,$G778,$S$7:$S778,$S778)) | W778: =IF(NOT(ISNUMBER($S778)),"",COUNTIFS($G$7:$G$850,$G778,$S$7:$S$850,"<"&$S778)+COUNTIFS($G$7:$G778,$G778,$S$7:$S778,$S778)) | X778: =IF($V778="","",$G778&"|"&$V778) | Y778: =IF($W778="","",$G778&"|"&$W778)
B779: =IF($A779="","",PROPER(_xll.BDP($A779&" Corp","NAME"))) | C779: =IF($A779="","",IFERROR(INDEX(Company_desc!$B$2:$B$1144,MATCH($A779,Company_desc!$A$2:$A$1144,0)),IFERROR(INDEX(SYZ_static!$Q$2:$Q$806,MATCH($A779,SYZ_static!$A$2:$A$806,0)),""))) | D779: =IF($A779="","",IFERROR(INDEX(SYZ_static!$B$2:$B$806,MATCH($A779,SYZ_static!$A$2:$A$806,0)),"")) | E779: =IF($A779="","",_xll.BDP($A779&" Corp","INDUSTRY_SECTOR")) | F779: =IF($A779="","",PROPER(_xll.BDP($A779&" Corp","COUNTRY_FULL_NAME"))) | G779: =IF($A779="","",_xll.BDP($A779&" Corp","CRNCY")) | H779: =IF($A779="","",IFERROR(INDEX(SYZ_static!$T$2:$T$806,MATCH($A779,SYZ_static!$A$2:$A$806,0)),_xll.BDP($A779&" Corp","RTG_SP"))) | I779: =IF($A779="","",IFERROR(INDEX(SYZ_static!$S$2:$S$806,MATCH($A779,SYZ_static!$A$2:$A$806,0)),"")) | J779: =IF($A779="","",_xll.BDP($A779&" Corp","PAYMENT_RANK")) | K779: =IF($A779="","",_xll.BDP($A779&" Corp","CPN")) | L779: =IF($A779="","",_xll.BDP($A779&" Corp","MATURITY")) | M779: =IF($A779="","",IFERROR(_xll.BDP($A779&" Corp","MIN_PIECE")/1000,"")) | N779: =IF($A779="","",_xll.BDP($A779&" Corp","PX_LAST")) | O779: =IF($A779="","",_xll.BDP($A779&" Corp","YAS_BOND_YLD","YAS_YLD_FLAG=15")) | P779: =IF($A779="","",_xll.BDP($A779&" Corp","YAS_MOD_DUR")) | Q779: =IF($A779="","",_xll.BDP($A779&" Corp","YAS_OAS_SPRD")) | R779: =IF($A779="","",_xll.BDP($A779&" Corp","YAS_OAS_SPRD","SETTLE_DT",$B$2)) | S779: =IF($A779="","",IF(OR(NOT(ISNUMBER($Q779)),NOT(ISNUMBER($R779))),"",$Q779-$R779)) | T779: =IF($A779="","",_xll.BDP($A779&" Corp","YAS_BOND_YLD","YAS_YLD_FLAG=15","SETTLE_DT",$B$2)) | U779: =IF($A779="","",IF(OR(NOT(ISNUMBER($O779)),NOT(ISNUMBER($T779))),"",$O779-$T779)) | V779: =IF(NOT(ISNUMBER($S779)),"",COUNTIFS($G$7:$G$850,$G779,$S$7:$S$850,">"&$S779)+COUNTIFS($G$7:$G779,$G779,$S$7:$S779,$S779)) | W779: =IF(NOT(ISNUMBER($S779)),"",COUNTIFS($G$7:$G$850,$G779,$S$7:$S$850,"<"&$S779)+COUNTIFS($G$7:$G779,$G779,$S$7:$S779,$S779)) | X779: =IF($V779="","",$G779&"|"&$V779) | Y779: =IF($W779="","",$G779&"|"&$W779)
B780: =IF($A780="","",PROPER(_xll.BDP($A780&" Corp","NAME"))) | C780: =IF($A780="","",IFERROR(INDEX(Company_desc!$B$2:$B$1144,MATCH($A780,Company_desc!$A$2:$A$1144,0)),IFERROR(INDEX(SYZ_static!$Q$2:$Q$806,MATCH($A780,SYZ_static!$A$2:$A$806,0)),""))) | D780: =IF($A780="","",IFERROR(INDEX(SYZ_static!$B$2:$B$806,MATCH($A780,SYZ_static!$A$2:$A$806,0)),"")) | E780: =IF($A780="","",_xll.BDP($A780&" Corp","INDUSTRY_SECTOR")) | F780: =IF($A780="","",PROPER(_xll.BDP($A780&" Corp","COUNTRY_FULL_NAME"))) | G780: =IF($A780="","",_xll.BDP($A780&" Corp","CRNCY")) | H780: =IF($A780="","",IFERROR(INDEX(SYZ_static!$T$2:$T$806,MATCH($A780,SYZ_static!$A$2:$A$806,0)),_xll.BDP($A780&" Corp","RTG_SP"))) | I780: =IF($A780="","",IFERROR(INDEX(SYZ_static!$S$2:$S$806,MATCH($A780,SYZ_static!$A$2:$A$806,0)),"")) | J780: =IF($A780="","",_xll.BDP($A780&" Corp","PAYMENT_RANK")) | K780: =IF($A780="","",_xll.BDP($A780&" Corp","CPN")) | L780: =IF($A780="","",_xll.BDP($A780&" Corp","MATURITY")) | M780: =IF($A780="","",IFERROR(_xll.BDP($A780&" Corp","MIN_PIECE")/1000,"")) | N780: =IF($A780="","",_xll.BDP($A780&" Corp","PX_LAST")) | O780: =IF($A780="","",_xll.BDP($A780&" Corp","YAS_BOND_YLD","YAS_YLD_FLAG=15")) | P780: =IF($A780="","",_xll.BDP($A780&" Corp","YAS_MOD_DUR")) | Q780: =IF($A780="","",_xll.BDP($A780&" Corp","YAS_OAS_SPRD")) | R780: =IF($A780="","",_xll.BDP($A780&" Corp","YAS_OAS_SPRD","SETTLE_DT",$B$2)) | S780: =IF($A780="","",IF(OR(NOT(ISNUMBER($Q780)),NOT(ISNUMBER($R780))),"",$Q780-$R780)) | T780: =IF($A780="","",_xll.BDP($A780&" Corp","YAS_BOND_YLD","YAS_YLD_FLAG=15","SETTLE_DT",$B$2)) | U780: =IF($A780="","",IF(OR(NOT(ISNUMBER($O780)),NOT(ISNUMBER($T780))),"",$O780-$T780)) | V780: =IF(NOT(ISNUMBER($S780)),"",COUNTIFS($G$7:$G$850,$G780,$S$7:$S$850,">"&$S780)+COUNTIFS($G$7:$G780,$G780,$S$7:$S780,$S780)) | W780: =IF(NOT(ISNUMBER($S780)),"",COUNTIFS($G$7:$G$850,$G780,$S$7:$S$850,"<"&$S780)+COUNTIFS($G$7:$G780,$G780,$S$7:$S780,$S780)) | X780: =IF($V780="","",$G780&"|"&$V780) | Y780: =IF($W780="","",$G780&"|"&$W780)
B781: =IF($A781="","",PROPER(_xll.BDP($A781&" Corp","NAME"))) | C781: =IF($A781="","",IFERROR(INDEX(Company_desc!$B$2:$B$1144,MATCH($A781,Company_desc!$A$2:$A$1144,0)),IFERROR(INDEX(SYZ_static!$Q$2:$Q$806,MATCH($A781,SYZ_static!$A$2:$A$806,0)),""))) | D781: =IF($A781="","",IFERROR(INDEX(SYZ_static!$B$2:$B$806,MATCH($A781,SYZ_static!$A$2:$A$806,0)),"")) | E781: =IF($A781="","",_xll.BDP($A781&" Corp","INDUSTRY_SECTOR")) | F781: =IF($A781="","",PROPER(_xll.BDP($A781&" Corp","COUNTRY_FULL_NAME"))) | G781: =IF($A781="","",_xll.BDP($A781&" Corp","CRNCY")) | H781: =IF($A781="","",IFERROR(INDEX(SYZ_static!$T$2:$T$806,MATCH($A781,SYZ_static!$A$2:$A$806,0)),_xll.BDP($A781&" Corp","RTG_SP"))) | I781: =IF($A781="","",IFERROR(INDEX(SYZ_static!$S$2:$S$806,MATCH($A781,SYZ_static!$A$2:$A$806,0)),"")) | J781: =IF($A781="","",_xll.BDP($A781&" Corp","PAYMENT_RANK")) | K781: =IF($A781="","",_xll.BDP($A781&" Corp","CPN")) | L781: =IF($A781="","",_xll.BDP($A781&" Corp","MATURITY")) | M781: =IF($A781="","",IFERROR(_xll.BDP($A781&" Corp","MIN_PIECE")/1000,"")) | N781: =IF($A781="","",_xll.BDP($A781&" Corp","PX_LAST")) | O781: =IF($A781="","",_xll.BDP($A781&" Corp","YAS_BOND_YLD","YAS_YLD_FLAG=15")) | P781: =IF($A781="","",_xll.BDP($A781&" Corp","YAS_MOD_DUR")) | Q781: =IF($A781="","",_xll.BDP($A781&" Corp","YAS_OAS_SPRD")) | R781: =IF($A781="","",_xll.BDP($A781&" Corp","YAS_OAS_SPRD","SETTLE_DT",$B$2)) | S781: =IF($A781="","",IF(OR(NOT(ISNUMBER($Q781)),NOT(ISNUMBER($R781))),"",$Q781-$R781)) | T781: =IF($A781="","",_xll.BDP($A781&" Corp","YAS_BOND_YLD","YAS_YLD_FLAG=15","SETTLE_DT",$B$2)) | U781: =IF($A781="","",IF(OR(NOT(ISNUMBER($O781)),NOT(ISNUMBER($T781))),"",$O781-$T781)) | V781: =IF(NOT(ISNUMBER($S781)),"",COUNTIFS($G$7:$G$850,$G781,$S$7:$S$850,">"&$S781)+COUNTIFS($G$7:$G781,$G781,$S$7:$S781,$S781)) | W781: =IF(NOT(ISNUMBER($S781)),"",COUNTIFS($G$7:$G$850,$G781,$S$7:$S$850,"<"&$S781)+COUNTIFS($G$7:$G781,$G781,$S$7:$S781,$S781)) | X781: =IF($V781="","",$G781&"|"&$V781) | Y781: =IF($W781="","",$G781&"|"&$W781)
... B850: =IF($A850="","",PROPER(_xll.BDP($A850&" Corp","NAME"))) | C850: =IF($A850="","",IFERROR(INDEX(Company_desc!$B$2:$B$1144,MATCH($A850,Company_desc!$A$2:$A$1144,0)),IFERROR(INDEX(SYZ_static!$Q$2:$Q$806,MATCH($A850,SYZ_static!$A$2:$A$806,0)),""))) | D850: =IF($A850="","",IFERROR(INDEX(SYZ_static!$B$2:$B$806,MATCH($A850,SYZ_static!$A$2:$A$806,0)),"")) | E850: =IF($A850="","",_xll.BDP($A850&" Corp","INDUSTRY_SECTOR")) | F850: =IF($A850="","",PROPER(_xll.BDP($A850&" Corp","COUNTRY_FULL_NAME"))) | G850: =IF($A850="","",_xll.BDP($A850&" Corp","CRNCY")) | H850: =IF($A850="","",IFERROR(INDEX(SYZ_static!$T$2:$T$806,MATCH($A850,SYZ_static!$A$2:$A$806,0)),_xll.BDP($A850&" Corp","RTG_SP"))) | I850: =IF($A850="","",IFERROR(INDEX(SYZ_static!$S$2:$S$806,MATCH($A850,SYZ_static!$A$2:$A$806,0)),"")) | J850: =IF($A850="","",_xll.BDP($A850&" Corp","PAYMENT_RANK")) | K850: =IF($A850="","",_xll.BDP($A850&" Corp","CPN")) | L850: =IF($A850="","",_xll.BDP($A850&" Corp","MATURITY")) | M850: =IF($A850="","",IFERROR(_xll.BDP($A850&" Corp","MIN_PIECE")/1000,"")) | N850: =IF($A850="","",_xll.BDP($A850&" Corp","PX_LAST")) | O850: =IF($A850="","",_xll.BDP($A850&" Corp","YAS_BOND_YLD","YAS_YLD_FLAG=15")) | P850: =IF($A850="","",_xll.BDP($A850&" Corp","YAS_MOD_DUR")) | Q850: =IF($A850="","",_xll.BDP($A850&" Corp","YAS_OAS_SPRD")) | R850: =IF($A850="","",_xll.BDP($A850&" Corp","YAS_OAS_SPRD","SETTLE_DT",$B$2)) | S850: =IF($A850="","",IF(OR(NOT(ISNUMBER($Q850)),NOT(ISNUMBER($R850))),"",$Q850-$R850)) | T850: =IF($A850="","",_xll.BDP($A850&" Corp","YAS_BOND_YLD","YAS_YLD_FLAG=15","SETTLE_DT",$B$2)) | U850: =IF($A850="","",IF(OR(NOT(ISNUMBER($O850)),NOT(ISNUMBER($T850))),"",$O850-$T850)) | V850: =IF(NOT(ISNUMBER($S850)),"",COUNTIFS($G$7:$G$850,$G850,$S$7:$S$850,">"&$S850)+COUNTIFS($G$7:$G850,$G850,$S$7:$S850,$S850)) | W850: =IF(NOT(ISNUMBER($S850)),"",COUNTIFS($G$7:$G$850,$G850,$S$7:$S$850,"<"&$S850)+COUNTIFS($G$7:$G850,$G850,$S$7:$S850,$S850)) | X850: =IF($V850="","",$G850&"|"&$V850) | Y850: =IF($W850="","",$G850&"|"&$W850)

Sheet Top & Bottom
A1: Biggest spread movers since 14.07.2026
A2: ='Spread Monitor'!$B$2
A3: Ranked within each currency. Live formulas - they follow the Spread Monitor sheet automatically.
A5: USD - Top 10 that widened the most since 14.07.2026
A6: ISIN | B6: Company | C6: Company description | D6: Sector | E6: Ccy | F6: Rating | G6: Maturity | H6: YTW (%) | I6: Spread today (bp) | J6: Spread on anchor (bp) | K6: Spread change (bp)
A7: =IFERROR(INDEX('Spread Monitor'!$A$7:$A$850,MATCH("USD|1",'Spread Monitor'!$X$7:$X$850,0)),"") | B7: =IFERROR(INDEX('Spread Monitor'!$B$7:$B$850,MATCH("USD|1",'Spread Monitor'!$X$7:$X$850,0)),"") | C7: =IFERROR(INDEX('Spread Monitor'!$C$7:$C$850,MATCH("USD|1",'Spread Monitor'!$X$7:$X$850,0)),"") | D7: =IFERROR(INDEX('Spread Monitor'!$E$7:$E$850,MATCH("USD|1",'Spread Monitor'!$X$7:$X$850,0)),"") | E7: =IFERROR(INDEX('Spread Monitor'!$G$7:$G$850,MATCH("USD|1",'Spread Monitor'!$X$7:$X$850,0)),"") | F7: =IFERROR(INDEX('Spread Monitor'!$H$7:$H$850,MATCH("USD|1",'Spread Monitor'!$X$7:$X$850,0)),"") | G7: =IFERROR(INDEX('Spread Monitor'!$L$7:$L$850,MATCH("USD|1",'Spread Monitor'!$X$7:$X$850,0)),"") | H7: =IFERROR(INDEX('Spread Monitor'!$O$7:$O$850,MATCH("USD|1",'Spread Monitor'!$X$7:$X$850,0)),"") | I7: =IFERROR(INDEX('Spread Monitor'!$Q$7:$Q$850,MATCH("USD|1",'Spread Monitor'!$X$7:$X$850,0)),"") | J7: =IFERROR(INDEX('Spread Monitor'!$R$7:$R$850,MATCH("USD|1",'Spread Monitor'!$X$7:$X$850,0)),"") | K7: =IFERROR(INDEX('Spread Monitor'!$S$7:$S$850,MATCH("USD|1",'Spread Monitor'!$X$7:$X$850,0)),"")
A8: =IFERROR(INDEX('Spread Monitor'!$A$7:$A$850,MATCH("USD|2",'Spread Monitor'!$X$7:$X$850,0)),"") | B8: =IFERROR(INDEX('Spread Monitor'!$B$7:$B$850,MATCH("USD|2",'Spread Monitor'!$X$7:$X$850,0)),"") | C8: =IFERROR(INDEX('Spread Monitor'!$C$7:$C$850,MATCH("USD|2",'Spread Monitor'!$X$7:$X$850,0)),"") | D8: =IFERROR(INDEX('Spread Monitor'!$E$7:$E$850,MATCH("USD|2",'Spread Monitor'!$X$7:$X$850,0)),"") | E8: =IFERROR(INDEX('Spread Monitor'!$G$7:$G$850,MATCH("USD|2",'Spread Monitor'!$X$7:$X$850,0)),"") | F8: =IFERROR(INDEX('Spread Monitor'!$H$7:$H$850,MATCH("USD|2",'Spread Monitor'!$X$7:$X$850,0)),"") | G8: =IFERROR(INDEX('Spread Monitor'!$L$7:$L$850,MATCH("USD|2",'Spread Monitor'!$X$7:$X$850,0)),"") | H8: =IFERROR(INDEX('Spread Monitor'!$O$7:$O$850,MATCH("USD|2",'Spread Monitor'!$X$7:$X$850,0)),"") | I8: =IFERROR(INDEX('Spread Monitor'!$Q$7:$Q$850,MATCH("USD|2",'Spread Monitor'!$X$7:$X$850,0)),"") | J8: =IFERROR(INDEX('Spread Monitor'!$R$7:$R$850,MATCH("USD|2",'Spread Monitor'!$X$7:$X$850,0)),"") | K8: =IFERROR(INDEX('Spread Monitor'!$S$7:$S$850,MATCH("USD|2",'Spread Monitor'!$X$7:$X$850,0)),"")
A9: =IFERROR(INDEX('Spread Monitor'!$A$7:$A$850,MATCH("USD|3",'Spread Monitor'!$X$7:$X$850,0)),"") | B9: =IFERROR(INDEX('Spread Monitor'!$B$7:$B$850,MATCH("USD|3",'Spread Monitor'!$X$7:$X$850,0)),"") | C9: =IFERROR(INDEX('Spread Monitor'!$C$7:$C$850,MATCH("USD|3",'Spread Monitor'!$X$7:$X$850,0)),"") | D9: =IFERROR(INDEX('Spread Monitor'!$E$7:$E$850,MATCH("USD|3",'Spread Monitor'!$X$7:$X$850,0)),"") | E9: =IFERROR(INDEX('Spread Monitor'!$G$7:$G$850,MATCH("USD|3",'Spread Monitor'!$X$7:$X$850,0)),"") | F9: =IFERROR(INDEX('Spread Monitor'!$H$7:$H$850,MATCH("USD|3",'Spread Monitor'!$X$7:$X$850,0)),"") | G9: =IFERROR(INDEX('Spread Monitor'!$L$7:$L$850,MATCH("USD|3",'Spread Monitor'!$X$7:$X$850,0)),"") | H9: =IFERROR(INDEX('Spread Monitor'!$O$7:$O$850,MATCH("USD|3",'Spread Monitor'!$X$7:$X$850,0)),"") | I9: =IFERROR(INDEX('Spread Monitor'!$Q$7:$Q$850,MATCH("USD|3",'Spread Monitor'!$X$7:$X$850,0)),"") | J9: =IFERROR(INDEX('Spread Monitor'!$R$7:$R$850,MATCH("USD|3",'Spread Monitor'!$X$7:$X$850,0)),"") | K9: =IFERROR(INDEX('Spread Monitor'!$S$7:$S$850,MATCH("USD|3",'Spread Monitor'!$X$7:$X$850,0)),"")
A10: =IFERROR(INDEX('Spread Monitor'!$A$7:$A$850,MATCH("USD|4",'Spread Monitor'!$X$7:$X$850,0)),"") | B10: =IFERROR(INDEX('Spread Monitor'!$B$7:$B$850,MATCH("USD|4",'Spread Monitor'!$X$7:$X$850,0)),"") | C10: =IFERROR(INDEX('Spread Monitor'!$C$7:$C$850,MATCH("USD|4",'Spread Monitor'!$X$7:$X$850,0)),"") | D10: =IFERROR(INDEX('Spread Monitor'!$E$7:$E$850,MATCH("USD|4",'Spread Monitor'!$X$7:$X$850,0)),"") | E10: =IFERROR(INDEX('Spread Monitor'!$G$7:$G$850,MATCH("USD|4",'Spread Monitor'!$X$7:$X$850,0)),"") | F10: =IFERROR(INDEX('Spread Monitor'!$H$7:$H$850,MATCH("USD|4",'Spread Monitor'!$X$7:$X$850,0)),"") | G10: =IFERROR(INDEX('Spread Monitor'!$L$7:$L$850,MATCH("USD|4",'Spread Monitor'!$X$7:$X$850,0)),"") | H10: =IFERROR(INDEX('Spread Monitor'!$O$7:$O$850,MATCH("USD|4",'Spread Monitor'!$X$7:$X$850,0)),"") | I10: =IFERROR(INDEX('Spread Monitor'!$Q$7:$Q$850,MATCH("USD|4",'Spread Monitor'!$X$7:$X$850,0)),"") | J10: =IFERROR(INDEX('Spread Monitor'!$R$7:$R$850,MATCH("USD|4",'Spread Monitor'!$X$7:$X$850,0)),"") | K10: =IFERROR(INDEX('Spread Monitor'!$S$7:$S$850,MATCH("USD|4",'Spread Monitor'!$X$7:$X$850,0)),"")
A11: =IFERROR(INDEX('Spread Monitor'!$A$7:$A$850,MATCH("USD|5",'Spread Monitor'!$X$7:$X$850,0)),"") | B11: =IFERROR(INDEX('Spread Monitor'!$B$7:$B$850,MATCH("USD|5",'Spread Monitor'!$X$7:$X$850,0)),"") | C11: =IFERROR(INDEX('Spread Monitor'!$C$7:$C$850,MATCH("USD|5",'Spread Monitor'!$X$7:$X$850,0)),"") | D11: =IFERROR(INDEX('Spread Monitor'!$E$7:$E$850,MATCH("USD|5",'Spread Monitor'!$X$7:$X$850,0)),"") | E11: =IFERROR(INDEX('Spread Monitor'!$G$7:$G$850,MATCH("USD|5",'Spread Monitor'!$X$7:$X$850,0)),"") | F11: =IFERROR(INDEX('Spread Monitor'!$H$7:$H$850,MATCH("USD|5",'Spread Monitor'!$X$7:$X$850,0)),"") | G11: =IFERROR(INDEX('Spread Monitor'!$L$7:$L$850,MATCH("USD|5",'Spread Monitor'!$X$7:$X$850,0)),"") | H11: =IFERROR(INDEX('Spread Monitor'!$O$7:$O$850,MATCH("USD|5",'Spread Monitor'!$X$7:$X$850,0)),"") | I11: =IFERROR(INDEX('Spread Monitor'!$Q$7:$Q$850,MATCH("USD|5",'Spread Monitor'!$X$7:$X$850,0)),"") | J11: =IFERROR(INDEX('Spread Monitor'!$R$7:$R$850,MATCH("USD|5",'Spread Monitor'!$X$7:$X$850,0)),"") | K11: =IFERROR(INDEX('Spread Monitor'!$S$7:$S$850,MATCH("USD|5",'Spread Monitor'!$X$7:$X$850,0)),"")
A12: =IFERROR(INDEX('Spread Monitor'!$A$7:$A$850,MATCH("USD|6",'Spread Monitor'!$X$7:$X$850,0)),"") | B12: =IFERROR(INDEX('Spread Monitor'!$B$7:$B$850,MATCH("USD|6",'Spread Monitor'!$X$7:$X$850,0)),"") | C12: =IFERROR(INDEX('Spread Monitor'!$C$7:$C$850,MATCH("USD|6",'Spread Monitor'!$X$7:$X$850,0)),"") | D12: =IFERROR(INDEX('Spread Monitor'!$E$7:$E$850,MATCH("USD|6",'Spread Monitor'!$X$7:$X$850,0)),"") | E12: =IFERROR(INDEX('Spread Monitor'!$G$7:$G$850,MATCH("USD|6",'Spread Monitor'!$X$7:$X$850,0)),"") | F12: =IFERROR(INDEX('Spread Monitor'!$H$7:$H$850,MATCH("USD|6",'Spread Monitor'!$X$7:$X$850,0)),"") | G12: =IFERROR(INDEX('Spread Monitor'!$L$7:$L$850,MATCH("USD|6",'Spread Monitor'!$X$7:$X$850,0)),"") | H12: =IFERROR(INDEX('Spread Monitor'!$O$7:$O$850,MATCH("USD|6",'Spread Monitor'!$X$7:$X$850,0)),"") | I12: =IFERROR(INDEX('Spread Monitor'!$Q$7:$Q$850,MATCH("USD|6",'Spread Monitor'!$X$7:$X$850,0)),"") | J12: =IFERROR(INDEX('Spread Monitor'!$R$7:$R$850,MATCH("USD|6",'Spread Monitor'!$X$7:$X$850,0)),"") | K12: =IFERROR(INDEX('Spread Monitor'!$S$7:$S$850,MATCH("USD|6",'Spread Monitor'!$X$7:$X$850,0)),"")
A13: =IFERROR(INDEX('Spread Monitor'!$A$7:$A$850,MATCH("USD|7",'Spread Monitor'!$X$7:$X$850,0)),"") | B13: =IFERROR(INDEX('Spread Monitor'!$B$7:$B$850,MATCH("USD|7",'Spread Monitor'!$X$7:$X$850,0)),"") | C13: =IFERROR(INDEX('Spread Monitor'!$C$7:$C$850,MATCH("USD|7",'Spread Monitor'!$X$7:$X$850,0)),"") | D13: =IFERROR(INDEX('Spread Monitor'!$E$7:$E$850,MATCH("USD|7",'Spread Monitor'!$X$7:$X$850,0)),"") | E13: =IFERROR(INDEX('Spread Monitor'!$G$7:$G$850,MATCH("USD|7",'Spread Monitor'!$X$7:$X$850,0)),"") | F13: =IFERROR(INDEX('Spread Monitor'!$H$7:$H$850,MATCH("USD|7",'Spread Monitor'!$X$7:$X$850,0)),"") | G13: =IFERROR(INDEX('Spread Monitor'!$L$7:$L$850,MATCH("USD|7",'Spread Monitor'!$X$7:$X$850,0)),"") | H13: =IFERROR(INDEX('Spread Monitor'!$O$7:$O$850,MATCH("USD|7",'Spread Monitor'!$X$7:$X$850,0)),"") | I13: =IFERROR(INDEX('Spread Monitor'!$Q$7:$Q$850,MATCH("USD|7",'Spread Monitor'!$X$7:$X$850,0)),"") | J13: =IFERROR(INDEX('Spread Monitor'!$R$7:$R$850,MATCH("USD|7",'Spread Monitor'!$X$7:$X$850,0)),"") | K13: =IFERROR(INDEX('Spread Monitor'!$S$7:$S$850,MATCH("USD|7",'Spread Monitor'!$X$7:$X$850,0)),"")
A14: =IFERROR(INDEX('Spread Monitor'!$A$7:$A$850,MATCH("USD|8",'Spread Monitor'!$X$7:$X$850,0)),"") | B14: =IFERROR(INDEX('Spread Monitor'!$B$7:$B$850,MATCH("USD|8",'Spread Monitor'!$X$7:$X$850,0)),"") | C14: =IFERROR(INDEX('Spread Monitor'!$C$7:$C$850,MATCH("USD|8",'Spread Monitor'!$X$7:$X$850,0)),"") | D14: =IFERROR(INDEX('Spread Monitor'!$E$7:$E$850,MATCH("USD|8",'Spread Monitor'!$X$7:$X$850,0)),"") | E14: =IFERROR(INDEX('Spread Monitor'!$G$7:$G$850,MATCH("USD|8",'Spread Monitor'!$X$7:$X$850,0)),"") | F14: =IFERROR(INDEX('Spread Monitor'!$H$7:$H$850,MATCH("USD|8",'Spread Monitor'!$X$7:$X$850,0)),"") | G14: =IFERROR(INDEX('Spread Monitor'!$L$7:$L$850,MATCH("USD|8",'Spread Monitor'!$X$7:$X$850,0)),"") | H14: =IFERROR(INDEX('Spread Monitor'!$O$7:$O$850,MATCH("USD|8",'Spread Monitor'!$X$7:$X$850,0)),"") | I14: =IFERROR(INDEX('Spread Monitor'!$Q$7:$Q$850,MATCH("USD|8",'Spread Monitor'!$X$7:$X$850,0)),"") | J14: =IFERROR(INDEX('Spread Monitor'!$R$7:$R$850,MATCH("USD|8",'Spread Monitor'!$X$7:$X$850,0)),"") | K14: =IFERROR(INDEX('Spread Monitor'!$S$7:$S$850,MATCH("USD|8",'Spread Monitor'!$X$7:$X$850,0)),"")
A15: =IFERROR(INDEX('Spread Monitor'!$A$7:$A$850,MATCH("USD|9",'Spread Monitor'!$X$7:$X$850,0)),"") | B15: =IFERROR(INDEX('Spread Monitor'!$B$7:$B$850,MATCH("USD|9",'Spread Monitor'!$X$7:$X$850,0)),"") | C15: =IFERROR(INDEX('Spread Monitor'!$C$7:$C$850,MATCH("USD|9",'Spread Monitor'!$X$7:$X$850,0)),"") | D15: =IFERROR(INDEX('Spread Monitor'!$E$7:$E$850,MATCH("USD|9",'Spread Monitor'!$X$7:$X$850,0)),"") | E15: =IFERROR(INDEX('Spread Monitor'!$G$7:$G$850,MATCH("USD|9",'Spread Monitor'!$X$7:$X$850,0)),"") | F15: =IFERROR(INDEX('Spread Monitor'!$H$7:$H$850,MATCH("USD|9",'Spread Monitor'!$X$7:$X$850,0)),"") | G15: =IFERROR(INDEX('Spread Monitor'!$L$7:$L$850,MATCH("USD|9",'Spread Monitor'!$X$7:$X$850,0)),"") | H15: =IFERROR(INDEX('Spread Monitor'!$O$7:$O$850,MATCH("USD|9",'Spread Monitor'!$X$7:$X$850,0)),"") | I15: =IFERROR(INDEX('Spread Monitor'!$Q$7:$Q$850,MATCH("USD|9",'Spread Monitor'!$X$7:$X$850,0)),"") | J15: =IFERROR(INDEX('Spread Monitor'!$R$7:$R$850,MATCH("USD|9",'Spread Monitor'!$X$7:$X$850,0)),"") | K15: =IFERROR(INDEX('Spread Monitor'!$S$7:$S$850,MATCH("USD|9",'Spread Monitor'!$X$7:$X$850,0)),"")
A16: =IFERROR(INDEX('Spread Monitor'!$A$7:$A$850,MATCH("USD|10",'Spread Monitor'!$X$7:$X$850,0)),"") | B16: =IFERROR(INDEX('Spread Monitor'!$B$7:$B$850,MATCH("USD|10",'Spread Monitor'!$X$7:$X$850,0)),"") | C16: =IFERROR(INDEX('Spread Monitor'!$C$7:$C$850,MATCH("USD|10",'Spread Monitor'!$X$7:$X$850,0)),"") | D16: =IFERROR(INDEX('Spread Monitor'!$E$7:$E$850,MATCH("USD|10",'Spread Monitor'!$X$7:$X$850,0)),"") | E16: =IFERROR(INDEX('Spread Monitor'!$G$7:$G$850,MATCH("USD|10",'Spread Monitor'!$X$7:$X$850,0)),"") | F16: =IFERROR(INDEX('Spread Monitor'!$H$7:$H$850,MATCH("USD|10",'Spread Monitor'!$X$7:$X$850,0)),"") | G16: =IFERROR(INDEX('Spread Monitor'!$L$7:$L$850,MATCH("USD|10",'Spread Monitor'!$X$7:$X$850,0)),"") | H16: =IFERROR(INDEX('Spread Monitor'!$O$7:$O$850,MATCH("USD|10",'Spread Monitor'!$X$7:$X$850,0)),"") | I16: =IFERROR(INDEX('Spread Monitor'!$Q$7:$Q$850,MATCH("USD|10",'Spread Monitor'!$X$7:$X$850,0)),"") | J16: =IFERROR(INDEX('Spread Monitor'!$R$7:$R$850,MATCH("USD|10",'Spread Monitor'!$X$7:$X$850,0)),"") | K16: =IFERROR(INDEX('Spread Monitor'!$S$7:$S$850,MATCH("USD|10",'Spread Monitor'!$X$7:$X$850,0)),"")
A19: USD - Top 10 that tightened the most since 14.07.2026
A20: ISIN | B20: Company | C20: Company description | D20: Sector | E20: Ccy | F20: Rating | G20: Maturity | H20: YTW (%) | I20: Spread today (bp) | J20: Spread on anchor (bp) | K20: Spread change (bp)
A21: =IFERROR(INDEX('Spread Monitor'!$A$7:$A$850,MATCH("USD|1",'Spread Monitor'!$Y$7:$Y$850,0)),"") | B21: =IFERROR(INDEX('Spread Monitor'!$B$7:$B$850,MATCH("USD|1",'Spread Monitor'!$Y$7:$Y$850,0)),"") | C21: =IFERROR(INDEX('Spread Monitor'!$C$7:$C$850,MATCH("USD|1",'Spread Monitor'!$Y$7:$Y$850,0)),"") | D21: =IFERROR(INDEX('Spread Monitor'!$E$7:$E$850,MATCH("USD|1",'Spread Monitor'!$Y$7:$Y$850,0)),"") | E21: =IFERROR(INDEX('Spread Monitor'!$G$7:$G$850,MATCH("USD|1",'Spread Monitor'!$Y$7:$Y$850,0)),"") | F21: =IFERROR(INDEX('Spread Monitor'!$H$7:$H$850,MATCH("USD|1",'Spread Monitor'!$Y$7:$Y$850,0)),"") | G21: =IFERROR(INDEX('Spread Monitor'!$L$7:$L$850,MATCH("USD|1",'Spread Monitor'!$Y$7:$Y$850,0)),"") | H21: =IFERROR(INDEX('Spread Monitor'!$O$7:$O$850,MATCH("USD|1",'Spread Monitor'!$Y$7:$Y$850,0)),"") | I21: =IFERROR(INDEX('Spread Monitor'!$Q$7:$Q$850,MATCH("USD|1",'Spread Monitor'!$Y$7:$Y$850,0)),"") | J21: =IFERROR(INDEX('Spread Monitor'!$R$7:$R$850,MATCH("USD|1",'Spread Monitor'!$Y$7:$Y$850,0)),"") | K21: =IFERROR(INDEX('Spread Monitor'!$S$7:$S$850,MATCH("USD|1",'Spread Monitor'!$Y$7:$Y$850,0)),"")
A22: =IFERROR(INDEX('Spread Monitor'!$A$7:$A$850,MATCH("USD|2",'Spread Monitor'!$Y$7:$Y$850,0)),"") | B22: =IFERROR(INDEX('Spread Monitor'!$B$7:$B$850,MATCH("USD|2",'Spread Monitor'!$Y$7:$Y$850,0)),"") | C22: =IFERROR(INDEX('Spread Monitor'!$C$7:$C$850,MATCH("USD|2",'Spread Monitor'!$Y$7:$Y$850,0)),"") | D22: =IFERROR(INDEX('Spread Monitor'!$E$7:$E$850,MATCH("USD|2",'Spread Monitor'!$Y$7:$Y$850,0)),"") | E22: =IFERROR(INDEX('Spread Monitor'!$G$7:$G$850,MATCH("USD|2",'Spread Monitor'!$Y$7:$Y$850,0)),"") | F22: =IFERROR(INDEX('Spread Monitor'!$H$7:$H$850,MATCH("USD|2",'Spread Monitor'!$Y$7:$Y$850,0)),"") | G22: =IFERROR(INDEX('Spread Monitor'!$L$7:$L$850,MATCH("USD|2",'Spread Monitor'!$Y$7:$Y$850,0)),"") | H22: =IFERROR(INDEX('Spread Monitor'!$O$7:$O$850,MATCH("USD|2",'Spread Monitor'!$Y$7:$Y$850,0)),"") | I22: =IFERROR(INDEX('Spread Monitor'!$Q$7:$Q$850,MATCH("USD|2",'Spread Monitor'!$Y$7:$Y$850,0)),"") | J22: =IFERROR(INDEX('Spread Monitor'!$R$7:$R$850,MATCH("USD|2",'Spread Monitor'!$Y$7:$Y$850,0)),"") | K22: =IFERROR(INDEX('Spread Monitor'!$S$7:$S$850,MATCH("USD|2",'Spread Monitor'!$Y$7:$Y$850,0)),"")
A23: =IFERROR(INDEX('Spread Monitor'!$A$7:$A$850,MATCH("USD|3",'Spread Monitor'!$Y$7:$Y$850,0)),"") | B23: =IFERROR(INDEX('Spread Monitor'!$B$7:$B$850,MATCH("USD|3",'Spread Monitor'!$Y$7:$Y$850,0)),"") | C23: =IFERROR(INDEX('Spread Monitor'!$C$7:$C$850,MATCH("USD|3",'Spread Monitor'!$Y$7:$Y$850,0)),"") | D23: =IFERROR(INDEX('Spread Monitor'!$E$7:$E$850,MATCH("USD|3",'Spread Monitor'!$Y$7:$Y$850,0)),"") | E23: =IFERROR(INDEX('Spread Monitor'!$G$7:$G$850,MATCH("USD|3",'Spread Monitor'!$Y$7:$Y$850,0)),"") | F23: =IFERROR(INDEX('Spread Monitor'!$H$7:$H$850,MATCH("USD|3",'Spread Monitor'!$Y$7:$Y$850,0)),"") | G23: =IFERROR(INDEX('Spread Monitor'!$L$7:$L$850,MATCH("USD|3",'Spread Monitor'!$Y$7:$Y$850,0)),"") | H23: =IFERROR(INDEX('Spread Monitor'!$O$7:$O$850,MATCH("USD|3",'Spread Monitor'!$Y$7:$Y$850,0)),"") | I23: =IFERROR(INDEX('Spread Monitor'!$Q$7:$Q$850,MATCH("USD|3",'Spread Monitor'!$Y$7:$Y$850,0)),"") | J23: =IFERROR(INDEX('Spread Monitor'!$R$7:$R$850,MATCH("USD|3",'Spread Monitor'!$Y$7:$Y$850,0)),"") | K23: =IFERROR(INDEX('Spread Monitor'!$S$7:$S$850,MATCH("USD|3",'Spread Monitor'!$Y$7:$Y$850,0)),"")
A24: =IFERROR(INDEX('Spread Monitor'!$A$7:$A$850,MATCH("USD|4",'Spread Monitor'!$Y$7:$Y$850,0)),"") | B24: =IFERROR(INDEX('Spread Monitor'!$B$7:$B$850,MATCH("USD|4",'Spread Monitor'!$Y$7:$Y$850,0)),"") | C24: =IFERROR(INDEX('Spread Monitor'!$C$7:$C$850,MATCH("USD|4",'Spread Monitor'!$Y$7:$Y$850,0)),"") | D24: =IFERROR(INDEX('Spread Monitor'!$E$7:$E$850,MATCH("USD|4",'Spread Monitor'!$Y$7:$Y$850,0)),"") | E24: =IFERROR(INDEX('Spread Monitor'!$G$7:$G$850,MATCH("USD|4",'Spread Monitor'!$Y$7:$Y$850,0)),"") | F24: =IFERROR(INDEX('Spread Monitor'!$H$7:$H$850,MATCH("USD|4",'Spread Monitor'!$Y$7:$Y$850,0)),"") | G24: =IFERROR(INDEX('Spread Monitor'!$L$7:$L$850,MATCH("USD|4",'Spread Monitor'!$Y$7:$Y$850,0)),"") | H24: =IFERROR(INDEX('Spread Monitor'!$O$7:$O$850,MATCH("USD|4",'Spread Monitor'!$Y$7:$Y$850,0)),"") | I24: =IFERROR(INDEX('Spread Monitor'!$Q$7:$Q$850,MATCH("USD|4",'Spread Monitor'!$Y$7:$Y$850,0)),"") | J24: =IFERROR(INDEX('Spread Monitor'!$R$7:$R$850,MATCH("USD|4",'Spread Monitor'!$Y$7:$Y$850,0)),"") | K24: =IFERROR(INDEX('Spread Monitor'!$S$7:$S$850,MATCH("USD|4",'Spread Monitor'!$Y$7:$Y$850,0)),"")
A25: =IFERROR(INDEX('Spread Monitor'!$A$7:$A$850,MATCH("USD|5",'Spread Monitor'!$Y$7:$Y$850,0)),"") | B25: =IFERROR(INDEX('Spread Monitor'!$B$7:$B$850,MATCH("USD|5",'Spread Monitor'!$Y$7:$Y$850,0)),"") | C25: =IFERROR(INDEX('Spread Monitor'!$C$7:$C$850,MATCH("USD|5",'Spread Monitor'!$Y$7:$Y$850,0)),"") | D25: =IFERROR(INDEX('Spread Monitor'!$E$7:$E$850,MATCH("USD|5",'Spread Monitor'!$Y$7:$Y$850,0)),"") | E25: =IFERROR(INDEX('Spread Monitor'!$G$7:$G$850,MATCH("USD|5",'Spread Monitor'!$Y$7:$Y$850,0)),"") | F25: =IFERROR(INDEX('Spread Monitor'!$H$7:$H$850,MATCH("USD|5",'Spread Monitor'!$Y$7:$Y$850,0)),"") | G25: =IFERROR(INDEX('Spread Monitor'!$L$7:$L$850,MATCH("USD|5",'Spread Monitor'!$Y$7:$Y$850,0)),"") | H25: =IFERROR(INDEX('Spread Monitor'!$O$7:$O$850,MATCH("USD|5",'Spread Monitor'!$Y$7:$Y$850,0)),"") | I25: =IFERROR(INDEX('Spread Monitor'!$Q$7:$Q$850,MATCH("USD|5",'Spread Monitor'!$Y$7:$Y$850,0)),"") | J25: =IFERROR(INDEX('Spread Monitor'!$R$7:$R$850,MATCH("USD|5",'Spread Monitor'!$Y$7:$Y$850,0)),"") | K25: =IFERROR(INDEX('Spread Monitor'!$S$7:$S$850,MATCH("USD|5",'Spread Monitor'!$Y$7:$Y$850,0)),"")
A26: =IFERROR(INDEX('Spread Monitor'!$A$7:$A$850,MATCH("USD|6",'Spread Monitor'!$Y$7:$Y$850,0)),"") | B26: =IFERROR(INDEX('Spread Monitor'!$B$7:$B$850,MATCH("USD|6",'Spread Monitor'!$Y$7:$Y$850,0)),"") | C26: =IFERROR(INDEX('Spread Monitor'!$C$7:$C$850,MATCH("USD|6",'Spread Monitor'!$Y$7:$Y$850,0)),"") | D26: =IFERROR(INDEX('Spread Monitor'!$E$7:$E$850,MATCH("USD|6",'Spread Monitor'!$Y$7:$Y$850,0)),"") | E26: =IFERROR(INDEX('Spread Monitor'!$G$7:$G$850,MATCH("USD|6",'Spread Monitor'!$Y$7:$Y$850,0)),"") | F26: =IFERROR(INDEX('Spread Monitor'!$H$7:$H$850,MATCH("USD|6",'Spread Monitor'!$Y$7:$Y$850,0)),"") | G26: =IFERROR(INDEX('Spread Monitor'!$L$7:$L$850,MATCH("USD|6",'Spread Monitor'!$Y$7:$Y$850,0)),"") | H26: =IFERROR(INDEX('Spread Monitor'!$O$7:$O$850,MATCH("USD|6",'Spread Monitor'!$Y$7:$Y$850,0)),"") | I26: =IFERROR(INDEX('Spread Monitor'!$Q$7:$Q$850,MATCH("USD|6",'Spread Monitor'!$Y$7:$Y$850,0)),"") | J26: =IFERROR(INDEX('Spread Monitor'!$R$7:$R$850,MATCH("USD|6",'Spread Monitor'!$Y$7:$Y$850,0)),"") | K26: =IFERROR(INDEX('Spread Monitor'!$S$7:$S$850,MATCH("USD|6",'Spread Monitor'!$Y$7:$Y$850,0)),"")
A27: =IFERROR(INDEX('Spread Monitor'!$A$7:$A$850,MATCH("USD|7",'Spread Monitor'!$Y$7:$Y$850,0)),"") | B27: =IFERROR(INDEX('Spread Monitor'!$B$7:$B$850,MATCH("USD|7",'Spread Monitor'!$Y$7:$Y$850,0)),"") | C27: =IFERROR(INDEX('Spread Monitor'!$C$7:$C$850,MATCH("USD|7",'Spread Monitor'!$Y$7:$Y$850,0)),"") | D27: =IFERROR(INDEX('Spread Monitor'!$E$7:$E$850,MATCH("USD|7",'Spread Monitor'!$Y$7:$Y$850,0)),"") | E27: =IFERROR(INDEX('Spread Monitor'!$G$7:$G$850,MATCH("USD|7",'Spread Monitor'!$Y$7:$Y$850,0)),"") | F27: =IFERROR(INDEX('Spread Monitor'!$H$7:$H$850,MATCH("USD|7",'Spread Monitor'!$Y$7:$Y$850,0)),"") | G27: =IFERROR(INDEX('Spread Monitor'!$L$7:$L$850,MATCH("USD|7",'Spread Monitor'!$Y$7:$Y$850,0)),"") | H27: =IFERROR(INDEX('Spread Monitor'!$O$7:$O$850,MATCH("USD|7",'Spread Monitor'!$Y$7:$Y$850,0)),"") | I27: =IFERROR(INDEX('Spread Monitor'!$Q$7:$Q$850,MATCH("USD|7",'Spread Monitor'!$Y$7:$Y$850,0)),"") | J27: =IFERROR(INDEX('Spread Monitor'!$R$7:$R$850,MATCH("USD|7",'Spread Monitor'!$Y$7:$Y$850,0)),"") | K27: =IFERROR(INDEX('Spread Monitor'!$S$7:$S$850,MATCH("USD|7",'Spread Monitor'!$Y$7:$Y$850,0)),"")
A28: =IFERROR(INDEX('Spread Monitor'!$A$7:$A$850,MATCH("USD|8",'Spread Monitor'!$Y$7:$Y$850,0)),"") | B28: =IFERROR(INDEX('Spread Monitor'!$B$7:$B$850,MATCH("USD|8",'Spread Monitor'!$Y$7:$Y$850,0)),"") | C28: =IFERROR(INDEX('Spread Monitor'!$C$7:$C$850,MATCH("USD|8",'Spread Monitor'!$Y$7:$Y$850,0)),"") | D28: =IFERROR(INDEX('Spread Monitor'!$E$7:$E$850,MATCH("USD|8",'Spread Monitor'!$Y$7:$Y$850,0)),"") | E28: =IFERROR(INDEX('Spread Monitor'!$G$7:$G$850,MATCH("USD|8",'Spread Monitor'!$Y$7:$Y$850,0)),"") | F28: =IFERROR(INDEX('Spread Monitor'!$H$7:$H$850,MATCH("USD|8",'Spread Monitor'!$Y$7:$Y$850,0)),"") | G28: =IFERROR(INDEX('Spread Monitor'!$L$7:$L$850,MATCH("USD|8",'Spread Monitor'!$Y$7:$Y$850,0)),"") | H28: =IFERROR(INDEX('Spread Monitor'!$O$7:$O$850,MATCH("USD|8",'Spread Monitor'!$Y$7:$Y$850,0)),"") | I28: =IFERROR(INDEX('Spread Monitor'!$Q$7:$Q$850,MATCH("USD|8",'Spread Monitor'!$Y$7:$Y$850,0)),"") | J28: =IFERROR(INDEX('Spread Monitor'!$R$7:$R$850,MATCH("USD|8",'Spread Monitor'!$Y$7:$Y$850,0)),"") | K28: =IFERROR(INDEX('Spread Monitor'!$S$7:$S$850,MATCH("USD|8",'Spread Monitor'!$Y$7:$Y$850,0)),"")
A29: =IFERROR(INDEX('Spread Monitor'!$A$7:$A$850,MATCH("USD|9",'Spread Monitor'!$Y$7:$Y$850,0)),"") | B29: =IFERROR(INDEX('Spread Monitor'!$B$7:$B$850,MATCH("USD|9",'Spread Monitor'!$Y$7:$Y$850,0)),"") | C29: =IFERROR(INDEX('Spread Monitor'!$C$7:$C$850,MATCH("USD|9",'Spread Monitor'!$Y$7:$Y$850,0)),"") | D29: =IFERROR(INDEX('Spread Monitor'!$E$7:$E$850,MATCH("USD|9",'Spread Monitor'!$Y$7:$Y$850,0)),"") | E29: =IFERROR(INDEX('Spread Monitor'!$G$7:$G$850,MATCH("USD|9",'Spread Monitor'!$Y$7:$Y$850,0)),"") | F29: =IFERROR(INDEX('Spread Monitor'!$H$7:$H$850,MATCH("USD|9",'Spread Monitor'!$Y$7:$Y$850,0)),"") | G29: =IFERROR(INDEX('Spread Monitor'!$L$7:$L$850,MATCH("USD|9",'Spread Monitor'!$Y$7:$Y$850,0)),"") | H29: =IFERROR(INDEX('Spread Monitor'!$O$7:$O$850,MATCH("USD|9",'Spread Monitor'!$Y$7:$Y$850,0)),"") | I29: =IFERROR(INDEX('Spread Monitor'!$Q$7:$Q$850,MATCH("USD|9",'Spread Monitor'!$Y$7:$Y$850,0)),"") | J29: =IFERROR(INDEX('Spread Monitor'!$R$7:$R$850,MATCH("USD|9",'Spread Monitor'!$Y$7:$Y$850,0)),"") | K29: =IFERROR(INDEX('Spread Monitor'!$S$7:$S$850,MATCH("USD|9",'Spread Monitor'!$Y$7:$Y$850,0)),"")
A30: =IFERROR(INDEX('Spread Monitor'!$A$7:$A$850,MATCH("USD|10",'Spread Monitor'!$Y$7:$Y$850,0)),"") | B30: =IFERROR(INDEX('Spread Monitor'!$B$7:$B$850,MATCH("USD|10",'Spread Monitor'!$Y$7:$Y$850,0)),"") | C30: =IFERROR(INDEX('Spread Monitor'!$C$7:$C$850,MATCH("USD|10",'Spread Monitor'!$Y$7:$Y$850,0)),"") | D30: =IFERROR(INDEX('Spread Monitor'!$E$7:$E$850,MATCH("USD|10",'Spread Monitor'!$Y$7:$Y$850,0)),"") | E30: =IFERROR(INDEX('Spread Monitor'!$G$7:$G$850,MATCH("USD|10",'Spread Monitor'!$Y$7:$Y$850,0)),"") | F30: =IFERROR(INDEX('Spread Monitor'!$H$7:$H$850,MATCH("USD|10",'Spread Monitor'!$Y$7:$Y$850,0)),"") | G30: =IFERROR(INDEX('Spread Monitor'!$L$7:$L$850,MATCH("USD|10",'Spread Monitor'!$Y$7:$Y$850,0)),"") | H30: =IFERROR(INDEX('Spread Monitor'!$O$7:$O$850,MATCH("USD|10",'Spread Monitor'!$Y$7:$Y$850,0)),"") | I30: =IFERROR(INDEX('Spread Monitor'!$Q$7:$Q$850,MATCH("USD|10",'Spread Monitor'!$Y$7:$Y$850,0)),"") | J30: =IFERROR(INDEX('Spread Monitor'!$R$7:$R$850,MATCH("USD|10",'Spread Monitor'!$Y$7:$Y$850,0)),"") | K30: =IFERROR(INDEX('Spread Monitor'!$S$7:$S$850,MATCH("USD|10",'Spread Monitor'!$Y$7:$Y$850,0)),"")
A33: EUR - Top 10 that widened the most since 14.07.2026
A34: ISIN | B34: Company | C34: Company description | D34: Sector | E34: Ccy | F34: Rating | G34: Maturity | H34: YTW (%) | I34: Spread today (bp) | J34: Spread on anchor (bp) | K34: Spread change (bp)
A35: =IFERROR(INDEX('Spread Monitor'!$A$7:$A$850,MATCH("EUR|1",'Spread Monitor'!$X$7:$X$850,0)),"") | B35: =IFERROR(INDEX('Spread Monitor'!$B$7:$B$850,MATCH("EUR|1",'Spread Monitor'!$X$7:$X$850,0)),"") | C35: =IFERROR(INDEX('Spread Monitor'!$C$7:$C$850,MATCH("EUR|1",'Spread Monitor'!$X$7:$X$850,0)),"") | D35: =IFERROR(INDEX('Spread Monitor'!$E$7:$E$850,MATCH("EUR|1",'Spread Monitor'!$X$7:$X$850,0)),"") | E35: =IFERROR(INDEX('Spread Monitor'!$G$7:$G$850,MATCH("EUR|1",'Spread Monitor'!$X$7:$X$850,0)),"") | F35: =IFERROR(INDEX('Spread Monitor'!$H$7:$H$850,MATCH("EUR|1",'Spread Monitor'!$X$7:$X$850,0)),"") | G35: =IFERROR(INDEX('Spread Monitor'!$L$7:$L$850,MATCH("EUR|1",'Spread Monitor'!$X$7:$X$850,0)),"") | H35: =IFERROR(INDEX('Spread Monitor'!$O$7:$O$850,MATCH("EUR|1",'Spread Monitor'!$X$7:$X$850,0)),"") | I35: =IFERROR(INDEX('Spread Monitor'!$Q$7:$Q$850,MATCH("EUR|1",'Spread Monitor'!$X$7:$X$850,0)),"") | J35: =IFERROR(INDEX('Spread Monitor'!$R$7:$R$850,MATCH("EUR|1",'Spread Monitor'!$X$7:$X$850,0)),"") | K35: =IFERROR(INDEX('Spread Monitor'!$S$7:$S$850,MATCH("EUR|1",'Spread Monitor'!$X$7:$X$850,0)),"")
A36: =IFERROR(INDEX('Spread Monitor'!$A$7:$A$850,MATCH("EUR|2",'Spread Monitor'!$X$7:$X$850,0)),"") | B36: =IFERROR(INDEX('Spread Monitor'!$B$7:$B$850,MATCH("EUR|2",'Spread Monitor'!$X$7:$X$850,0)),"") | C36: =IFERROR(INDEX('Spread Monitor'!$C$7:$C$850,MATCH("EUR|2",'Spread Monitor'!$X$7:$X$850,0)),"") | D36: =IFERROR(INDEX('Spread Monitor'!$E$7:$E$850,MATCH("EUR|2",'Spread Monitor'!$X$7:$X$850,0)),"") | E36: =IFERROR(INDEX('Spread Monitor'!$G$7:$G$850,MATCH("EUR|2",'Spread Monitor'!$X$7:$X$850,0)),"") | F36: =IFERROR(INDEX('Spread Monitor'!$H$7:$H$850,MATCH("EUR|2",'Spread Monitor'!$X$7:$X$850,0)),"") | G36: =IFERROR(INDEX('Spread Monitor'!$L$7:$L$850,MATCH("EUR|2",'Spread Monitor'!$X$7:$X$850,0)),"") | H36: =IFERROR(INDEX('Spread Monitor'!$O$7:$O$850,MATCH("EUR|2",'Spread Monitor'!$X$7:$X$850,0)),"") | I36: =IFERROR(INDEX('Spread Monitor'!$Q$7:$Q$850,MATCH("EUR|2",'Spread Monitor'!$X$7:$X$850,0)),"") | J36: =IFERROR(INDEX('Spread Monitor'!$R$7:$R$850,MATCH("EUR|2",'Spread Monitor'!$X$7:$X$850,0)),"") | K36: =IFERROR(INDEX('Spread Monitor'!$S$7:$S$850,MATCH("EUR|2",'Spread Monitor'!$X$7:$X$850,0)),"")
A37: =IFERROR(INDEX('Spread Monitor'!$A$7:$A$850,MATCH("EUR|3",'Spread Monitor'!$X$7:$X$850,0)),"") | B37: =IFERROR(INDEX('Spread Monitor'!$B$7:$B$850,MATCH("EUR|3",'Spread Monitor'!$X$7:$X$850,0)),"") | C37: =IFERROR(INDEX('Spread Monitor'!$C$7:$C$850,MATCH("EUR|3",'Spread Monitor'!$X$7:$X$850,0)),"") | D37: =IFERROR(INDEX('Spread Monitor'!$E$7:$E$850,MATCH("EUR|3",'Spread Monitor'!$X$7:$X$850,0)),"") | E37: =IFERROR(INDEX('Spread Monitor'!$G$7:$G$850,MATCH("EUR|3",'Spread Monitor'!$X$7:$X$850,0)),"") | F37: =IFERROR(INDEX('Spread Monitor'!$H$7:$H$850,MATCH("EUR|3",'Spread Monitor'!$X$7:$X$850,0)),"") | G37: =IFERROR(INDEX('Spread Monitor'!$L$7:$L$850,MATCH("EUR|3",'Spread Monitor'!$X$7:$X$850,0)),"") | H37: =IFERROR(INDEX('Spread Monitor'!$O$7:$O$850,MATCH("EUR|3",'Spread Monitor'!$X$7:$X$850,0)),"") | I37: =IFERROR(INDEX('Spread Monitor'!$Q$7:$Q$850,MATCH("EUR|3",'Spread Monitor'!$X$7:$X$850,0)),"") | J37: =IFERROR(INDEX('Spread Monitor'!$R$7:$R$850,MATCH("EUR|3",'Spread Monitor'!$X$7:$X$850,0)),"") | K37: =IFERROR(INDEX('Spread Monitor'!$S$7:$S$850,MATCH("EUR|3",'Spread Monitor'!$X$7:$X$850,0)),"")
A38: =IFERROR(INDEX('Spread Monitor'!$A$7:$A$850,MATCH("EUR|4",'Spread Monitor'!$X$7:$X$850,0)),"") | B38: =IFERROR(INDEX('Spread Monitor'!$B$7:$B$850,MATCH("EUR|4",'Spread Monitor'!$X$7:$X$850,0)),"") | C38: =IFERROR(INDEX('Spread Monitor'!$C$7:$C$850,MATCH("EUR|4",'Spread Monitor'!$X$7:$X$850,0)),"") | D38: =IFERROR(INDEX('Spread Monitor'!$E$7:$E$850,MATCH("EUR|4",'Spread Monitor'!$X$7:$X$850,0)),"") | E38: =IFERROR(INDEX('Spread Monitor'!$G$7:$G$850,MATCH("EUR|4",'Spread Monitor'!$X$7:$X$850,0)),"") | F38: =IFERROR(INDEX('Spread Monitor'!$H$7:$H$850,MATCH("EUR|4",'Spread Monitor'!$X$7:$X$850,0)),"") | G38: =IFERROR(INDEX('Spread Monitor'!$L$7:$L$850,MATCH("EUR|4",'Spread Monitor'!$X$7:$X$850,0)),"") | H38: =IFERROR(INDEX('Spread Monitor'!$O$7:$O$850,MATCH("EUR|4",'Spread Monitor'!$X$7:$X$850,0)),"") | I38: =IFERROR(INDEX('Spread Monitor'!$Q$7:$Q$850,MATCH("EUR|4",'Spread Monitor'!$X$7:$X$850,0)),"") | J38: =IFERROR(INDEX('Spread Monitor'!$R$7:$R$850,MATCH("EUR|4",'Spread Monitor'!$X$7:$X$850,0)),"") | K38: =IFERROR(INDEX('Spread Monitor'!$S$7:$S$850,MATCH("EUR|4",'Spread Monitor'!$X$7:$X$850,0)),"")
A39: =IFERROR(INDEX('Spread Monitor'!$A$7:$A$850,MATCH("EUR|5",'Spread Monitor'!$X$7:$X$850,0)),"") | B39: =IFERROR(INDEX('Spread Monitor'!$B$7:$B$850,MATCH("EUR|5",'Spread Monitor'!$X$7:$X$850,0)),"") | C39: =IFERROR(INDEX('Spread Monitor'!$C$7:$C$850,MATCH("EUR|5",'Spread Monitor'!$X$7:$X$850,0)),"") | D39: =IFERROR(INDEX('Spread Monitor'!$E$7:$E$850,MATCH("EUR|5",'Spread Monitor'!$X$7:$X$850,0)),"") | E39: =IFERROR(INDEX('Spread Monitor'!$G$7:$G$850,MATCH("EUR|5",'Spread Monitor'!$X$7:$X$850,0)),"") | F39: =IFERROR(INDEX('Spread Monitor'!$H$7:$H$850,MATCH("EUR|5",'Spread Monitor'!$X$7:$X$850,0)),"") | G39: =IFERROR(INDEX('Spread Monitor'!$L$7:$L$850,MATCH("EUR|5",'Spread Monitor'!$X$7:$X$850,0)),"") | H39: =IFERROR(INDEX('Spread Monitor'!$O$7:$O$850,MATCH("EUR|5",'Spread Monitor'!$X$7:$X$850,0)),"") | I39: =IFERROR(INDEX('Spread Monitor'!$Q$7:$Q$850,MATCH("EUR|5",'Spread Monitor'!$X$7:$X$850,0)),"") | J39: =IFERROR(INDEX('Spread Monitor'!$R$7:$R$850,MATCH("EUR|5",'Spread Monitor'!$X$7:$X$850,0)),"") | K39: =IFERROR(INDEX('Spread Monitor'!$S$7:$S$850,MATCH("EUR|5",'Spread Monitor'!$X$7:$X$850,0)),"")
A40: =IFERROR(INDEX('Spread Monitor'!$A$7:$A$850,MATCH("EUR|6",'Spread Monitor'!$X$7:$X$850,0)),"") | B40: =IFERROR(INDEX('Spread Monitor'!$B$7:$B$850,MATCH("EUR|6",'Spread Monitor'!$X$7:$X$850,0)),"") | C40: =IFERROR(INDEX('Spread Monitor'!$C$7:$C$850,MATCH("EUR|6",'Spread Monitor'!$X$7:$X$850,0)),"") | D40: =IFERROR(INDEX('Spread Monitor'!$E$7:$E$850,MATCH("EUR|6",'Spread Monitor'!$X$7:$X$850,0)),"") | E40: =IFERROR(INDEX('Spread Monitor'!$G$7:$G$850,MATCH("EUR|6",'Spread Monitor'!$X$7:$X$850,0)),"") | F40: =IFERROR(INDEX('Spread Monitor'!$H$7:$H$850,MATCH("EUR|6",'Spread Monitor'!$X$7:$X$850,0)),"") | G40: =IFERROR(INDEX('Spread Monitor'!$L$7:$L$850,MATCH("EUR|6",'Spread Monitor'!$X$7:$X$850,0)),"") | H40: =IFERROR(INDEX('Spread Monitor'!$O$7:$O$850,MATCH("EUR|6",'Spread Monitor'!$X$7:$X$850,0)),"") | I40: =IFERROR(INDEX('Spread Monitor'!$Q$7:$Q$850,MATCH("EUR|6",'Spread Monitor'!$X$7:$X$850,0)),"") | J40: =IFERROR(INDEX('Spread Monitor'!$R$7:$R$850,MATCH("EUR|6",'Spread Monitor'!$X$7:$X$850,0)),"") | K40: =IFERROR(INDEX('Spread Monitor'!$S$7:$S$850,MATCH("EUR|6",'Spread Monitor'!$X$7:$X$850,0)),"")
A41: =IFERROR(INDEX('Spread Monitor'!$A$7:$A$850,MATCH("EUR|7",'Spread Monitor'!$X$7:$X$850,0)),"") | B41: =IFERROR(INDEX('Spread Monitor'!$B$7:$B$850,MATCH("EUR|7",'Spread Monitor'!$X$7:$X$850,0)),"") | C41: =IFERROR(INDEX('Spread Monitor'!$C$7:$C$850,MATCH("EUR|7",'Spread Monitor'!$X$7:$X$850,0)),"") | D41: =IFERROR(INDEX('Spread Monitor'!$E$7:$E$850,MATCH("EUR|7",'Spread Monitor'!$X$7:$X$850,0)),"") | E41: =IFERROR(INDEX('Spread Monitor'!$G$7:$G$850,MATCH("EUR|7",'Spread Monitor'!$X$7:$X$850,0)),"") | F41: =IFERROR(INDEX('Spread Monitor'!$H$7:$H$850,MATCH("EUR|7",'Spread Monitor'!$X$7:$X$850,0)),"") | G41: =IFERROR(INDEX('Spread Monitor'!$L$7:$L$850,MATCH("EUR|7",'Spread Monitor'!$X$7:$X$850,0)),"") | H41: =IFERROR(INDEX('Spread Monitor'!$O$7:$O$850,MATCH("EUR|7",'Spread Monitor'!$X$7:$X$850,0)),"") | I41: =IFERROR(INDEX('Spread Monitor'!$Q$7:$Q$850,MATCH("EUR|7",'Spread Monitor'!$X$7:$X$850,0)),"") | J41: =IFERROR(INDEX('Spread Monitor'!$R$7:$R$850,MATCH("EUR|7",'Spread Monitor'!$X$7:$X$850,0)),"") | K41: =IFERROR(INDEX('Spread Monitor'!$S$7:$S$850,MATCH("EUR|7",'Spread Monitor'!$X$7:$X$850,0)),"")
A42: =IFERROR(INDEX('Spread Monitor'!$A$7:$A$850,MATCH("EUR|8",'Spread Monitor'!$X$7:$X$850,0)),"") | B42: =IFERROR(INDEX('Spread Monitor'!$B$7:$B$850,MATCH("EUR|8",'Spread Monitor'!$X$7:$X$850,0)),"") | C42: =IFERROR(INDEX('Spread Monitor'!$C$7:$C$850,MATCH("EUR|8",'Spread Monitor'!$X$7:$X$850,0)),"") | D42: =IFERROR(INDEX('Spread Monitor'!$E$7:$E$850,MATCH("EUR|8",'Spread Monitor'!$X$7:$X$850,0)),"") | E42: =IFERROR(INDEX('Spread Monitor'!$G$7:$G$850,MATCH("EUR|8",'Spread Monitor'!$X$7:$X$850,0)),"") | F42: =IFERROR(INDEX('Spread Monitor'!$H$7:$H$850,MATCH("EUR|8",'Spread Monitor'!$X$7:$X$850,0)),"") | G42: =IFERROR(INDEX('Spread Monitor'!$L$7:$L$850,MATCH("EUR|8",'Spread Monitor'!$X$7:$X$850,0)),"") | H42: =IFERROR(INDEX('Spread Monitor'!$O$7:$O$850,MATCH("EUR|8",'Spread Monitor'!$X$7:$X$850,0)),"") | I42: =IFERROR(INDEX('Spread Monitor'!$Q$7:$Q$850,MATCH("EUR|8",'Spread Monitor'!$X$7:$X$850,0)),"") | J42: =IFERROR(INDEX('Spread Monitor'!$R$7:$R$850,MATCH("EUR|8",'Spread Monitor'!$X$7:$X$850,0)),"") | K42: =IFERROR(INDEX('Spread Monitor'!$S$7:$S$850,MATCH("EUR|8",'Spread Monitor'!$X$7:$X$850,0)),"")
A43: =IFERROR(INDEX('Spread Monitor'!$A$7:$A$850,MATCH("EUR|9",'Spread Monitor'!$X$7:$X$850,0)),"") | B43: =IFERROR(INDEX('Spread Monitor'!$B$7:$B$850,MATCH("EUR|9",'Spread Monitor'!$X$7:$X$850,0)),"") | C43: =IFERROR(INDEX('Spread Monitor'!$C$7:$C$850,MATCH("EUR|9",'Spread Monitor'!$X$7:$X$850,0)),"") | D43: =IFERROR(INDEX('Spread Monitor'!$E$7:$E$850,MATCH("EUR|9",'Spread Monitor'!$X$7:$X$850,0)),"") | E43: =IFERROR(INDEX('Spread Monitor'!$G$7:$G$850,MATCH("EUR|9",'Spread Monitor'!$X$7:$X$850,0)),"") | F43: =IFERROR(INDEX('Spread Monitor'!$H$7:$H$850,MATCH("EUR|9",'Spread Monitor'!$X$7:$X$850,0)),"") | G43: =IFERROR(INDEX('Spread Monitor'!$L$7:$L$850,MATCH("EUR|9",'Spread Monitor'!$X$7:$X$850,0)),"") | H43: =IFERROR(INDEX('Spread Monitor'!$O$7:$O$850,MATCH("EUR|9",'Spread Monitor'!$X$7:$X$850,0)),"") | I43: =IFERROR(INDEX('Spread Monitor'!$Q$7:$Q$850,MATCH("EUR|9",'Spread Monitor'!$X$7:$X$850,0)),"") | J43: =IFERROR(INDEX('Spread Monitor'!$R$7:$R$850,MATCH("EUR|9",'Spread Monitor'!$X$7:$X$850,0)),"") | K43: =IFERROR(INDEX('Spread Monitor'!$S$7:$S$850,MATCH("EUR|9",'Spread Monitor'!$X$7:$X$850,0)),"")
A44: =IFERROR(INDEX('Spread Monitor'!$A$7:$A$850,MATCH("EUR|10",'Spread Monitor'!$X$7:$X$850,0)),"") | B44: =IFERROR(INDEX('Spread Monitor'!$B$7:$B$850,MATCH("EUR|10",'Spread Monitor'!$X$7:$X$850,0)),"") | C44: =IFERROR(INDEX('Spread Monitor'!$C$7:$C$850,MATCH("EUR|10",'Spread Monitor'!$X$7:$X$850,0)),"") | D44: =IFERROR(INDEX('Spread Monitor'!$E$7:$E$850,MATCH("EUR|10",'Spread Monitor'!$X$7:$X$850,0)),"") | E44: =IFERROR(INDEX('Spread Monitor'!$G$7:$G$850,MATCH("EUR|10",'Spread Monitor'!$X$7:$X$850,0)),"") | F44: =IFERROR(INDEX('Spread Monitor'!$H$7:$H$850,MATCH("EUR|10",'Spread Monitor'!$X$7:$X$850,0)),"") | G44: =IFERROR(INDEX('Spread Monitor'!$L$7:$L$850,MATCH("EUR|10",'Spread Monitor'!$X$7:$X$850,0)),"") | H44: =IFERROR(INDEX('Spread Monitor'!$O$7:$O$850,MATCH("EUR|10",'Spread Monitor'!$X$7:$X$850,0)),"") | I44: =IFERROR(INDEX('Spread Monitor'!$Q$7:$Q$850,MATCH("EUR|10",'Spread Monitor'!$X$7:$X$850,0)),"") | J44: =IFERROR(INDEX('Spread Monitor'!$R$7:$R$850,MATCH("EUR|10",'Spread Monitor'!$X$7:$X$850,0)),"") | K44: =IFERROR(INDEX('Spread Monitor'!$S$7:$S$850,MATCH("EUR|10",'Spread Monitor'!$X$7:$X$850,0)),"")
A47: EUR - Top 10 that tightened the most since 14.07.2026
A48: ISIN | B48: Company | C48: Company description | D48: Sector | E48: Ccy | F48: Rating | G48: Maturity | H48: YTW (%) | I48: Spread today (bp) | J48: Spread on anchor (bp) | K48: Spread change (bp)
A49: =IFERROR(INDEX('Spread Monitor'!$A$7:$A$850,MATCH("EUR|1",'Spread Monitor'!$Y$7:$Y$850,0)),"") | B49: =IFERROR(INDEX('Spread Monitor'!$B$7:$B$850,MATCH("EUR|1",'Spread Monitor'!$Y$7:$Y$850,0)),"") | C49: =IFERROR(INDEX('Spread Monitor'!$C$7:$C$850,MATCH("EUR|1",'Spread Monitor'!$Y$7:$Y$850,0)),"") | D49: =IFERROR(INDEX('Spread Monitor'!$E$7:$E$850,MATCH("EUR|1",'Spread Monitor'!$Y$7:$Y$850,0)),"") | E49: =IFERROR(INDEX('Spread Monitor'!$G$7:$G$850,MATCH("EUR|1",'Spread Monitor'!$Y$7:$Y$850,0)),"") | F49: =IFERROR(INDEX('Spread Monitor'!$H$7:$H$850,MATCH("EUR|1",'Spread Monitor'!$Y$7:$Y$850,0)),"") | G49: =IFERROR(INDEX('Spread Monitor'!$L$7:$L$850,MATCH("EUR|1",'Spread Monitor'!$Y$7:$Y$850,0)),"") | H49: =IFERROR(INDEX('Spread Monitor'!$O$7:$O$850,MATCH("EUR|1",'Spread Monitor'!$Y$7:$Y$850,0)),"") | I49: =IFERROR(INDEX('Spread Monitor'!$Q$7:$Q$850,MATCH("EUR|1",'Spread Monitor'!$Y$7:$Y$850,0)),"") | J49: =IFERROR(INDEX('Spread Monitor'!$R$7:$R$850,MATCH("EUR|1",'Spread Monitor'!$Y$7:$Y$850,0)),"") | K49: =IFERROR(INDEX('Spread Monitor'!$S$7:$S$850,MATCH("EUR|1",'Spread Monitor'!$Y$7:$Y$850,0)),"")
A50: =IFERROR(INDEX('Spread Monitor'!$A$7:$A$850,MATCH("EUR|2",'Spread Monitor'!$Y$7:$Y$850,0)),"") | B50: =IFERROR(INDEX('Spread Monitor'!$B$7:$B$850,MATCH("EUR|2",'Spread Monitor'!$Y$7:$Y$850,0)),"") | C50: =IFERROR(INDEX('Spread Monitor'!$C$7:$C$850,MATCH("EUR|2",'Spread Monitor'!$Y$7:$Y$850,0)),"") | D50: =IFERROR(INDEX('Spread Monitor'!$E$7:$E$850,MATCH("EUR|2",'Spread Monitor'!$Y$7:$Y$850,0)),"") | E50: =IFERROR(INDEX('Spread Monitor'!$G$7:$G$850,MATCH("EUR|2",'Spread Monitor'!$Y$7:$Y$850,0)),"") | F50: =IFERROR(INDEX('Spread Monitor'!$H$7:$H$850,MATCH("EUR|2",'Spread Monitor'!$Y$7:$Y$850,0)),"") | G50: =IFERROR(INDEX('Spread Monitor'!$L$7:$L$850,MATCH("EUR|2",'Spread Monitor'!$Y$7:$Y$850,0)),"") | H50: =IFERROR(INDEX('Spread Monitor'!$O$7:$O$850,MATCH("EUR|2",'Spread Monitor'!$Y$7:$Y$850,0)),"") | I50: =IFERROR(INDEX('Spread Monitor'!$Q$7:$Q$850,MATCH("EUR|2",'Spread Monitor'!$Y$7:$Y$850,0)),"") | J50: =IFERROR(INDEX('Spread Monitor'!$R$7:$R$850,MATCH("EUR|2",'Spread Monitor'!$Y$7:$Y$850,0)),"") | K50: =IFERROR(INDEX('Spread Monitor'!$S$7:$S$850,MATCH("EUR|2",'Spread Monitor'!$Y$7:$Y$850,0)),"")
A51: =IFERROR(INDEX('Spread Monitor'!$A$7:$A$850,MATCH("EUR|3",'Spread Monitor'!$Y$7:$Y$850,0)),"") | B51: =IFERROR(INDEX('Spread Monitor'!$B$7:$B$850,MATCH("EUR|3",'Spread Monitor'!$Y$7:$Y$850,0)),"") | C51: =IFERROR(INDEX('Spread Monitor'!$C$7:$C$850,MATCH("EUR|3",'Spread Monitor'!$Y$7:$Y$850,0)),"") | D51: =IFERROR(INDEX('Spread Monitor'!$E$7:$E$850,MATCH("EUR|3",'Spread Monitor'!$Y$7:$Y$850,0)),"") | E51: =IFERROR(INDEX('Spread Monitor'!$G$7:$G$850,MATCH("EUR|3",'Spread Monitor'!$Y$7:$Y$850,0)),"") | F51: =IFERROR(INDEX('Spread Monitor'!$H$7:$H$850,MATCH("EUR|3",'Spread Monitor'!$Y$7:$Y$850,0)),"") | G51: =IFERROR(INDEX('Spread Monitor'!$L$7:$L$850,MATCH("EUR|3",'Spread Monitor'!$Y$7:$Y$850,0)),"") | H51: =IFERROR(INDEX('Spread Monitor'!$O$7:$O$850,MATCH("EUR|3",'Spread Monitor'!$Y$7:$Y$850,0)),"") | I51: =IFERROR(INDEX('Spread Monitor'!$Q$7:$Q$850,MATCH("EUR|3",'Spread Monitor'!$Y$7:$Y$850,0)),"") | J51: =IFERROR(INDEX('Spread Monitor'!$R$7:$R$850,MATCH("EUR|3",'Spread Monitor'!$Y$7:$Y$850,0)),"") | K51: =IFERROR(INDEX('Spread Monitor'!$S$7:$S$850,MATCH("EUR|3",'Spread Monitor'!$Y$7:$Y$850,0)),"")
A52: =IFERROR(INDEX('Spread Monitor'!$A$7:$A$850,MATCH("EUR|4",'Spread Monitor'!$Y$7:$Y$850,0)),"") | B52: =IFERROR(INDEX('Spread Monitor'!$B$7:$B$850,MATCH("EUR|4",'Spread Monitor'!$Y$7:$Y$850,0)),"") | C52: =IFERROR(INDEX('Spread Monitor'!$C$7:$C$850,MATCH("EUR|4",'Spread Monitor'!$Y$7:$Y$850,0)),"") | D52: =IFERROR(INDEX('Spread Monitor'!$E$7:$E$850,MATCH("EUR|4",'Spread Monitor'!$Y$7:$Y$850,0)),"") | E52: =IFERROR(INDEX('Spread Monitor'!$G$7:$G$850,MATCH("EUR|4",'Spread Monitor'!$Y$7:$Y$850,0)),"") | F52: =IFERROR(INDEX('Spread Monitor'!$H$7:$H$850,MATCH("EUR|4",'Spread Monitor'!$Y$7:$Y$850,0)),"") | G52: =IFERROR(INDEX('Spread Monitor'!$L$7:$L$850,MATCH("EUR|4",'Spread Monitor'!$Y$7:$Y$850,0)),"") | H52: =IFERROR(INDEX('Spread Monitor'!$O$7:$O$850,MATCH("EUR|4",'Spread Monitor'!$Y$7:$Y$850,0)),"") | I52: =IFERROR(INDEX('Spread Monitor'!$Q$7:$Q$850,MATCH("EUR|4",'Spread Monitor'!$Y$7:$Y$850,0)),"") | J52: =IFERROR(INDEX('Spread Monitor'!$R$7:$R$850,MATCH("EUR|4",'Spread Monitor'!$Y$7:$Y$850,0)),"") | K52: =IFERROR(INDEX('Spread Monitor'!$S$7:$S$850,MATCH("EUR|4",'Spread Monitor'!$Y$7:$Y$850,0)),"")
A53: =IFERROR(INDEX('Spread Monitor'!$A$7:$A$850,MATCH("EUR|5",'Spread Monitor'!$Y$7:$Y$850,0)),"") | B53: =IFERROR(INDEX('Spread Monitor'!$B$7:$B$850,MATCH("EUR|5",'Spread Monitor'!$Y$7:$Y$850,0)),"") | C53: =IFERROR(INDEX('Spread Monitor'!$C$7:$C$850,MATCH("EUR|5",'Spread Monitor'!$Y$7:$Y$850,0)),"") | D53: =IFERROR(INDEX('Spread Monitor'!$E$7:$E$850,MATCH("EUR|5",'Spread Monitor'!$Y$7:$Y$850,0)),"") | E53: =IFERROR(INDEX('Spread Monitor'!$G$7:$G$850,MATCH("EUR|5",'Spread Monitor'!$Y$7:$Y$850,0)),"") | F53: =IFERROR(INDEX('Spread Monitor'!$H$7:$H$850,MATCH("EUR|5",'Spread Monitor'!$Y$7:$Y$850,0)),"") | G53: =IFERROR(INDEX('Spread Monitor'!$L$7:$L$850,MATCH("EUR|5",'Spread Monitor'!$Y$7:$Y$850,0)),"") | H53: =IFERROR(INDEX('Spread Monitor'!$O$7:$O$850,MATCH("EUR|5",'Spread Monitor'!$Y$7:$Y$850,0)),"") | I53: =IFERROR(INDEX('Spread Monitor'!$Q$7:$Q$850,MATCH("EUR|5",'Spread Monitor'!$Y$7:$Y$850,0)),"") | J53: =IFERROR(INDEX('Spread Monitor'!$R$7:$R$850,MATCH("EUR|5",'Spread Monitor'!$Y$7:$Y$850,0)),"") | K53: =IFERROR(INDEX('Spread Monitor'!$S$7:$S$850,MATCH("EUR|5",'Spread Monitor'!$Y$7:$Y$850,0)),"")
A54: =IFERROR(INDEX('Spread Monitor'!$A$7:$A$850,MATCH("EUR|6",'Spread Monitor'!$Y$7:$Y$850,0)),"") | B54: =IFERROR(INDEX('Spread Monitor'!$B$7:$B$850,MATCH("EUR|6",'Spread Monitor'!$Y$7:$Y$850,0)),"") | C54: =IFERROR(INDEX('Spread Monitor'!$C$7:$C$850,MATCH("EUR|6",'Spread Monitor'!$Y$7:$Y$850,0)),"") | D54: =IFERROR(INDEX('Spread Monitor'!$E$7:$E$850,MATCH("EUR|6",'Spread Monitor'!$Y$7:$Y$850,0)),"") | E54: =IFERROR(INDEX('Spread Monitor'!$G$7:$G$850,MATCH("EUR|6",'Spread Monitor'!$Y$7:$Y$850,0)),"") | F54: =IFERROR(INDEX('Spread Monitor'!$H$7:$H$850,MATCH("EUR|6",'Spread Monitor'!$Y$7:$Y$850,0)),"") | G54: =IFERROR(INDEX('Spread Monitor'!$L$7:$L$850,MATCH("EUR|6",'Spread Monitor'!$Y$7:$Y$850,0)),"") | H54: =IFERROR(INDEX('Spread Monitor'!$O$7:$O$850,MATCH("EUR|6",'Spread Monitor'!$Y$7:$Y$850,0)),"") | I54: =IFERROR(INDEX('Spread Monitor'!$Q$7:$Q$850,MATCH("EUR|6",'Spread Monitor'!$Y$7:$Y$850,0)),"") | J54: =IFERROR(INDEX('Spread Monitor'!$R$7:$R$850,MATCH("EUR|6",'Spread Monitor'!$Y$7:$Y$850,0)),"") | K54: =IFERROR(INDEX('Spread Monitor'!$S$7:$S$850,MATCH("EUR|6",'Spread Monitor'!$Y$7:$Y$850,0)),"")
A55: =IFERROR(INDEX('Spread Monitor'!$A$7:$A$850,MATCH("EUR|7",'Spread Monitor'!$Y$7:$Y$850,0)),"") | B55: =IFERROR(INDEX('Spread Monitor'!$B$7:$B$850,MATCH("EUR|7",'Spread Monitor'!$Y$7:$Y$850,0)),"") | C55: =IFERROR(INDEX('Spread Monitor'!$C$7:$C$850,MATCH("EUR|7",'Spread Monitor'!$Y$7:$Y$850,0)),"") | D55: =IFERROR(INDEX('Spread Monitor'!$E$7:$E$850,MATCH("EUR|7",'Spread Monitor'!$Y$7:$Y$850,0)),"") | E55: =IFERROR(INDEX('Spread Monitor'!$G$7:$G$850,MATCH("EUR|7",'Spread Monitor'!$Y$7:$Y$850,0)),"") | F55: =IFERROR(INDEX('Spread Monitor'!$H$7:$H$850,MATCH("EUR|7",'Spread Monitor'!$Y$7:$Y$850,0)),"") | G55: =IFERROR(INDEX('Spread Monitor'!$L$7:$L$850,MATCH("EUR|7",'Spread Monitor'!$Y$7:$Y$850,0)),"") | H55: =IFERROR(INDEX('Spread Monitor'!$O$7:$O$850,MATCH("EUR|7",'Spread Monitor'!$Y$7:$Y$850,0)),"") | I55: =IFERROR(INDEX('Spread Monitor'!$Q$7:$Q$850,MATCH("EUR|7",'Spread Monitor'!$Y$7:$Y$850,0)),"") | J55: =IFERROR(INDEX('Spread Monitor'!$R$7:$R$850,MATCH("EUR|7",'Spread Monitor'!$Y$7:$Y$850,0)),"") | K55: =IFERROR(INDEX('Spread Monitor'!$S$7:$S$850,MATCH("EUR|7",'Spread Monitor'!$Y$7:$Y$850,0)),"")
A56: =IFERROR(INDEX('Spread Monitor'!$A$7:$A$850,MATCH("EUR|8",'Spread Monitor'!$Y$7:$Y$850,0)),"") | B56: =IFERROR(INDEX('Spread Monitor'!$B$7:$B$850,MATCH("EUR|8",'Spread Monitor'!$Y$7:$Y$850,0)),"") | C56: =IFERROR(INDEX('Spread Monitor'!$C$7:$C$850,MATCH("EUR|8",'Spread Monitor'!$Y$7:$Y$850,0)),"") | D56: =IFERROR(INDEX('Spread Monitor'!$E$7:$E$850,MATCH("EUR|8",'Spread Monitor'!$Y$7:$Y$850,0)),"") | E56: =IFERROR(INDEX('Spread Monitor'!$G$7:$G$850,MATCH("EUR|8",'Spread Monitor'!$Y$7:$Y$850,0)),"") | F56: =IFERROR(INDEX('Spread Monitor'!$H$7:$H$850,MATCH("EUR|8",'Spread Monitor'!$Y$7:$Y$850,0)),"") | G56: =IFERROR(INDEX('Spread Monitor'!$L$7:$L$850,MATCH("EUR|8",'Spread Monitor'!$Y$7:$Y$850,0)),"") | H56: =IFERROR(INDEX('Spread Monitor'!$O$7:$O$850,MATCH("EUR|8",'Spread Monitor'!$Y$7:$Y$850,0)),"") | I56: =IFERROR(INDEX('Spread Monitor'!$Q$7:$Q$850,MATCH("EUR|8",'Spread Monitor'!$Y$7:$Y$850,0)),"") | J56: =IFERROR(INDEX('Spread Monitor'!$R$7:$R$850,MATCH("EUR|8",'Spread Monitor'!$Y$7:$Y$850,0)),"") | K56: =IFERROR(INDEX('Spread Monitor'!$S$7:$S$850,MATCH("EUR|8",'Spread Monitor'!$Y$7:$Y$850,0)),"")
A57: =IFERROR(INDEX('Spread Monitor'!$A$7:$A$850,MATCH("EUR|9",'Spread Monitor'!$Y$7:$Y$850,0)),"") | B57: =IFERROR(INDEX('Spread Monitor'!$B$7:$B$850,MATCH("EUR|9",'Spread Monitor'!$Y$7:$Y$850,0)),"") | C57: =IFERROR(INDEX('Spread Monitor'!$C$7:$C$850,MATCH("EUR|9",'Spread Monitor'!$Y$7:$Y$850,0)),"") | D57: =IFERROR(INDEX('Spread Monitor'!$E$7:$E$850,MATCH("EUR|9",'Spread Monitor'!$Y$7:$Y$850,0)),"") | E57: =IFERROR(INDEX('Spread Monitor'!$G$7:$G$850,MATCH("EUR|9",'Spread Monitor'!$Y$7:$Y$850,0)),"") | F57: =IFERROR(INDEX('Spread Monitor'!$H$7:$H$850,MATCH("EUR|9",'Spread Monitor'!$Y$7:$Y$850,0)),"") | G57: =IFERROR(INDEX('Spread Monitor'!$L$7:$L$850,MATCH("EUR|9",'Spread Monitor'!$Y$7:$Y$850,0)),"") | H57: =IFERROR(INDEX('Spread Monitor'!$O$7:$O$850,MATCH("EUR|9",'Spread Monitor'!$Y$7:$Y$850,0)),"") | I57: =IFERROR(INDEX('Spread Monitor'!$Q$7:$Q$850,MATCH("EUR|9",'Spread Monitor'!$Y$7:$Y$850,0)),"") | J57: =IFERROR(INDEX('Spread Monitor'!$R$7:$R$850,MATCH("EUR|9",'Spread Monitor'!$Y$7:$Y$850,0)),"") | K57: =IFERROR(INDEX('Spread Monitor'!$S$7:$S$850,MATCH("EUR|9",'Spread Monitor'!$Y$7:$Y$850,0)),"")
A58: =IFERROR(INDEX('Spread Monitor'!$A$7:$A$850,MATCH("EUR|10",'Spread Monitor'!$Y$7:$Y$850,0)),"") | B58: =IFERROR(INDEX('Spread Monitor'!$B$7:$B$850,MATCH("EUR|10",'Spread Monitor'!$Y$7:$Y$850,0)),"") | C58: =IFERROR(INDEX('Spread Monitor'!$C$7:$C$850,MATCH("EUR|10",'Spread Monitor'!$Y$7:$Y$850,0)),"") | D58: =IFERROR(INDEX('Spread Monitor'!$E$7:$E$850,MATCH("EUR|10",'Spread Monitor'!$Y$7:$Y$850,0)),"") | E58: =IFERROR(INDEX('Spread Monitor'!$G$7:$G$850,MATCH("EUR|10",'Spread Monitor'!$Y$7:$Y$850,0)),"") | F58: =IFERROR(INDEX('Spread Monitor'!$H$7:$H$850,MATCH("EUR|10",'Spread Monitor'!$Y$7:$Y$850,0)),"") | G58: =IFERROR(INDEX('Spread Monitor'!$L$7:$L$850,MATCH("EUR|10",'Spread Monitor'!$Y$7:$Y$850,0)),"") | H58: =IFERROR(INDEX('Spread Monitor'!$O$7:$O$850,MATCH("EUR|10",'Spread Monitor'!$Y$7:$Y$850,0)),"") | I58: =IFERROR(INDEX('Spread Monitor'!$Q$7:$Q$850,MATCH("EUR|10",'Spread Monitor'!$Y$7:$Y$850,0)),"") | J58: =IFERROR(INDEX('Spread Monitor'!$R$7:$R$850,MATCH("EUR|10",'Spread Monitor'!$Y$7:$Y$850,0)),"") | K58: =IFERROR(INDEX('Spread Monitor'!$S$7:$S$850,MATCH("EUR|10",'Spread Monitor'!$Y$7:$Y$850,0)),"")
A61: GBP - Top 10 that widened the most since 14.07.2026
A62: ISIN | B62: Company | C62: Company description | D62: Sector | E62: Ccy | F62: Rating | G62: Maturity | H62: YTW (%) | I62: Spread today (bp) | J62: Spread on anchor (bp) | K62: Spread change (bp)
A63: =IFERROR(INDEX('Spread Monitor'!$A$7:$A$850,MATCH("GBP|1",'Spread Monitor'!$X$7:$X$850,0)),"") | B63: =IFERROR(INDEX('Spread Monitor'!$B$7:$B$850,MATCH("GBP|1",'Spread Monitor'!$X$7:$X$850,0)),"") | C63: =IFERROR(INDEX('Spread Monitor'!$C$7:$C$850,MATCH("GBP|1",'Spread Monitor'!$X$7:$X$850,0)),"") | D63: =IFERROR(INDEX('Spread Monitor'!$E$7:$E$850,MATCH("GBP|1",'Spread Monitor'!$X$7:$X$850,0)),"") | E63: =IFERROR(INDEX('Spread Monitor'!$G$7:$G$850,MATCH("GBP|1",'Spread Monitor'!$X$7:$X$850,0)),"") | F63: =IFERROR(INDEX('Spread Monitor'!$H$7:$H$850,MATCH("GBP|1",'Spread Monitor'!$X$7:$X$850,0)),"") | G63: =IFERROR(INDEX('Spread Monitor'!$L$7:$L$850,MATCH("GBP|1",'Spread Monitor'!$X$7:$X$850,0)),"") | H63: =IFERROR(INDEX('Spread Monitor'!$O$7:$O$850,MATCH("GBP|1",'Spread Monitor'!$X$7:$X$850,0)),"") | I63: =IFERROR(INDEX('Spread Monitor'!$Q$7:$Q$850,MATCH("GBP|1",'Spread Monitor'!$X$7:$X$850,0)),"") | J63: =IFERROR(INDEX('Spread Monitor'!$R$7:$R$850,MATCH("GBP|1",'Spread Monitor'!$X$7:$X$850,0)),"") | K63: =IFERROR(INDEX('Spread Monitor'!$S$7:$S$850,MATCH("GBP|1",'Spread Monitor'!$X$7:$X$850,0)),"")
A64: =IFERROR(INDEX('Spread Monitor'!$A$7:$A$850,MATCH("GBP|2",'Spread Monitor'!$X$7:$X$850,0)),"") | B64: =IFERROR(INDEX('Spread Monitor'!$B$7:$B$850,MATCH("GBP|2",'Spread Monitor'!$X$7:$X$850,0)),"") | C64: =IFERROR(INDEX('Spread Monitor'!$C$7:$C$850,MATCH("GBP|2",'Spread Monitor'!$X$7:$X$850,0)),"") | D64: =IFERROR(INDEX('Spread Monitor'!$E$7:$E$850,MATCH("GBP|2",'Spread Monitor'!$X$7:$X$850,0)),"") | E64: =IFERROR(INDEX('Spread Monitor'!$G$7:$G$850,MATCH("GBP|2",'Spread Monitor'!$X$7:$X$850,0)),"") | F64: =IFERROR(INDEX('Spread Monitor'!$H$7:$H$850,MATCH("GBP|2",'Spread Monitor'!$X$7:$X$850,0)),"") | G64: =IFERROR(INDEX('Spread Monitor'!$L$7:$L$850,MATCH("GBP|2",'Spread Monitor'!$X$7:$X$850,0)),"") | H64: =IFERROR(INDEX('Spread Monitor'!$O$7:$O$850,MATCH("GBP|2",'Spread Monitor'!$X$7:$X$850,0)),"") | I64: =IFERROR(INDEX('Spread Monitor'!$Q$7:$Q$850,MATCH("GBP|2",'Spread Monitor'!$X$7:$X$850,0)),"") | J64: =IFERROR(INDEX('Spread Monitor'!$R$7:$R$850,MATCH("GBP|2",'Spread Monitor'!$X$7:$X$850,0)),"") | K64: =IFERROR(INDEX('Spread Monitor'!$S$7:$S$850,MATCH("GBP|2",'Spread Monitor'!$X$7:$X$850,0)),"")
A65: =IFERROR(INDEX('Spread Monitor'!$A$7:$A$850,MATCH("GBP|3",'Spread Monitor'!$X$7:$X$850,0)),"") | B65: =IFERROR(INDEX('Spread Monitor'!$B$7:$B$850,MATCH("GBP|3",'Spread Monitor'!$X$7:$X$850,0)),"") | C65: =IFERROR(INDEX('Spread Monitor'!$C$7:$C$850,MATCH("GBP|3",'Spread Monitor'!$X$7:$X$850,0)),"") | D65: =IFERROR(INDEX('Spread Monitor'!$E$7:$E$850,MATCH("GBP|3",'Spread Monitor'!$X$7:$X$850,0)),"") | E65: =IFERROR(INDEX('Spread Monitor'!$G$7:$G$850,MATCH("GBP|3",'Spread Monitor'!$X$7:$X$850,0)),"") | F65: =IFERROR(INDEX('Spread Monitor'!$H$7:$H$850,MATCH("GBP|3",'Spread Monitor'!$X$7:$X$850,0)),"") | G65: =IFERROR(INDEX('Spread Monitor'!$L$7:$L$850,MATCH("GBP|3",'Spread Monitor'!$X$7:$X$850,0)),"") | H65: =IFERROR(INDEX('Spread Monitor'!$O$7:$O$850,MATCH("GBP|3",'Spread Monitor'!$X$7:$X$850,0)),"") | I65: =IFERROR(INDEX('Spread Monitor'!$Q$7:$Q$850,MATCH("GBP|3",'Spread Monitor'!$X$7:$X$850,0)),"") | J65: =IFERROR(INDEX('Spread Monitor'!$R$7:$R$850,MATCH("GBP|3",'Spread Monitor'!$X$7:$X$850,0)),"") | K65: =IFERROR(INDEX('Spread Monitor'!$S$7:$S$850,MATCH("GBP|3",'Spread Monitor'!$X$7:$X$850,0)),"")
A66: =IFERROR(INDEX('Spread Monitor'!$A$7:$A$850,MATCH("GBP|4",'Spread Monitor'!$X$7:$X$850,0)),"") | B66: =IFERROR(INDEX('Spread Monitor'!$B$7:$B$850,MATCH("GBP|4",'Spread Monitor'!$X$7:$X$850,0)),"") | C66: =IFERROR(INDEX('Spread Monitor'!$C$7:$C$850,MATCH("GBP|4",'Spread Monitor'!$X$7:$X$850,0)),"") | D66: =IFERROR(INDEX('Spread Monitor'!$E$7:$E$850,MATCH("GBP|4",'Spread Monitor'!$X$7:$X$850,0)),"") | E66: =IFERROR(INDEX('Spread Monitor'!$G$7:$G$850,MATCH("GBP|4",'Spread Monitor'!$X$7:$X$850,0)),"") | F66: =IFERROR(INDEX('Spread Monitor'!$H$7:$H$850,MATCH("GBP|4",'Spread Monitor'!$X$7:$X$850,0)),"") | G66: =IFERROR(INDEX('Spread Monitor'!$L$7:$L$850,MATCH("GBP|4",'Spread Monitor'!$X$7:$X$850,0)),"") | H66: =IFERROR(INDEX('Spread Monitor'!$O$7:$O$850,MATCH("GBP|4",'Spread Monitor'!$X$7:$X$850,0)),"") | I66: =IFERROR(INDEX('Spread Monitor'!$Q$7:$Q$850,MATCH("GBP|4",'Spread Monitor'!$X$7:$X$850,0)),"") | J66: =IFERROR(INDEX('Spread Monitor'!$R$7:$R$850,MATCH("GBP|4",'Spread Monitor'!$X$7:$X$850,0)),"") | K66: =IFERROR(INDEX('Spread Monitor'!$S$7:$S$850,MATCH("GBP|4",'Spread Monitor'!$X$7:$X$850,0)),"")
A67: =IFERROR(INDEX('Spread Monitor'!$A$7:$A$850,MATCH("GBP|5",'Spread Monitor'!$X$7:$X$850,0)),"") | B67: =IFERROR(INDEX('Spread Monitor'!$B$7:$B$850,MATCH("GBP|5",'Spread Monitor'!$X$7:$X$850,0)),"") | C67: =IFERROR(INDEX('Spread Monitor'!$C$7:$C$850,MATCH("GBP|5",'Spread Monitor'!$X$7:$X$850,0)),"") | D67: =IFERROR(INDEX('Spread Monitor'!$E$7:$E$850,MATCH("GBP|5",'Spread Monitor'!$X$7:$X$850,0)),"") | E67: =IFERROR(INDEX('Spread Monitor'!$G$7:$G$850,MATCH("GBP|5",'Spread Monitor'!$X$7:$X$850,0)),"") | F67: =IFERROR(INDEX('Spread Monitor'!$H$7:$H$850,MATCH("GBP|5",'Spread Monitor'!$X$7:$X$850,0)),"") | G67: =IFERROR(INDEX('Spread Monitor'!$L$7:$L$850,MATCH("GBP|5",'Spread Monitor'!$X$7:$X$850,0)),"") | H67: =IFERROR(INDEX('Spread Monitor'!$O$7:$O$850,MATCH("GBP|5",'Spread Monitor'!$X$7:$X$850,0)),"") | I67: =IFERROR(INDEX('Spread Monitor'!$Q$7:$Q$850,MATCH("GBP|5",'Spread Monitor'!$X$7:$X$850,0)),"") | J67: =IFERROR(INDEX('Spread Monitor'!$R$7:$R$850,MATCH("GBP|5",'Spread Monitor'!$X$7:$X$850,0)),"") | K67: =IFERROR(INDEX('Spread Monitor'!$S$7:$S$850,MATCH("GBP|5",'Spread Monitor'!$X$7:$X$850,0)),"")
A68: =IFERROR(INDEX('Spread Monitor'!$A$7:$A$850,MATCH("GBP|6",'Spread Monitor'!$X$7:$X$850,0)),"") | B68: =IFERROR(INDEX('Spread Monitor'!$B$7:$B$850,MATCH("GBP|6",'Spread Monitor'!$X$7:$X$850,0)),"") | C68: =IFERROR(INDEX('Spread Monitor'!$C$7:$C$850,MATCH("GBP|6",'Spread Monitor'!$X$7:$X$850,0)),"") | D68: =IFERROR(INDEX('Spread Monitor'!$E$7:$E$850,MATCH("GBP|6",'Spread Monitor'!$X$7:$X$850,0)),"") | E68: =IFERROR(INDEX('Spread Monitor'!$G$7:$G$850,MATCH("GBP|6",'Spread Monitor'!$X$7:$X$850,0)),"") | F68: =IFERROR(INDEX('Spread Monitor'!$H$7:$H$850,MATCH("GBP|6",'Spread Monitor'!$X$7:$X$850,0)),"") | G68: =IFERROR(INDEX('Spread Monitor'!$L$7:$L$850,MATCH("GBP|6",'Spread Monitor'!$X$7:$X$850,0)),"") | H68: =IFERROR(INDEX('Spread Monitor'!$O$7:$O$850,MATCH("GBP|6",'Spread Monitor'!$X$7:$X$850,0)),"") | I68: =IFERROR(INDEX('Spread Monitor'!$Q$7:$Q$850,MATCH("GBP|6",'Spread Monitor'!$X$7:$X$850,0)),"") | J68: =IFERROR(INDEX('Spread Monitor'!$R$7:$R$850,MATCH("GBP|6",'Spread Monitor'!$X$7:$X$850,0)),"") | K68: =IFERROR(INDEX('Spread Monitor'!$S$7:$S$850,MATCH("GBP|6",'Spread Monitor'!$X$7:$X$850,0)),"")
A69: =IFERROR(INDEX('Spread Monitor'!$A$7:$A$850,MATCH("GBP|7",'Spread Monitor'!$X$7:$X$850,0)),"") | B69: =IFERROR(INDEX('Spread Monitor'!$B$7:$B$850,MATCH("GBP|7",'Spread Monitor'!$X$7:$X$850,0)),"") | C69: =IFERROR(INDEX('Spread Monitor'!$C$7:$C$850,MATCH("GBP|7",'Spread Monitor'!$X$7:$X$850,0)),"") | D69: =IFERROR(INDEX('Spread Monitor'!$E$7:$E$850,MATCH("GBP|7",'Spread Monitor'!$X$7:$X$850,0)),"") | E69: =IFERROR(INDEX('Spread Monitor'!$G$7:$G$850,MATCH("GBP|7",'Spread Monitor'!$X$7:$X$850,0)),"") | F69: =IFERROR(INDEX('Spread Monitor'!$H$7:$H$850,MATCH("GBP|7",'Spread Monitor'!$X$7:$X$850,0)),"") | G69: =IFERROR(INDEX('Spread Monitor'!$L$7:$L$850,MATCH("GBP|7",'Spread Monitor'!$X$7:$X$850,0)),"") | H69: =IFERROR(INDEX('Spread Monitor'!$O$7:$O$850,MATCH("GBP|7",'Spread Monitor'!$X$7:$X$850,0)),"") | I69: =IFERROR(INDEX('Spread Monitor'!$Q$7:$Q$850,MATCH("GBP|7",'Spread Monitor'!$X$7:$X$850,0)),"") | J69: =IFERROR(INDEX('Spread Monitor'!$R$7:$R$850,MATCH("GBP|7",'Spread Monitor'!$X$7:$X$850,0)),"") | K69: =IFERROR(INDEX('Spread Monitor'!$S$7:$S$850,MATCH("GBP|7",'Spread Monitor'!$X$7:$X$850,0)),"")
A70: =IFERROR(INDEX('Spread Monitor'!$A$7:$A$850,MATCH("GBP|8",'Spread Monitor'!$X$7:$X$850,0)),"") | B70: =IFERROR(INDEX('Spread Monitor'!$B$7:$B$850,MATCH("GBP|8",'Spread Monitor'!$X$7:$X$850,0)),"") | C70: =IFERROR(INDEX('Spread Monitor'!$C$7:$C$850,MATCH("GBP|8",'Spread Monitor'!$X$7:$X$850,0)),"") | D70: =IFERROR(INDEX('Spread Monitor'!$E$7:$E$850,MATCH("GBP|8",'Spread Monitor'!$X$7:$X$850,0)),"") | E70: =IFERROR(INDEX('Spread Monitor'!$G$7:$G$850,MATCH("GBP|8",'Spread Monitor'!$X$7:$X$850,0)),"") | F70: =IFERROR(INDEX('Spread Monitor'!$H$7:$H$850,MATCH("GBP|8",'Spread Monitor'!$X$7:$X$850,0)),"") | G70: =IFERROR(INDEX('Spread Monitor'!$L$7:$L$850,MATCH("GBP|8",'Spread Monitor'!$X$7:$X$850,0)),"") | H70: =IFERROR(INDEX('Spread Monitor'!$O$7:$O$850,MATCH("GBP|8",'Spread Monitor'!$X$7:$X$850,0)),"") | I70: =IFERROR(INDEX('Spread Monitor'!$Q$7:$Q$850,MATCH("GBP|8",'Spread Monitor'!$X$7:$X$850,0)),"") | J70: =IFERROR(INDEX('Spread Monitor'!$R$7:$R$850,MATCH("GBP|8",'Spread Monitor'!$X$7:$X$850,0)),"") | K70: =IFERROR(INDEX('Spread Monitor'!$S$7:$S$850,MATCH("GBP|8",'Spread Monitor'!$X$7:$X$850,0)),"")
A71: =IFERROR(INDEX('Spread Monitor'!$A$7:$A$850,MATCH("GBP|9",'Spread Monitor'!$X$7:$X$850,0)),"") | B71: =IFERROR(INDEX('Spread Monitor'!$B$7:$B$850,MATCH("GBP|9",'Spread Monitor'!$X$7:$X$850,0)),"") | C71: =IFERROR(INDEX('Spread Monitor'!$C$7:$C$850,MATCH("GBP|9",'Spread Monitor'!$X$7:$X$850,0)),"") | D71: =IFERROR(INDEX('Spread Monitor'!$E$7:$E$850,MATCH("GBP|9",'Spread Monitor'!$X$7:$X$850,0)),"") | E71: =IFERROR(INDEX('Spread Monitor'!$G$7:$G$850,MATCH("GBP|9",'Spread Monitor'!$X$7:$X$850,0)),"") | F71: =IFERROR(INDEX('Spread Monitor'!$H$7:$H$850,MATCH("GBP|9",'Spread Monitor'!$X$7:$X$850,0)),"") | G71: =IFERROR(INDEX('Spread Monitor'!$L$7:$L$850,MATCH("GBP|9",'Spread Monitor'!$X$7:$X$850,0)),"") | H71: =IFERROR(INDEX('Spread Monitor'!$O$7:$O$850,MATCH("GBP|9",'Spread Monitor'!$X$7:$X$850,0)),"") | I71: =IFERROR(INDEX('Spread Monitor'!$Q$7:$Q$850,MATCH("GBP|9",'Spread Monitor'!$X$7:$X$850,0)),"") | J71: =IFERROR(INDEX('Spread Monitor'!$R$7:$R$850,MATCH("GBP|9",'Spread Monitor'!$X$7:$X$850,0)),"") | K71: =IFERROR(INDEX('Spread Monitor'!$S$7:$S$850,MATCH("GBP|9",'Spread Monitor'!$X$7:$X$850,0)),"")
A72: =IFERROR(INDEX('Spread Monitor'!$A$7:$A$850,MATCH("GBP|10",'Spread Monitor'!$X$7:$X$850,0)),"") | B72: =IFERROR(INDEX('Spread Monitor'!$B$7:$B$850,MATCH("GBP|10",'Spread Monitor'!$X$7:$X$850,0)),"") | C72: =IFERROR(INDEX('Spread Monitor'!$C$7:$C$850,MATCH("GBP|10",'Spread Monitor'!$X$7:$X$850,0)),"") | D72: =IFERROR(INDEX('Spread Monitor'!$E$7:$E$850,MATCH("GBP|10",'Spread Monitor'!$X$7:$X$850,0)),"") | E72: =IFERROR(INDEX('Spread Monitor'!$G$7:$G$850,MATCH("GBP|10",'Spread Monitor'!$X$7:$X$850,0)),"") | F72: =IFERROR(INDEX('Spread Monitor'!$H$7:$H$850,MATCH("GBP|10",'Spread Monitor'!$X$7:$X$850,0)),"") | G72: =IFERROR(INDEX('Spread Monitor'!$L$7:$L$850,MATCH("GBP|10",'Spread Monitor'!$X$7:$X$850,0)),"") | H72: =IFERROR(INDEX('Spread Monitor'!$O$7:$O$850,MATCH("GBP|10",'Spread Monitor'!$X$7:$X$850,0)),"") | I72: =IFERROR(INDEX('Spread Monitor'!$Q$7:$Q$850,MATCH("GBP|10",'Spread Monitor'!$X$7:$X$850,0)),"") | J72: =IFERROR(INDEX('Spread Monitor'!$R$7:$R$850,MATCH("GBP|10",'Spread Monitor'!$X$7:$X$850,0)),"") | K72: =IFERROR(INDEX('Spread Monitor'!$S$7:$S$850,MATCH("GBP|10",'Spread Monitor'!$X$7:$X$850,0)),"")
A75: GBP - Top 10 that tightened the most since 14.07.2026
A76: ISIN | B76: Company | C76: Company description | D76: Sector | E76: Ccy | F76: Rating | G76: Maturity | H76: YTW (%) | I76: Spread today (bp) | J76: Spread on anchor (bp) | K76: Spread change (bp)
A77: =IFERROR(INDEX('Spread Monitor'!$A$7:$A$850,MATCH("GBP|1",'Spread Monitor'!$Y$7:$Y$850,0)),"") | B77: =IFERROR(INDEX('Spread Monitor'!$B$7:$B$850,MATCH("GBP|1",'Spread Monitor'!$Y$7:$Y$850,0)),"") | C77: =IFERROR(INDEX('Spread Monitor'!$C$7:$C$850,MATCH("GBP|1",'Spread Monitor'!$Y$7:$Y$850,0)),"") | D77: =IFERROR(INDEX('Spread Monitor'!$E$7:$E$850,MATCH("GBP|1",'Spread Monitor'!$Y$7:$Y$850,0)),"") | E77: =IFERROR(INDEX('Spread Monitor'!$G$7:$G$850,MATCH("GBP|1",'Spread Monitor'!$Y$7:$Y$850,0)),"") | F77: =IFERROR(INDEX('Spread Monitor'!$H$7:$H$850,MATCH("GBP|1",'Spread Monitor'!$Y$7:$Y$850,0)),"") | G77: =IFERROR(INDEX('Spread Monitor'!$L$7:$L$850,MATCH("GBP|1",'Spread Monitor'!$Y$7:$Y$850,0)),"") | H77: =IFERROR(INDEX('Spread Monitor'!$O$7:$O$850,MATCH("GBP|1",'Spread Monitor'!$Y$7:$Y$850,0)),"") | I77: =IFERROR(INDEX('Spread Monitor'!$Q$7:$Q$850,MATCH("GBP|1",'Spread Monitor'!$Y$7:$Y$850,0)),"") | J77: =IFERROR(INDEX('Spread Monitor'!$R$7:$R$850,MATCH("GBP|1",'Spread Monitor'!$Y$7:$Y$850,0)),"") | K77: =IFERROR(INDEX('Spread Monitor'!$S$7:$S$850,MATCH("GBP|1",'Spread Monitor'!$Y$7:$Y$850,0)),"")
A78: =IFERROR(INDEX('Spread Monitor'!$A$7:$A$850,MATCH("GBP|2",'Spread Monitor'!$Y$7:$Y$850,0)),"") | B78: =IFERROR(INDEX('Spread Monitor'!$B$7:$B$850,MATCH("GBP|2",'Spread Monitor'!$Y$7:$Y$850,0)),"") | C78: =IFERROR(INDEX('Spread Monitor'!$C$7:$C$850,MATCH("GBP|2",'Spread Monitor'!$Y$7:$Y$850,0)),"") | D78: =IFERROR(INDEX('Spread Monitor'!$E$7:$E$850,MATCH("GBP|2",'Spread Monitor'!$Y$7:$Y$850,0)),"") | E78: =IFERROR(INDEX('Spread Monitor'!$G$7:$G$850,MATCH("GBP|2",'Spread Monitor'!$Y$7:$Y$850,0)),"") | F78: =IFERROR(INDEX('Spread Monitor'!$H$7:$H$850,MATCH("GBP|2",'Spread Monitor'!$Y$7:$Y$850,0)),"") | G78: =IFERROR(INDEX('Spread Monitor'!$L$7:$L$850,MATCH("GBP|2",'Spread Monitor'!$Y$7:$Y$850,0)),"") | H78: =IFERROR(INDEX('Spread Monitor'!$O$7:$O$850,MATCH("GBP|2",'Spread Monitor'!$Y$7:$Y$850,0)),"") | I78: =IFERROR(INDEX('Spread Monitor'!$Q$7:$Q$850,MATCH("GBP|2",'Spread Monitor'!$Y$7:$Y$850,0)),"") | J78: =IFERROR(INDEX('Spread Monitor'!$R$7:$R$850,MATCH("GBP|2",'Spread Monitor'!$Y$7:$Y$850,0)),"") | K78: =IFERROR(INDEX('Spread Monitor'!$S$7:$S$850,MATCH("GBP|2",'Spread Monitor'!$Y$7:$Y$850,0)),"")
A79: =IFERROR(INDEX('Spread Monitor'!$A$7:$A$850,MATCH("GBP|3",'Spread Monitor'!$Y$7:$Y$850,0)),"") | B79: =IFERROR(INDEX('Spread Monitor'!$B$7:$B$850,MATCH("GBP|3",'Spread Monitor'!$Y$7:$Y$850,0)),"") | C79: =IFERROR(INDEX('Spread Monitor'!$C$7:$C$850,MATCH("GBP|3",'Spread Monitor'!$Y$7:$Y$850,0)),"") | D79: =IFERROR(INDEX('Spread Monitor'!$E$7:$E$850,MATCH("GBP|3",'Spread Monitor'!$Y$7:$Y$850,0)),"") | E79: =IFERROR(INDEX('Spread Monitor'!$G$7:$G$850,MATCH("GBP|3",'Spread Monitor'!$Y$7:$Y$850,0)),"") | F79: =IFERROR(INDEX('Spread Monitor'!$H$7:$H$850,MATCH("GBP|3",'Spread Monitor'!$Y$7:$Y$850,0)),"") | G79: =IFERROR(INDEX('Spread Monitor'!$L$7:$L$850,MATCH("GBP|3",'Spread Monitor'!$Y$7:$Y$850,0)),"") | H79: =IFERROR(INDEX('Spread Monitor'!$O$7:$O$850,MATCH("GBP|3",'Spread Monitor'!$Y$7:$Y$850,0)),"") | I79: =IFERROR(INDEX('Spread Monitor'!$Q$7:$Q$850,MATCH("GBP|3",'Spread Monitor'!$Y$7:$Y$850,0)),"") | J79: =IFERROR(INDEX('Spread Monitor'!$R$7:$R$850,MATCH("GBP|3",'Spread Monitor'!$Y$7:$Y$850,0)),"") | K79: =IFERROR(INDEX('Spread Monitor'!$S$7:$S$850,MATCH("GBP|3",'Spread Monitor'!$Y$7:$Y$850,0)),"")
A80: =IFERROR(INDEX('Spread Monitor'!$A$7:$A$850,MATCH("GBP|4",'Spread Monitor'!$Y$7:$Y$850,0)),"") | B80: =IFERROR(INDEX('Spread Monitor'!$B$7:$B$850,MATCH("GBP|4",'Spread Monitor'!$Y$7:$Y$850,0)),"") | C80: =IFERROR(INDEX('Spread Monitor'!$C$7:$C$850,MATCH("GBP|4",'Spread Monitor'!$Y$7:$Y$850,0)),"") | D80: =IFERROR(INDEX('Spread Monitor'!$E$7:$E$850,MATCH("GBP|4",'Spread Monitor'!$Y$7:$Y$850,0)),"") | E80: =IFERROR(INDEX('Spread Monitor'!$G$7:$G$850,MATCH("GBP|4",'Spread Monitor'!$Y$7:$Y$850,0)),"") | F80: =IFERROR(INDEX('Spread Monitor'!$H$7:$H$850,MATCH("GBP|4",'Spread Monitor'!$Y$7:$Y$850,0)),"") | G80: =IFERROR(INDEX('Spread Monitor'!$L$7:$L$850,MATCH("GBP|4",'Spread Monitor'!$Y$7:$Y$850,0)),"") | H80: =IFERROR(INDEX('Spread Monitor'!$O$7:$O$850,MATCH("GBP|4",'Spread Monitor'!$Y$7:$Y$850,0)),"") | I80: =IFERROR(INDEX('Spread Monitor'!$Q$7:$Q$850,MATCH("GBP|4",'Spread Monitor'!$Y$7:$Y$850,0)),"") | J80: =IFERROR(INDEX('Spread Monitor'!$R$7:$R$850,MATCH("GBP|4",'Spread Monitor'!$Y$7:$Y$850,0)),"") | K80: =IFERROR(INDEX('Spread Monitor'!$S$7:$S$850,MATCH("GBP|4",'Spread Monitor'!$Y$7:$Y$850,0)),"")
A81: =IFERROR(INDEX('Spread Monitor'!$A$7:$A$850,MATCH("GBP|5",'Spread Monitor'!$Y$7:$Y$850,0)),"") | B81: =IFERROR(INDEX('Spread Monitor'!$B$7:$B$850,MATCH("GBP|5",'Spread Monitor'!$Y$7:$Y$850,0)),"") | C81: =IFERROR(INDEX('Spread Monitor'!$C$7:$C$850,MATCH("GBP|5",'Spread Monitor'!$Y$7:$Y$850,0)),"") | D81: =IFERROR(INDEX('Spread Monitor'!$E$7:$E$850,MATCH("GBP|5",'Spread Monitor'!$Y$7:$Y$850,0)),"") | E81: =IFERROR(INDEX('Spread Monitor'!$G$7:$G$850,MATCH("GBP|5",'Spread Monitor'!$Y$7:$Y$850,0)),"") | F81: =IFERROR(INDEX('Spread Monitor'!$H$7:$H$850,MATCH("GBP|5",'Spread Monitor'!$Y$7:$Y$850,0)),"") | G81: =IFERROR(INDEX('Spread Monitor'!$L$7:$L$850,MATCH("GBP|5",'Spread Monitor'!$Y$7:$Y$850,0)),"") | H81: =IFERROR(INDEX('Spread Monitor'!$O$7:$O$850,MATCH("GBP|5",'Spread Monitor'!$Y$7:$Y$850,0)),"") | I81: =IFERROR(INDEX('Spread Monitor'!$Q$7:$Q$850,MATCH("GBP|5",'Spread Monitor'!$Y$7:$Y$850,0)),"") | J81: =IFERROR(INDEX('Spread Monitor'!$R$7:$R$850,MATCH("GBP|5",'Spread Monitor'!$Y$7:$Y$850,0)),"") | K81: =IFERROR(INDEX('Spread Monitor'!$S$7:$S$850,MATCH("GBP|5",'Spread Monitor'!$Y$7:$Y$850,0)),"")
A82: =IFERROR(INDEX('Spread Monitor'!$A$7:$A$850,MATCH("GBP|6",'Spread Monitor'!$Y$7:$Y$850,0)),"") | B82: =IFERROR(INDEX('Spread Monitor'!$B$7:$B$850,MATCH("GBP|6",'Spread Monitor'!$Y$7:$Y$850,0)),"") | C82: =IFERROR(INDEX('Spread Monitor'!$C$7:$C$850,MATCH("GBP|6",'Spread Monitor'!$Y$7:$Y$850,0)),"") | D82: =IFERROR(INDEX('Spread Monitor'!$E$7:$E$850,MATCH("GBP|6",'Spread Monitor'!$Y$7:$Y$850,0)),"") | E82: =IFERROR(INDEX('Spread Monitor'!$G$7:$G$850,MATCH("GBP|6",'Spread Monitor'!$Y$7:$Y$850,0)),"") | F82: =IFERROR(INDEX('Spread Monitor'!$H$7:$H$850,MATCH("GBP|6",'Spread Monitor'!$Y$7:$Y$850,0)),"") | G82: =IFERROR(INDEX('Spread Monitor'!$L$7:$L$850,MATCH("GBP|6",'Spread Monitor'!$Y$7:$Y$850,0)),"") | H82: =IFERROR(INDEX('Spread Monitor'!$O$7:$O$850,MATCH("GBP|6",'Spread Monitor'!$Y$7:$Y$850,0)),"") | I82: =IFERROR(INDEX('Spread Monitor'!$Q$7:$Q$850,MATCH("GBP|6",'Spread Monitor'!$Y$7:$Y$850,0)),"") | J82: =IFERROR(INDEX('Spread Monitor'!$R$7:$R$850,MATCH("GBP|6",'Spread Monitor'!$Y$7:$Y$850,0)),"") | K82: =IFERROR(INDEX('Spread Monitor'!$S$7:$S$850,MATCH("GBP|6",'Spread Monitor'!$Y$7:$Y$850,0)),"")
A83: =IFERROR(INDEX('Spread Monitor'!$A$7:$A$850,MATCH("GBP|7",'Spread Monitor'!$Y$7:$Y$850,0)),"") | B83: =IFERROR(INDEX('Spread Monitor'!$B$7:$B$850,MATCH("GBP|7",'Spread Monitor'!$Y$7:$Y$850,0)),"") | C83: =IFERROR(INDEX('Spread Monitor'!$C$7:$C$850,MATCH("GBP|7",'Spread Monitor'!$Y$7:$Y$850,0)),"") | D83: =IFERROR(INDEX('Spread Monitor'!$E$7:$E$850,MATCH("GBP|7",'Spread Monitor'!$Y$7:$Y$850,0)),"") | E83: =IFERROR(INDEX('Spread Monitor'!$G$7:$G$850,MATCH("GBP|7",'Spread Monitor'!$Y$7:$Y$850,0)),"") | F83: =IFERROR(INDEX('Spread Monitor'!$H$7:$H$850,MATCH("GBP|7",'Spread Monitor'!$Y$7:$Y$850,0)),"") | G83: =IFERROR(INDEX('Spread Monitor'!$L$7:$L$850,MATCH("GBP|7",'Spread Monitor'!$Y$7:$Y$850,0)),"") | H83: =IFERROR(INDEX('Spread Monitor'!$O$7:$O$850,MATCH("GBP|7",'Spread Monitor'!$Y$7:$Y$850,0)),"") | I83: =IFERROR(INDEX('Spread Monitor'!$Q$7:$Q$850,MATCH("GBP|7",'Spread Monitor'!$Y$7:$Y$850,0)),"") | J83: =IFERROR(INDEX('Spread Monitor'!$R$7:$R$850,MATCH("GBP|7",'Spread Monitor'!$Y$7:$Y$850,0)),"") | K83: =IFERROR(INDEX('Spread Monitor'!$S$7:$S$850,MATCH("GBP|7",'Spread Monitor'!$Y$7:$Y$850,0)),"")
A84: =IFERROR(INDEX('Spread Monitor'!$A$7:$A$850,MATCH("GBP|8",'Spread Monitor'!$Y$7:$Y$850,0)),"") | B84: =IFERROR(INDEX('Spread Monitor'!$B$7:$B$850,MATCH("GBP|8",'Spread Monitor'!$Y$7:$Y$850,0)),"") | C84: =IFERROR(INDEX('Spread Monitor'!$C$7:$C$850,MATCH("GBP|8",'Spread Monitor'!$Y$7:$Y$850,0)),"") | D84: =IFERROR(INDEX('Spread Monitor'!$E$7:$E$850,MATCH("GBP|8",'Spread Monitor'!$Y$7:$Y$850,0)),"") | E84: =IFERROR(INDEX('Spread Monitor'!$G$7:$G$850,MATCH("GBP|8",'Spread Monitor'!$Y$7:$Y$850,0)),"") | F84: =IFERROR(INDEX('Spread Monitor'!$H$7:$H$850,MATCH("GBP|8",'Spread Monitor'!$Y$7:$Y$850,0)),"") | G84: =IFERROR(INDEX('Spread Monitor'!$L$7:$L$850,MATCH("GBP|8",'Spread Monitor'!$Y$7:$Y$850,0)),"") | H84: =IFERROR(INDEX('Spread Monitor'!$O$7:$O$850,MATCH("GBP|8",'Spread Monitor'!$Y$7:$Y$850,0)),"") | I84: =IFERROR(INDEX('Spread Monitor'!$Q$7:$Q$850,MATCH("GBP|8",'Spread Monitor'!$Y$7:$Y$850,0)),"") | J84: =IFERROR(INDEX('Spread Monitor'!$R$7:$R$850,MATCH("GBP|8",'Spread Monitor'!$Y$7:$Y$850,0)),"") | K84: =IFERROR(INDEX('Spread Monitor'!$S$7:$S$850,MATCH("GBP|8",'Spread Monitor'!$Y$7:$Y$850,0)),"")
A85: =IFERROR(INDEX('Spread Monitor'!$A$7:$A$850,MATCH("GBP|9",'Spread Monitor'!$Y$7:$Y$850,0)),"") | B85: =IFERROR(INDEX('Spread Monitor'!$B$7:$B$850,MATCH("GBP|9",'Spread Monitor'!$Y$7:$Y$850,0)),"") | C85: =IFERROR(INDEX('Spread Monitor'!$C$7:$C$850,MATCH("GBP|9",'Spread Monitor'!$Y$7:$Y$850,0)),"") | D85: =IFERROR(INDEX('Spread Monitor'!$E$7:$E$850,MATCH("GBP|9",'Spread Monitor'!$Y$7:$Y$850,0)),"") | E85: =IFERROR(INDEX('Spread Monitor'!$G$7:$G$850,MATCH("GBP|9",'Spread Monitor'!$Y$7:$Y$850,0)),"") | F85: =IFERROR(INDEX('Spread Monitor'!$H$7:$H$850,MATCH("GBP|9",'Spread Monitor'!$Y$7:$Y$850,0)),"") | G85: =IFERROR(INDEX('Spread Monitor'!$L$7:$L$850,MATCH("GBP|9",'Spread Monitor'!$Y$7:$Y$850,0)),"") | H85: =IFERROR(INDEX('Spread Monitor'!$O$7:$O$850,MATCH("GBP|9",'Spread Monitor'!$Y$7:$Y$850,0)),"") | I85: =IFERROR(INDEX('Spread Monitor'!$Q$7:$Q$850,MATCH("GBP|9",'Spread Monitor'!$Y$7:$Y$850,0)),"") | J85: =IFERROR(INDEX('Spread Monitor'!$R$7:$R$850,MATCH("GBP|9",'Spread Monitor'!$Y$7:$Y$850,0)),"") | K85: =IFERROR(INDEX('Spread Monitor'!$S$7:$S$850,MATCH("GBP|9",'Spread Monitor'!$Y$7:$Y$850,0)),"")
A86: =IFERROR(INDEX('Spread Monitor'!$A$7:$A$850,MATCH("GBP|10",'Spread Monitor'!$Y$7:$Y$850,0)),"") | B86: =IFERROR(INDEX('Spread Monitor'!$B$7:$B$850,MATCH("GBP|10",'Spread Monitor'!$Y$7:$Y$850,0)),"") | C86: =IFERROR(INDEX('Spread Monitor'!$C$7:$C$850,MATCH("GBP|10",'Spread Monitor'!$Y$7:$Y$850,0)),"") | D86: =IFERROR(INDEX('Spread Monitor'!$E$7:$E$850,MATCH("GBP|10",'Spread Monitor'!$Y$7:$Y$850,0)),"") | E86: =IFERROR(INDEX('Spread Monitor'!$G$7:$G$850,MATCH("GBP|10",'Spread Monitor'!$Y$7:$Y$850,0)),"") | F86: =IFERROR(INDEX('Spread Monitor'!$H$7:$H$850,MATCH("GBP|10",'Spread Monitor'!$Y$7:$Y$850,0)),"") | G86: =IFERROR(INDEX('Spread Monitor'!$L$7:$L$850,MATCH("GBP|10",'Spread Monitor'!$Y$7:$Y$850,0)),"") | H86: =IFERROR(INDEX('Spread Monitor'!$O$7:$O$850,MATCH("GBP|10",'Spread Monitor'!$Y$7:$Y$850,0)),"") | I86: =IFERROR(INDEX('Spread Monitor'!$Q$7:$Q$850,MATCH("GBP|10",'Spread Monitor'!$Y$7:$Y$850,0)),"") | J86: =IFERROR(INDEX('Spread Monitor'!$R$7:$R$850,MATCH("GBP|10",'Spread Monitor'!$Y$7:$Y$850,0)),"") | K86: =IFERROR(INDEX('Spread Monitor'!$S$7:$S$850,MATCH("GBP|10",'Spread Monitor'!$Y$7:$Y$850,0)),"")
A89: CHF - Top 10 that widened the most since 14.07.2026
A90: ISIN | B90: Company | C90: Company description | D90: Sector | E90: Ccy | F90: Rating | G90: Maturity | H90: YTW (%) | I90: Spread today (bp) | J90: Spread on anchor (bp) | K90: Spread change (bp)
A91: =IFERROR(INDEX('Spread Monitor'!$A$7:$A$850,MATCH("CHF|1",'Spread Monitor'!$X$7:$X$850,0)),"") | B91: =IFERROR(INDEX('Spread Monitor'!$B$7:$B$850,MATCH("CHF|1",'Spread Monitor'!$X$7:$X$850,0)),"") | C91: =IFERROR(INDEX('Spread Monitor'!$C$7:$C$850,MATCH("CHF|1",'Spread Monitor'!$X$7:$X$850,0)),"") | D91: =IFERROR(INDEX('Spread Monitor'!$E$7:$E$850,MATCH("CHF|1",'Spread Monitor'!$X$7:$X$850,0)),"") | E91: =IFERROR(INDEX('Spread Monitor'!$G$7:$G$850,MATCH("CHF|1",'Spread Monitor'!$X$7:$X$850,0)),"") | F91: =IFERROR(INDEX('Spread Monitor'!$H$7:$H$850,MATCH("CHF|1",'Spread Monitor'!$X$7:$X$850,0)),"") | G91: =IFERROR(INDEX('Spread Monitor'!$L$7:$L$850,MATCH("CHF|1",'Spread Monitor'!$X$7:$X$850,0)),"") | H91: =IFERROR(INDEX('Spread Monitor'!$O$7:$O$850,MATCH("CHF|1",'Spread Monitor'!$X$7:$X$850,0)),"") | I91: =IFERROR(INDEX('Spread Monitor'!$Q$7:$Q$850,MATCH("CHF|1",'Spread Monitor'!$X$7:$X$850,0)),"") | J91: =IFERROR(INDEX('Spread Monitor'!$R$7:$R$850,MATCH("CHF|1",'Spread Monitor'!$X$7:$X$850,0)),"") | K91: =IFERROR(INDEX('Spread Monitor'!$S$7:$S$850,MATCH("CHF|1",'Spread Monitor'!$X$7:$X$850,0)),"")
A92: =IFERROR(INDEX('Spread Monitor'!$A$7:$A$850,MATCH("CHF|2",'Spread Monitor'!$X$7:$X$850,0)),"") | B92: =IFERROR(INDEX('Spread Monitor'!$B$7:$B$850,MATCH("CHF|2",'Spread Monitor'!$X$7:$X$850,0)),"") | C92: =IFERROR(INDEX('Spread Monitor'!$C$7:$C$850,MATCH("CHF|2",'Spread Monitor'!$X$7:$X$850,0)),"") | D92: =IFERROR(INDEX('Spread Monitor'!$E$7:$E$850,MATCH("CHF|2",'Spread Monitor'!$X$7:$X$850,0)),"") | E92: =IFERROR(INDEX('Spread Monitor'!$G$7:$G$850,MATCH("CHF|2",'Spread Monitor'!$X$7:$X$850,0)),"") | F92: =IFERROR(INDEX('Spread Monitor'!$H$7:$H$850,MATCH("CHF|2",'Spread Monitor'!$X$7:$X$850,0)),"") | G92: =IFERROR(INDEX('Spread Monitor'!$L$7:$L$850,MATCH("CHF|2",'Spread Monitor'!$X$7:$X$850,0)),"") | H92: =IFERROR(INDEX('Spread Monitor'!$O$7:$O$850,MATCH("CHF|2",'Spread Monitor'!$X$7:$X$850,0)),"") | I92: =IFERROR(INDEX('Spread Monitor'!$Q$7:$Q$850,MATCH("CHF|2",'Spread Monitor'!$X$7:$X$850,0)),"") | J92: =IFERROR(INDEX('Spread Monitor'!$R$7:$R$850,MATCH("CHF|2",'Spread Monitor'!$X$7:$X$850,0)),"") | K92: =IFERROR(INDEX('Spread Monitor'!$S$7:$S$850,MATCH("CHF|2",'Spread Monitor'!$X$7:$X$850,0)),"")
A93: =IFERROR(INDEX('Spread Monitor'!$A$7:$A$850,MATCH("CHF|3",'Spread Monitor'!$X$7:$X$850,0)),"") | B93: =IFERROR(INDEX('Spread Monitor'!$B$7:$B$850,MATCH("CHF|3",'Spread Monitor'!$X$7:$X$850,0)),"") | C93: =IFERROR(INDEX('Spread Monitor'!$C$7:$C$850,MATCH("CHF|3",'Spread Monitor'!$X$7:$X$850,0)),"") | D93: =IFERROR(INDEX('Spread Monitor'!$E$7:$E$850,MATCH("CHF|3",'Spread Monitor'!$X$7:$X$850,0)),"") | E93: =IFERROR(INDEX('Spread Monitor'!$G$7:$G$850,MATCH("CHF|3",'Spread Monitor'!$X$7:$X$850,0)),"") | F93: =IFERROR(INDEX('Spread Monitor'!$H$7:$H$850,MATCH("CHF|3",'Spread Monitor'!$X$7:$X$850,0)),"") | G93: =IFERROR(INDEX('Spread Monitor'!$L$7:$L$850,MATCH("CHF|3",'Spread Monitor'!$X$7:$X$850,0)),"") | H93: =IFERROR(INDEX('Spread Monitor'!$O$7:$O$850,MATCH("CHF|3",'Spread Monitor'!$X$7:$X$850,0)),"") | I93: =IFERROR(INDEX('Spread Monitor'!$Q$7:$Q$850,MATCH("CHF|3",'Spread Monitor'!$X$7:$X$850,0)),"") | J93: =IFERROR(INDEX('Spread Monitor'!$R$7:$R$850,MATCH("CHF|3",'Spread Monitor'!$X$7:$X$850,0)),"") | K93: =IFERROR(INDEX('Spread Monitor'!$S$7:$S$850,MATCH("CHF|3",'Spread Monitor'!$X$7:$X$850,0)),"")
A94: =IFERROR(INDEX('Spread Monitor'!$A$7:$A$850,MATCH("CHF|4",'Spread Monitor'!$X$7:$X$850,0)),"") | B94: =IFERROR(INDEX('Spread Monitor'!$B$7:$B$850,MATCH("CHF|4",'Spread Monitor'!$X$7:$X$850,0)),"") | C94: =IFERROR(INDEX('Spread Monitor'!$C$7:$C$850,MATCH("CHF|4",'Spread Monitor'!$X$7:$X$850,0)),"") | D94: =IFERROR(INDEX('Spread Monitor'!$E$7:$E$850,MATCH("CHF|4",'Spread Monitor'!$X$7:$X$850,0)),"") | E94: =IFERROR(INDEX('Spread Monitor'!$G$7:$G$850,MATCH("CHF|4",'Spread Monitor'!$X$7:$X$850,0)),"") | F94: =IFERROR(INDEX('Spread Monitor'!$H$7:$H$850,MATCH("CHF|4",'Spread Monitor'!$X$7:$X$850,0)),"") | G94: =IFERROR(INDEX('Spread Monitor'!$L$7:$L$850,MATCH("CHF|4",'Spread Monitor'!$X$7:$X$850,0)),"") | H94: =IFERROR(INDEX('Spread Monitor'!$O$7:$O$850,MATCH("CHF|4",'Spread Monitor'!$X$7:$X$850,0)),"") | I94: =IFERROR(INDEX('Spread Monitor'!$Q$7:$Q$850,MATCH("CHF|4",'Spread Monitor'!$X$7:$X$850,0)),"") | J94: =IFERROR(INDEX('Spread Monitor'!$R$7:$R$850,MATCH("CHF|4",'Spread Monitor'!$X$7:$X$850,0)),"") | K94: =IFERROR(INDEX('Spread Monitor'!$S$7:$S$850,MATCH("CHF|4",'Spread Monitor'!$X$7:$X$850,0)),"")
A95: =IFERROR(INDEX('Spread Monitor'!$A$7:$A$850,MATCH("CHF|5",'Spread Monitor'!$X$7:$X$850,0)),"") | B95: =IFERROR(INDEX('Spread Monitor'!$B$7:$B$850,MATCH("CHF|5",'Spread Monitor'!$X$7:$X$850,0)),"") | C95: =IFERROR(INDEX('Spread Monitor'!$C$7:$C$850,MATCH("CHF|5",'Spread Monitor'!$X$7:$X$850,0)),"") | D95: =IFERROR(INDEX('Spread Monitor'!$E$7:$E$850,MATCH("CHF|5",'Spread Monitor'!$X$7:$X$850,0)),"") | E95: =IFERROR(INDEX('Spread Monitor'!$G$7:$G$850,MATCH("CHF|5",'Spread Monitor'!$X$7:$X$850,0)),"") | F95: =IFERROR(INDEX('Spread Monitor'!$H$7:$H$850,MATCH("CHF|5",'Spread Monitor'!$X$7:$X$850,0)),"") | G95: =IFERROR(INDEX('Spread Monitor'!$L$7:$L$850,MATCH("CHF|5",'Spread Monitor'!$X$7:$X$850,0)),"") | H95: =IFERROR(INDEX('Spread Monitor'!$O$7:$O$850,MATCH("CHF|5",'Spread Monitor'!$X$7:$X$850,0)),"") | I95: =IFERROR(INDEX('Spread Monitor'!$Q$7:$Q$850,MATCH("CHF|5",'Spread Monitor'!$X$7:$X$850,0)),"") | J95: =IFERROR(INDEX('Spread Monitor'!$R$7:$R$850,MATCH("CHF|5",'Spread Monitor'!$X$7:$X$850,0)),"") | K95: =IFERROR(INDEX('Spread Monitor'!$S$7:$S$850,MATCH("CHF|5",'Spread Monitor'!$X$7:$X$850,0)),"")
A96: =IFERROR(INDEX('Spread Monitor'!$A$7:$A$850,MATCH("CHF|6",'Spread Monitor'!$X$7:$X$850,0)),"") | B96: =IFERROR(INDEX('Spread Monitor'!$B$7:$B$850,MATCH("CHF|6",'Spread Monitor'!$X$7:$X$850,0)),"") | C96: =IFERROR(INDEX('Spread Monitor'!$C$7:$C$850,MATCH("CHF|6",'Spread Monitor'!$X$7:$X$850,0)),"") | D96: =IFERROR(INDEX('Spread Monitor'!$E$7:$E$850,MATCH("CHF|6",'Spread Monitor'!$X$7:$X$850,0)),"") | E96: =IFERROR(INDEX('Spread Monitor'!$G$7:$G$850,MATCH("CHF|6",'Spread Monitor'!$X$7:$X$850,0)),"") | F96: =IFERROR(INDEX('Spread Monitor'!$H$7:$H$850,MATCH("CHF|6",'Spread Monitor'!$X$7:$X$850,0)),"") | G96: =IFERROR(INDEX('Spread Monitor'!$L$7:$L$850,MATCH("CHF|6",'Spread Monitor'!$X$7:$X$850,0)),"") | H96: =IFERROR(INDEX('Spread Monitor'!$O$7:$O$850,MATCH("CHF|6",'Spread Monitor'!$X$7:$X$850,0)),"") | I96: =IFERROR(INDEX('Spread Monitor'!$Q$7:$Q$850,MATCH("CHF|6",'Spread Monitor'!$X$7:$X$850,0)),"") | J96: =IFERROR(INDEX('Spread Monitor'!$R$7:$R$850,MATCH("CHF|6",'Spread Monitor'!$X$7:$X$850,0)),"") | K96: =IFERROR(INDEX('Spread Monitor'!$S$7:$S$850,MATCH("CHF|6",'Spread Monitor'!$X$7:$X$850,0)),"")
A97: =IFERROR(INDEX('Spread Monitor'!$A$7:$A$850,MATCH("CHF|7",'Spread Monitor'!$X$7:$X$850,0)),"") | B97: =IFERROR(INDEX('Spread Monitor'!$B$7:$B$850,MATCH("CHF|7",'Spread Monitor'!$X$7:$X$850,0)),"") | C97: =IFERROR(INDEX('Spread Monitor'!$C$7:$C$850,MATCH("CHF|7",'Spread Monitor'!$X$7:$X$850,0)),"") | D97: =IFERROR(INDEX('Spread Monitor'!$E$7:$E$850,MATCH("CHF|7",'Spread Monitor'!$X$7:$X$850,0)),"") | E97: =IFERROR(INDEX('Spread Monitor'!$G$7:$G$850,MATCH("CHF|7",'Spread Monitor'!$X$7:$X$850,0)),"") | F97: =IFERROR(INDEX('Spread Monitor'!$H$7:$H$850,MATCH("CHF|7",'Spread Monitor'!$X$7:$X$850,0)),"") | G97: =IFERROR(INDEX('Spread Monitor'!$L$7:$L$850,MATCH("CHF|7",'Spread Monitor'!$X$7:$X$850,0)),"") | H97: =IFERROR(INDEX('Spread Monitor'!$O$7:$O$850,MATCH("CHF|7",'Spread Monitor'!$X$7:$X$850,0)),"") | I97: =IFERROR(INDEX('Spread Monitor'!$Q$7:$Q$850,MATCH("CHF|7",'Spread Monitor'!$X$7:$X$850,0)),"") | J97: =IFERROR(INDEX('Spread Monitor'!$R$7:$R$850,MATCH("CHF|7",'Spread Monitor'!$X$7:$X$850,0)),"") | K97: =IFERROR(INDEX('Spread Monitor'!$S$7:$S$850,MATCH("CHF|7",'Spread Monitor'!$X$7:$X$850,0)),"")
A98: =IFERROR(INDEX('Spread Monitor'!$A$7:$A$850,MATCH("CHF|8",'Spread Monitor'!$X$7:$X$850,0)),"") | B98: =IFERROR(INDEX('Spread Monitor'!$B$7:$B$850,MATCH("CHF|8",'Spread Monitor'!$X$7:$X$850,0)),"") | C98: =IFERROR(INDEX('Spread Monitor'!$C$7:$C$850,MATCH("CHF|8",'Spread Monitor'!$X$7:$X$850,0)),"") | D98: =IFERROR(INDEX('Spread Monitor'!$E$7:$E$850,MATCH("CHF|8",'Spread Monitor'!$X$7:$X$850,0)),"") | E98: =IFERROR(INDEX('Spread Monitor'!$G$7:$G$850,MATCH("CHF|8",'Spread Monitor'!$X$7:$X$850,0)),"") | F98: =IFERROR(INDEX('Spread Monitor'!$H$7:$H$850,MATCH("CHF|8",'Spread Monitor'!$X$7:$X$850,0)),"") | G98: =IFERROR(INDEX('Spread Monitor'!$L$7:$L$850,MATCH("CHF|8",'Spread Monitor'!$X$7:$X$850,0)),"") | H98: =IFERROR(INDEX('Spread Monitor'!$O$7:$O$850,MATCH("CHF|8",'Spread Monitor'!$X$7:$X$850,0)),"") | I98: =IFERROR(INDEX('Spread Monitor'!$Q$7:$Q$850,MATCH("CHF|8",'Spread Monitor'!$X$7:$X$850,0)),"") | J98: =IFERROR(INDEX('Spread Monitor'!$R$7:$R$850,MATCH("CHF|8",'Spread Monitor'!$X$7:$X$850,0)),"") | K98: =IFERROR(INDEX('Spread Monitor'!$S$7:$S$850,MATCH("CHF|8",'Spread Monitor'!$X$7:$X$850,0)),"")
A99: =IFERROR(INDEX('Spread Monitor'!$A$7:$A$850,MATCH("CHF|9",'Spread Monitor'!$X$7:$X$850,0)),"") | B99: =IFERROR(INDEX('Spread Monitor'!$B$7:$B$850,MATCH("CHF|9",'Spread Monitor'!$X$7:$X$850,0)),"") | C99: =IFERROR(INDEX('Spread Monitor'!$C$7:$C$850,MATCH("CHF|9",'Spread Monitor'!$X$7:$X$850,0)),"") | D99: =IFERROR(INDEX('Spread Monitor'!$E$7:$E$850,MATCH("CHF|9",'Spread Monitor'!$X$7:$X$850,0)),"") | E99: =IFERROR(INDEX('Spread Monitor'!$G$7:$G$850,MATCH("CHF|9",'Spread Monitor'!$X$7:$X$850,0)),"") | F99: =IFERROR(INDEX('Spread Monitor'!$H$7:$H$850,MATCH("CHF|9",'Spread Monitor'!$X$7:$X$850,0)),"") | G99: =IFERROR(INDEX('Spread Monitor'!$L$7:$L$850,MATCH("CHF|9",'Spread Monitor'!$X$7:$X$850,0)),"") | H99: =IFERROR(INDEX('Spread Monitor'!$O$7:$O$850,MATCH("CHF|9",'Spread Monitor'!$X$7:$X$850,0)),"") | I99: =IFERROR(INDEX('Spread Monitor'!$Q$7:$Q$850,MATCH("CHF|9",'Spread Monitor'!$X$7:$X$850,0)),"") | J99: =IFERROR(INDEX('Spread Monitor'!$R$7:$R$850,MATCH("CHF|9",'Spread Monitor'!$X$7:$X$850,0)),"") | K99: =IFERROR(INDEX('Spread Monitor'!$S$7:$S$850,MATCH("CHF|9",'Spread Monitor'!$X$7:$X$850,0)),"")
A100: =IFERROR(INDEX('Spread Monitor'!$A$7:$A$850,MATCH("CHF|10",'Spread Monitor'!$X$7:$X$850,0)),"") | B100: =IFERROR(INDEX('Spread Monitor'!$B$7:$B$850,MATCH("CHF|10",'Spread Monitor'!$X$7:$X$850,0)),"") | C100: =IFERROR(INDEX('Spread Monitor'!$C$7:$C$850,MATCH("CHF|10",'Spread Monitor'!$X$7:$X$850,0)),"") | D100: =IFERROR(INDEX('Spread Monitor'!$E$7:$E$850,MATCH("CHF|10",'Spread Monitor'!$X$7:$X$850,0)),"") | E100: =IFERROR(INDEX('Spread Monitor'!$G$7:$G$850,MATCH("CHF|10",'Spread Monitor'!$X$7:$X$850,0)),"") | F100: =IFERROR(INDEX('Spread Monitor'!$H$7:$H$850,MATCH("CHF|10",'Spread Monitor'!$X$7:$X$850,0)),"") | G100: =IFERROR(INDEX('Spread Monitor'!$L$7:$L$850,MATCH("CHF|10",'Spread Monitor'!$X$7:$X$850,0)),"") | H100: =IFERROR(INDEX('Spread Monitor'!$O$7:$O$850,MATCH("CHF|10",'Spread Monitor'!$X$7:$X$850,0)),"") | I100: =IFERROR(INDEX('Spread Monitor'!$Q$7:$Q$850,MATCH("CHF|10",'Spread Monitor'!$X$7:$X$850,0)),"") | J100: =IFERROR(INDEX('Spread Monitor'!$R$7:$R$850,MATCH("CHF|10",'Spread Monitor'!$X$7:$X$850,0)),"") | K100: =IFERROR(INDEX('Spread Monitor'!$S$7:$S$850,MATCH("CHF|10",'Spread Monitor'!$X$7:$X$850,0)),"")
A103: CHF - Top 10 that tightened the most since 14.07.2026
A104: ISIN | B104: Company | C104: Company description | D104: Sector | E104: Ccy | F104: Rating | G104: Maturity | H104: YTW (%) | I104: Spread today (bp) | J104: Spread on anchor (bp) | K104: Spread change (bp)
A105: =IFERROR(INDEX('Spread Monitor'!$A$7:$A$850,MATCH("CHF|1",'Spread Monitor'!$Y$7:$Y$850,0)),"") | B105: =IFERROR(INDEX('Spread Monitor'!$B$7:$B$850,MATCH("CHF|1",'Spread Monitor'!$Y$7:$Y$850,0)),"") | C105: =IFERROR(INDEX('Spread Monitor'!$C$7:$C$850,MATCH("CHF|1",'Spread Monitor'!$Y$7:$Y$850,0)),"") | D105: =IFERROR(INDEX('Spread Monitor'!$E$7:$E$850,MATCH("CHF|1",'Spread Monitor'!$Y$7:$Y$850,0)),"") | E105: =IFERROR(INDEX('Spread Monitor'!$G$7:$G$850,MATCH("CHF|1",'Spread Monitor'!$Y$7:$Y$850,0)),"") | F105: =IFERROR(INDEX('Spread Monitor'!$H$7:$H$850,MATCH("CHF|1",'Spread Monitor'!$Y$7:$Y$850,0)),"") | G105: =IFERROR(INDEX('Spread Monitor'!$L$7:$L$850,MATCH("CHF|1",'Spread Monitor'!$Y$7:$Y$850,0)),"") | H105: =IFERROR(INDEX('Spread Monitor'!$O$7:$O$850,MATCH("CHF|1",'Spread Monitor'!$Y$7:$Y$850,0)),"") | I105: =IFERROR(INDEX('Spread Monitor'!$Q$7:$Q$850,MATCH("CHF|1",'Spread Monitor'!$Y$7:$Y$850,0)),"") | J105: =IFERROR(INDEX('Spread Monitor'!$R$7:$R$850,MATCH("CHF|1",'Spread Monitor'!$Y$7:$Y$850,0)),"") | K105: =IFERROR(INDEX('Spread Monitor'!$S$7:$S$850,MATCH("CHF|1",'Spread Monitor'!$Y$7:$Y$850,0)),"")
A106: =IFERROR(INDEX('Spread Monitor'!$A$7:$A$850,MATCH("CHF|2",'Spread Monitor'!$Y$7:$Y$850,0)),"") | B106: =IFERROR(INDEX('Spread Monitor'!$B$7:$B$850,MATCH("CHF|2",'Spread Monitor'!$Y$7:$Y$850,0)),"") | C106: =IFERROR(INDEX('Spread Monitor'!$C$7:$C$850,MATCH("CHF|2",'Spread Monitor'!$Y$7:$Y$850,0)),"") | D106: =IFERROR(INDEX('Spread Monitor'!$E$7:$E$850,MATCH("CHF|2",'Spread Monitor'!$Y$7:$Y$850,0)),"") | E106: =IFERROR(INDEX('Spread Monitor'!$G$7:$G$850,MATCH("CHF|2",'Spread Monitor'!$Y$7:$Y$850,0)),"") | F106: =IFERROR(INDEX('Spread Monitor'!$H$7:$H$850,MATCH("CHF|2",'Spread Monitor'!$Y$7:$Y$850,0)),"") | G106: =IFERROR(INDEX('Spread Monitor'!$L$7:$L$850,MATCH("CHF|2",'Spread Monitor'!$Y$7:$Y$850,0)),"") | H106: =IFERROR(INDEX('Spread Monitor'!$O$7:$O$850,MATCH("CHF|2",'Spread Monitor'!$Y$7:$Y$850,0)),"") | I106: =IFERROR(INDEX('Spread Monitor'!$Q$7:$Q$850,MATCH("CHF|2",'Spread Monitor'!$Y$7:$Y$850,0)),"") | J106: =IFERROR(INDEX('Spread Monitor'!$R$7:$R$850,MATCH("CHF|2",'Spread Monitor'!$Y$7:$Y$850,0)),"") | K106: =IFERROR(INDEX('Spread Monitor'!$S$7:$S$850,MATCH("CHF|2",'Spread Monitor'!$Y$7:$Y$850,0)),"")
A107: =IFERROR(INDEX('Spread Monitor'!$A$7:$A$850,MATCH("CHF|3",'Spread Monitor'!$Y$7:$Y$850,0)),"") | B107: =IFERROR(INDEX('Spread Monitor'!$B$7:$B$850,MATCH("CHF|3",'Spread Monitor'!$Y$7:$Y$850,0)),"") | C107: =IFERROR(INDEX('Spread Monitor'!$C$7:$C$850,MATCH("CHF|3",'Spread Monitor'!$Y$7:$Y$850,0)),"") | D107: =IFERROR(INDEX('Spread Monitor'!$E$7:$E$850,MATCH("CHF|3",'Spread Monitor'!$Y$7:$Y$850,0)),"") | E107: =IFERROR(INDEX('Spread Monitor'!$G$7:$G$850,MATCH("CHF|3",'Spread Monitor'!$Y$7:$Y$850,0)),"") | F107: =IFERROR(INDEX('Spread Monitor'!$H$7:$H$850,MATCH("CHF|3",'Spread Monitor'!$Y$7:$Y$850,0)),"") | G107: =IFERROR(INDEX('Spread Monitor'!$L$7:$L$850,MATCH("CHF|3",'Spread Monitor'!$Y$7:$Y$850,0)),"") | H107: =IFERROR(INDEX('Spread Monitor'!$O$7:$O$850,MATCH("CHF|3",'Spread Monitor'!$Y$7:$Y$850,0)),"") | I107: =IFERROR(INDEX('Spread Monitor'!$Q$7:$Q$850,MATCH("CHF|3",'Spread Monitor'!$Y$7:$Y$850,0)),"") | J107: =IFERROR(INDEX('Spread Monitor'!$R$7:$R$850,MATCH("CHF|3",'Spread Monitor'!$Y$7:$Y$850,0)),"") | K107: =IFERROR(INDEX('Spread Monitor'!$S$7:$S$850,MATCH("CHF|3",'Spread Monitor'!$Y$7:$Y$850,0)),"")
A108: =IFERROR(INDEX('Spread Monitor'!$A$7:$A$850,MATCH("CHF|4",'Spread Monitor'!$Y$7:$Y$850,0)),"") | B108: =IFERROR(INDEX('Spread Monitor'!$B$7:$B$850,MATCH("CHF|4",'Spread Monitor'!$Y$7:$Y$850,0)),"") | C108: =IFERROR(INDEX('Spread Monitor'!$C$7:$C$850,MATCH("CHF|4",'Spread Monitor'!$Y$7:$Y$850,0)),"") | D108: =IFERROR(INDEX('Spread Monitor'!$E$7:$E$850,MATCH("CHF|4",'Spread Monitor'!$Y$7:$Y$850,0)),"") | E108: =IFERROR(INDEX('Spread Monitor'!$G$7:$G$850,MATCH("CHF|4",'Spread Monitor'!$Y$7:$Y$850,0)),"") | F108: =IFERROR(INDEX('Spread Monitor'!$H$7:$H$850,MATCH("CHF|4",'Spread Monitor'!$Y$7:$Y$850,0)),"") | G108: =IFERROR(INDEX('Spread Monitor'!$L$7:$L$850,MATCH("CHF|4",'Spread Monitor'!$Y$7:$Y$850,0)),"") | H108: =IFERROR(INDEX('Spread Monitor'!$O$7:$O$850,MATCH("CHF|4",'Spread Monitor'!$Y$7:$Y$850,0)),"") | I108: =IFERROR(INDEX('Spread Monitor'!$Q$7:$Q$850,MATCH("CHF|4",'Spread Monitor'!$Y$7:$Y$850,0)),"") | J108: =IFERROR(INDEX('Spread Monitor'!$R$7:$R$850,MATCH("CHF|4",'Spread Monitor'!$Y$7:$Y$850,0)),"") | K108: =IFERROR(INDEX('Spread Monitor'!$S$7:$S$850,MATCH("CHF|4",'Spread Monitor'!$Y$7:$Y$850,0)),"")
A109: =IFERROR(INDEX('Spread Monitor'!$A$7:$A$850,MATCH("CHF|5",'Spread Monitor'!$Y$7:$Y$850,0)),"") | B109: =IFERROR(INDEX('Spread Monitor'!$B$7:$B$850,MATCH("CHF|5",'Spread Monitor'!$Y$7:$Y$850,0)),"") | C109: =IFERROR(INDEX('Spread Monitor'!$C$7:$C$850,MATCH("CHF|5",'Spread Monitor'!$Y$7:$Y$850,0)),"") | D109: =IFERROR(INDEX('Spread Monitor'!$E$7:$E$850,MATCH("CHF|5",'Spread Monitor'!$Y$7:$Y$850,0)),"") | E109: =IFERROR(INDEX('Spread Monitor'!$G$7:$G$850,MATCH("CHF|5",'Spread Monitor'!$Y$7:$Y$850,0)),"") | F109: =IFERROR(INDEX('Spread Monitor'!$H$7:$H$850,MATCH("CHF|5",'Spread Monitor'!$Y$7:$Y$850,0)),"") | G109: =IFERROR(INDEX('Spread Monitor'!$L$7:$L$850,MATCH("CHF|5",'Spread Monitor'!$Y$7:$Y$850,0)),"") | H109: =IFERROR(INDEX('Spread Monitor'!$O$7:$O$850,MATCH("CHF|5",'Spread Monitor'!$Y$7:$Y$850,0)),"") | I109: =IFERROR(INDEX('Spread Monitor'!$Q$7:$Q$850,MATCH("CHF|5",'Spread Monitor'!$Y$7:$Y$850,0)),"") | J109: =IFERROR(INDEX('Spread Monitor'!$R$7:$R$850,MATCH("CHF|5",'Spread Monitor'!$Y$7:$Y$850,0)),"") | K109: =IFERROR(INDEX('Spread Monitor'!$S$7:$S$850,MATCH("CHF|5",'Spread Monitor'!$Y$7:$Y$850,0)),"")
A110: =IFERROR(INDEX('Spread Monitor'!$A$7:$A$850,MATCH("CHF|6",'Spread Monitor'!$Y$7:$Y$850,0)),"") | B110: =IFERROR(INDEX('Spread Monitor'!$B$7:$B$850,MATCH("CHF|6",'Spread Monitor'!$Y$7:$Y$850,0)),"") | C110: =IFERROR(INDEX('Spread Monitor'!$C$7:$C$850,MATCH("CHF|6",'Spread Monitor'!$Y$7:$Y$850,0)),"") | D110: =IFERROR(INDEX('Spread Monitor'!$E$7:$E$850,MATCH("CHF|6",'Spread Monitor'!$Y$7:$Y$850,0)),"") | E110: =IFERROR(INDEX('Spread Monitor'!$G$7:$G$850,MATCH("CHF|6",'Spread Monitor'!$Y$7:$Y$850,0)),"") | F110: =IFERROR(INDEX('Spread Monitor'!$H$7:$H$850,MATCH("CHF|6",'Spread Monitor'!$Y$7:$Y$850,0)),"") | G110: =IFERROR(INDEX('Spread Monitor'!$L$7:$L$850,MATCH("CHF|6",'Spread Monitor'!$Y$7:$Y$850,0)),"") | H110: =IFERROR(INDEX('Spread Monitor'!$O$7:$O$850,MATCH("CHF|6",'Spread Monitor'!$Y$7:$Y$850,0)),"") | I110: =IFERROR(INDEX('Spread Monitor'!$Q$7:$Q$850,MATCH("CHF|6",'Spread Monitor'!$Y$7:$Y$850,0)),"") | J110: =IFERROR(INDEX('Spread Monitor'!$R$7:$R$850,MATCH("CHF|6",'Spread Monitor'!$Y$7:$Y$850,0)),"") | K110: =IFERROR(INDEX('Spread Monitor'!$S$7:$S$850,MATCH("CHF|6",'Spread Monitor'!$Y$7:$Y$850,0)),"")
A111: =IFERROR(INDEX('Spread Monitor'!$A$7:$A$850,MATCH("CHF|7",'Spread Monitor'!$Y$7:$Y$850,0)),"") | B111: =IFERROR(INDEX('Spread Monitor'!$B$7:$B$850,MATCH("CHF|7",'Spread Monitor'!$Y$7:$Y$850,0)),"") | C111: =IFERROR(INDEX('Spread Monitor'!$C$7:$C$850,MATCH("CHF|7",'Spread Monitor'!$Y$7:$Y$850,0)),"") | D111: =IFERROR(INDEX('Spread Monitor'!$E$7:$E$850,MATCH("CHF|7",'Spread Monitor'!$Y$7:$Y$850,0)),"") | E111: =IFERROR(INDEX('Spread Monitor'!$G$7:$G$850,MATCH("CHF|7",'Spread Monitor'!$Y$7:$Y$850,0)),"") | F111: =IFERROR(INDEX('Spread Monitor'!$H$7:$H$850,MATCH("CHF|7",'Spread Monitor'!$Y$7:$Y$850,0)),"") | G111: =IFERROR(INDEX('Spread Monitor'!$L$7:$L$850,MATCH("CHF|7",'Spread Monitor'!$Y$7:$Y$850,0)),"") | H111: =IFERROR(INDEX('Spread Monitor'!$O$7:$O$850,MATCH("CHF|7",'Spread Monitor'!$Y$7:$Y$850,0)),"") | I111: =IFERROR(INDEX('Spread Monitor'!$Q$7:$Q$850,MATCH("CHF|7",'Spread Monitor'!$Y$7:$Y$850,0)),"") | J111: =IFERROR(INDEX('Spread Monitor'!$R$7:$R$850,MATCH("CHF|7",'Spread Monitor'!$Y$7:$Y$850,0)),"") | K111: =IFERROR(INDEX('Spread Monitor'!$S$7:$S$850,MATCH("CHF|7",'Spread Monitor'!$Y$7:$Y$850,0)),"")
A112: =IFERROR(INDEX('Spread Monitor'!$A$7:$A$850,MATCH("CHF|8",'Spread Monitor'!$Y$7:$Y$850,0)),"") | B112: =IFERROR(INDEX('Spread Monitor'!$B$7:$B$850,MATCH("CHF|8",'Spread Monitor'!$Y$7:$Y$850,0)),"") | C112: =IFERROR(INDEX('Spread Monitor'!$C$7:$C$850,MATCH("CHF|8",'Spread Monitor'!$Y$7:$Y$850,0)),"") | D112: =IFERROR(INDEX('Spread Monitor'!$E$7:$E$850,MATCH("CHF|8",'Spread Monitor'!$Y$7:$Y$850,0)),"") | E112: =IFERROR(INDEX('Spread Monitor'!$G$7:$G$850,MATCH("CHF|8",'Spread Monitor'!$Y$7:$Y$850,0)),"") | F112: =IFERROR(INDEX('Spread Monitor'!$H$7:$H$850,MATCH("CHF|8",'Spread Monitor'!$Y$7:$Y$850,0)),"") | G112: =IFERROR(INDEX('Spread Monitor'!$L$7:$L$850,MATCH("CHF|8",'Spread Monitor'!$Y$7:$Y$850,0)),"") | H112: =IFERROR(INDEX('Spread Monitor'!$O$7:$O$850,MATCH("CHF|8",'Spread Monitor'!$Y$7:$Y$850,0)),"") | I112: =IFERROR(INDEX('Spread Monitor'!$Q$7:$Q$850,MATCH("CHF|8",'Spread Monitor'!$Y$7:$Y$850,0)),"") | J112: =IFERROR(INDEX('Spread Monitor'!$R$7:$R$850,MATCH("CHF|8",'Spread Monitor'!$Y$7:$Y$850,0)),"") | K112: =IFERROR(INDEX('Spread Monitor'!$S$7:$S$850,MATCH("CHF|8",'Spread Monitor'!$Y$7:$Y$850,0)),"")
A113: =IFERROR(INDEX('Spread Monitor'!$A$7:$A$850,MATCH("CHF|9",'Spread Monitor'!$Y$7:$Y$850,0)),"") | B113: =IFERROR(INDEX('Spread Monitor'!$B$7:$B$850,MATCH("CHF|9",'Spread Monitor'!$Y$7:$Y$850,0)),"") | C113: =IFERROR(INDEX('Spread Monitor'!$C$7:$C$850,MATCH("CHF|9",'Spread Monitor'!$Y$7:$Y$850,0)),"") | D113: =IFERROR(INDEX('Spread Monitor'!$E$7:$E$850,MATCH("CHF|9",'Spread Monitor'!$Y$7:$Y$850,0)),"") | E113: =IFERROR(INDEX('Spread Monitor'!$G$7:$G$850,MATCH("CHF|9",'Spread Monitor'!$Y$7:$Y$850,0)),"") | F113: =IFERROR(INDEX('Spread Monitor'!$H$7:$H$850,MATCH("CHF|9",'Spread Monitor'!$Y$7:$Y$850,0)),"") | G113: =IFERROR(INDEX('Spread Monitor'!$L$7:$L$850,MATCH("CHF|9",'Spread Monitor'!$Y$7:$Y$850,0)),"") | H113: =IFERROR(INDEX('Spread Monitor'!$O$7:$O$850,MATCH("CHF|9",'Spread Monitor'!$Y$7:$Y$850,0)),"") | I113: =IFERROR(INDEX('Spread Monitor'!$Q$7:$Q$850,MATCH("CHF|9",'Spread Monitor'!$Y$7:$Y$850,0)),"") | J113: =IFERROR(INDEX('Spread Monitor'!$R$7:$R$850,MATCH("CHF|9",'Spread Monitor'!$Y$7:$Y$850,0)),"") | K113: =IFERROR(INDEX('Spread Monitor'!$S$7:$S$850,MATCH("CHF|9",'Spread Monitor'!$Y$7:$Y$850,0)),"")
A114: =IFERROR(INDEX('Spread Monitor'!$A$7:$A$850,MATCH("CHF|10",'Spread Monitor'!$Y$7:$Y$850,0)),"") | B114: =IFERROR(INDEX('Spread Monitor'!$B$7:$B$850,MATCH("CHF|10",'Spread Monitor'!$Y$7:$Y$850,0)),"") | C114: =IFERROR(INDEX('Spread Monitor'!$C$7:$C$850,MATCH("CHF|10",'Spread Monitor'!$Y$7:$Y$850,0)),"") | D114: =IFERROR(INDEX('Spread Monitor'!$E$7:$E$850,MATCH("CHF|10",'Spread Monitor'!$Y$7:$Y$850,0)),"") | E114: =IFERROR(INDEX('Spread Monitor'!$G$7:$G$850,MATCH("CHF|10",'Spread Monitor'!$Y$7:$Y$850,0)),"") | F114: =IFERROR(INDEX('Spread Monitor'!$H$7:$H$850,MATCH("CHF|10",'Spread Monitor'!$Y$7:$Y$850,0)),"") | G114: =IFERROR(INDEX('Spread Monitor'!$L$7:$L$850,MATCH("CHF|10",'Spread Monitor'!$Y$7:$Y$850,0)),"") | H114: =IFERROR(INDEX('Spread Monitor'!$O$7:$O$850,MATCH("CHF|10",'Spread Monitor'!$Y$7:$Y$850,0)),"") | I114: =IFERROR(INDEX('Spread Monitor'!$Q$7:$Q$850,MATCH("CHF|10",'Spread Monitor'!$Y$7:$Y$850,0)),"") | J114: =IFERROR(INDEX('Spread Monitor'!$R$7:$R$850,MATCH("CHF|10",'Spread Monitor'!$Y$7:$Y$850,0)),"") | K114: =IFERROR(INDEX('Spread Monitor'!$S$7:$S$850,MATCH("CHF|10",'Spread Monitor'!$Y$7:$Y$850,0)),"")

Sheet Company_desc
A1: ISIN | B1: Company description
A2: US88579YBJ91 | B2: US industrial and consumer company
A3: XS2534976886 | B3: Italian diversified utility in electricity, renewables, gas, water, waste management
A4: XS2583205906 | B4: Italian diversified utility in electricity, renewables, gas, water, waste management
A5: XS2575555938 | B5: Provides power and automation technologies
A6: XS1709529520 | B6: Abu Dhabi Crude Oil Pipeline L.L.C. operates as a pipeline company.
A7: XS1402929746 | B7: United Arab Emirates Government
A8: XS2600248335 | B8: Abu Dhabi majority state-owned energy company
A9: FR0014006ND8 | B9: operates managed and franchised hotels, resort and vacation facility
A10: XS1799545329 | B10: Spanish engineering and contracting company
A11: XS2109438205 | B11: Provides rail transportation, catering and tourism services, majority state-owned
A12: XS1636266832 | B12: Indian operator of shipping port and special economic zones
... A989: US912797GB79 | B989: U.S. Government bond
A990: USP9406GAC26
A991: US872898AA96 | B991: Manufactures semiconductor devices
A992: US872898AC52 | B992: Manufactures semiconductor devices
A993: US872898AD36 | B993: Manufactures semiconductor devices
A994: US872898AE19 | B994: Manufactures semiconductor devices
A995: USG91139Af57 | B995: Manufactures semiconductor devices
A996: USG91139AD00 | B996: Manufactures semiconductor devices
A997: US912828Z377 | B997: U.S. Government bond
A998: US91282CBF77 | B998: U.S. Government bond
A999: US912828N712 | B999: U.S. Government bond
A1000: US9128283R96 | B1000: U.S. Government bond
A1001: US91282CGK18 | B1001: U.S. Government bond
A1002: US912810QF84 | B1002: U.S. Government bond
... A1085: XS2338564870 | B1085: Germany's leading auto supplier

Sheet SYZ_static
A1: ISIN | B1: SYZ view | C1: Company | D1: Coupon | E1: Structure | F1: Maturity | G1: Country | H1: Sector | I1: Den. (k) | J1: Price | K1: YTW | L1: YTW 1w chg | M1: YTW 1m chg | N1: Spread | O1: Dur. | P1: Ind LV. | Q1: Company Description | R1: Currency | S1: Bond Classification | T1: rating | U1: Tax Group | V1: Column1
A2: USN15516AB83 | B2: Hold | C2: Braskem Netherlands | D2: 4.5 | E2: Sr Unsecured | F2: 10.01.2028 | G2: Brazil | H2: Basic Materials | I2: 200 | J2: 83.007 | K2: 12.620055 | L2: 1.763736 | M2: 2.963971 | N2: 876.87753 | O2: 2.6281524 | P2: 25 | Q2: Largest producer of thermoplastic resins in South America | R2: USD | S2: Latin America | T2: BB | U2: NR
A3: USN15516AG70 | B3: Hold | C3: Braskem Netherlands | D3: 7.25 | E3: Sr Unsecured | F3: 13.02.2033 | G3: Brazil | H3: Basic Materials | I3: 200 | J3: 75.662 | K3: 12.261012 | L3: 0.84246 | M3: 1.748375 | N3: 810.00866 | O3: 5.8893849 | P3: 25 | Q3: Largest producer of thermoplastic resins in South America | R3: USD | S3: Latin America | T3: BB | U3: BB+
A4: USU60050AA61 | B4: Hold | C4: Mileage Plus Hldings Llc | D4: 6.5 | E4: 1St Lien | F4: 20.06.2027 | G4: United states | H4: Consumer, Cyclical | I4: 0.001 | J4: 100 | K4: 6.483611 | L4: 2.455632 | M4: 3.827457 | N4: 668.57041 | O4: 1.124939 | P4: 0 | Q4: Frequent flyer program of United Airlines | R4: USD | S4: Investment Grade | T4: BBB- | U4: BBB-
A5: USU1065PAA94 | B5: Hold | C5: Braskem America Finance | D5: 7.125 | E5: Sr Unsecured | F5: 22.07.2041 | G5: Brazil | H5: Basic Materials | I5: 200 | J5: 70.683 | K5: 11.070353 | L5: 0.37326 | M5: 0.495851 | N5: 644.49545 | O5: 9.0007008 | P5: 25 | Q5: Largest producer of thermoplastic resins in South America | R5: USD | S5: Latin America | T5: BB | U5: NR
A6: US80386WAD74 | B6: Top pick | C6: Sasol Financing Usa Llc | D6: 5.5 | E6: Sr Unsecured | F6: 18.03.2031 | G6: South africa | H6: Basic Materials | I6: 200 | J6: 82.178 | K6: 9.635929 | L6: -0.000375 | M6: 0.222237 | N6: 563.60306 | O6: 4.8121109 | P6: 25 | Q6: Integrated energy and chemical company | R6: USD | S6: High Yield | T6: BB+ | U6: BB+
A7: USG2583XAB76 | B7: Not accumulate | C7: Csn Islands Xi Corp | D7: 6.75 | E7: Sr Unsecured | F7: 28.01.2028 | G7: Brazil | H7: Basic Materials | I7: 200 | J7: 94.781 | K7: 9.080597 | L7: -0.001952 | M7: -0.42103 | N7: 523.50063 | O7: 2.5869376 | P7: 25 | Q7: Steel maker | R7: USD | S7: Latin America | T7: BB- | U7: BB-
A8: USE0R75RAB28 | B8: Hold | C8: Ai Candelaria -Spain- Sa | D8: 5.75 | E8: Secured | F8: 15.06.2033 | G8: Colombia | H8: Energy | I8: 250 | J8: 84.735 | K8: 8.425234 | L8: -0.175475 | M8: -0.106448 | N8: 518.16614 | O8: 4.8528797 | P8: 0 | Q8: Holding company of oil pipeline | R8: USD | S8: Latin America | T8: B+ | U8: BB-
A9: USU8035UAC63 | B9: Hold | C9: Sasol Financing Usa Llc | D9: 8.75 | E9: Sr Unsecured | F9: 03.05.2029 | G9: South africa | H9: Basic Materials | I9: 200 | J9: 99.134 | K9: 9.016033 | L9: -0.032661 | M9: 0.010598 | N9: 511.53662 | O9: 3.2725758 | P9: 25 | Q9: Integrated energy and chemical company | R9: USD | S9: High Yield | T9: BB+ | U9: BB+
A10: CH0333827506 | B10: Hold | C10: Teva Pharm Fin Iv | D10: 1 | E10: Sr Unsecured | F10: 28.07.2025 | G10: Israel | H10: Consumer, Non-cyclical | I10: 5 | J10: 99.795 | K10: 4.857654 | L10: -0.046412 | M10: 1.919441 | N10: 506.33195 | O10: 0.4262455 | P10: 20 | Q10: Largest manufacturer of pharmaceutical generics | R10: CHF | S10: High Yield | T10: BB | U10: BB
A11: USU8215LAA27 | B11: Hold | C11: Sierracol Enrgy Andina | D11: 6 | E11: Sr Unsecured | F11: 15.06.2028 | G11: Colombia | H11: Energy | I11: 200 | J11: 92.788 | K11: 8.839394 | L11: -0.014173 | M11: -0.33487 | N11: 500.8934 | O11: 2.8895959 | P11: 0 | Q11: Oil and gas company | R11: USD | S11: Latin America | T11: B+ | U11: B+
A12: FR001400QC85 | B12: Hold | C12: Eramet | D12: 6.5 | E12: Sr Unsecured | F12: 30.11.2029 | G12: France | H12: Basic Materials | I12: 100 | J12: 99.717 | K12: 6.56289 | L12: -0.08319 | M12: -0.201254 | N12: 427.20822 | O12: 3.9336327 | P12: 25 | Q12: Partially state-owned mining company in manganese, nickel, and special steels. | R12: EUR | S12: High Yield | T12: BB- | U12: BB-
A13: FR001400HZE3 | B13: Hold | C13: Eramet | D13: 7 | E13: Sr Unsecured | F13: 22.05.2028 | G13: France | H13: Basic Materials | I13: 100 | J13: 101.982 | K13: 6.162619 | L13: -0.141099 | M13: -0.252569 | N13: 411.02319 | O13: 2.519972 | P13: 25 | Q13: Partially state-owned mining company in manganese, nickel, and special steels. | R13: EUR | S13: High Yield | T13: BB- | U13: BB-
... A127: XS2431029441 | B127: Hold | C127: Axa Sa | D127: 1.875 | E127: Subordinated | F127: 10.07.2042 | G127: France | H127: Financial | I127: 100 | J127: 89.53 | K127: 3.592715 | L127: -0.077509 | M127: -0.124003 | N127: 147.42548 | O127: 6.5911615 | P127: 50 | Q127: Global insurance group | R127: EUR | S127: Investment Grade | T127: A- | U127: A-
A128: XS0556373347 | B128: Hold | C128: Cosan Overseas Ltd | D128: 8.25 | E128: Sr Unsecured | F128: 46752 | G128: Brazil | H128: Energy | I128: 100 | J128: 100.532 | K128: 6.610807 | L128: 3.307967 | M128: -0.547609 | N128: 146.75383 | O128: 0.19794283 | P128: 0 | Q128: Brazilian producer in bioethanol, sugar and energy | R128: USD | S128: Latin America | T128: BB | U128: BB
A129: USP04568AB06 | B129: Top Pick | C129: Arcos Dorados Bv | D129: 6.125 | E129: Sr Unsecured | F129: 27.05.2029 | G129: Brazil | H129: Consumer, Cyclical | I129: 200 | J129: 101.439 | K129: 5.575504 | L129: 0.059752 | M129: -0.238129 | N129: 146.42666 | O129: 2.8926626 | P129: 0 | Q129: Largest MacDonald franchisee in Latin America | R129: USD | S129: Latin America | T129: BB+ | U129: BB+
A130: US05947LBB36 | B130: Top Pick | C130: Banco Bradesco (Cayman) | D130: 6.5 | E130: Sr Unsecured | F130: 22.01.2030 | G130: Brazil | H130: Financial | I130: 200 | J130: 104.489 | K130: 5.371717 | L130: -0.002948 | M130: -0.135452 | N130: 145.93201 | O130: 4.160838 | P130: 0 | Q130: One of the largest banks in Spain | R130: USD | S130: Latin America | T130: BB | U130: BB+
A131: USU1022EAF52 | B131: Hold | C131: Boyd Gaming Corp | D131: 4.75 | E131: Sr Unsecured | F131: 15.06.2031 | G131: United states | H131: Consumer, Cyclical | I131: 2 | J131: 95.624 | K131: 5.627014 | L131: -0.000802 | M131: -0.225768 | N131: 145.64543 | O131: 5.2231857 | P131: 25 | Q131: A casino entertainment | R131: USD | S131: High Yield | T131: BB- | U131: BB-
A132: USH42097DT18 | B132: Hold | C132: Ubs Group Ag | D132: 5.959 | E132: Sr Unsecured | F132: 12.01.2034 | G132: Switzerland | H132: Financial | I132: 200 | J132: 105.003 | K132: 5.14724 | L132: -0.024911 | M132: -0.194086 | N132: 145.30526 | O132: 6.230711 | P132: 25 | Q132: Largest bank of Switzerland | R132: USD | S132: Investment Grade | T132: A- | U132: A-
A133: USG2440JAG07 | B133: Hold | C133: Gusap Iii Lp | D133: 7.25 | E133: Sr Unsecured | F133: 16.04.2044 | G133: Brazil | H133: Basic Materials | I133: 200 | J133: 110.896 | K133: 6.240776 | L133: -0.009039 | M133: -0.175371 | N133: 145.27817 | O133: 10.325569 | P133: 25 | Q133: Leading producer of steel in the Americas | R133: USD | S133: Latin America | T133: BBB | U133: BBB
A134: XS2984222989 | B134: Hold | C134: Banco Santander Sa | D134: 5.625 | E134: Sr Non Preferred | F134: 27.01.2031 | G134: Spain | H134: Financial | I134: 100 | J134: 101.893 | K134: 5.055578 | L134: -0.030085 | M134: -0.23169 | N134: 144.97621 | O134: 4.1956228 | P134: 0 | Q134: Spain's largest banking group | R134: GBP | S134: Investment Grade | T134: A- | U134: A-
A135: XS2802883731 | B135: Hold | C135: Dufry One Bv | D135: 4.75 | E135: Sr Unsecured | F135: 18.04.2031 | G135: Switzerland | H135: Consumer, Cyclical | I135: 100 | J135: 102.9 | K135: 3.952821 | L135: -0.038697 | M135: 0.049395 | N135: 144.87083 | O135: 3.698572 | P135: 25 | Q135: World's biggest airport retailer | R135: EUR | S135: High Yield | T135: NR | U135: NR
A136: USP30179BQ04 | B136: Top pick | C136: Comision Federal De Elec | D136: 4.688 | E136: Sr Unsecured | F136: 15.05.2029 | G136: Mexico | H136: Utilities | I136: 200 | J136: 97.745 | K136: 5.341327 | L136: 0.000621 | M136: -0.183382 | N136: 144.58489 | O136: 3.7147684 | P136: 60 | Q136: Generates and distributes electricity. | R136: USD | S136: Latin America | T136: BBB- | U136: BBB-
A137: US38141GC449 | B137: Hold | C137: Goldman Sachs Group Inc | D137: 5.536 | E137: Sr Unsecured | F137: 28.01.2036 | G137: United states | H137: Financial | I137: 1 | J137: 102.27 | K137: 5.230643 | L137: -0.037273 | M137: -0.186455 | N137: 143.72783 | O137: 7.5443877 | P137: 0 | Q137: One of the largest US investment banks | R137: USD | S137: Investment Grade | T137: A- | U137: A-
A138: FR001400Q6Z9 | B138: Top Pick | C138: Air France-Klm | D138: 4.625 | E138: Sr Unsecured | F138: 23.05.2029 | G138: France | H138: Consumer, Cyclical | I138: 100 | J138: 103.608 | K138: 3.548669 | L138: -0.073328 | M138: 0.105508 | N138: 141.86658 | O138: 3.4927924 | P138: 25 | Q138: Offers air transportation services | R138: EUR | S138: High Yield | T138: BB+ | U138: BB+
A139: XS2434515313 | B139: Hold | C139: Coca-Cola Icecek As | D139: 4.5 | E139: Sr Unsecured | F139: 20.01.2029 | G139: Turkey | H139: Consumer, Non-cyclical | I139: 200 | J139: 97.433 | K139: 5.306356 | L139: -0.057566 | M139: -0.227373 | N139: 141.76239 | O139: 3.4992525 | P139: 25 | Q139: Coca-Cola's top ten largest bottler | R139: USD | S139: Investment Grade | T139: BBB- | U139: BBB-
A140: US88167AAR23 | B140: Hold | C140: Teva Pharmaceuticals Ne | D140: 8.125 | E140: Sr Unsecured | F140: 15.09.2031 | G140: Israel | H140: Consumer, Non-cyclical | I140: 200 | J140: 113.463 | K140: 5.440035 | L140: -0.088975 | M140: -0.39012 | N140: 140.34601 | O140: 4.8466894 | P140: 0 | Q140: Largest manufacturer of pharmaceutical generics | R140: USD | S140: High Yield | T140: BB | U140: BB
... A177: US71647NAY58 | B177: Hold | C177: Petrobras Global Finance | D177: 5.999 | E177: Sr Unsecured | F177: 27.01.2028 | G177: Brazil | H177: Energy | I177: 2 | J177: 102.132 | K177: 5.096236 | L177: -0.057446 | M177: -0.1454 | N177: 125.47595 | O177: 2.65447 | P177: 25 | Q177: Largest oil company in Latin America | R177: USD | S177: Latin America | T177: BB | U177: BB
A178: US4651387N91 | B178: Not accumulate | C178: State Of Israel | D178: 4.5 | E178: Sr Unsecured | F178: 30.01.2043 | G178: Israel | H178: Government | I178: 200 | J178: 83.286 | K178: 6.058899 | L178: -0.054361 | M178: -0.046472 | N178: 125.18803 | O178: 11.594592 | P178: 85 | R178: USD | S178: Investment Grade | T178: A- | U178: A-
A179: US345397F810 | B179: Top Pick | C179: Ford Motor Credit Co Llc | D179: 5.125 | E179: Sr Unsecured | F179: 05.11.2026 | G179: United states | H179: Consumer, Cyclical | I179: 200 | J179: 99.897 | K179: 5.200937 | L179: -0.082301 | M179: -0.388855 | N179: 124.535 | O179: 1.58905 | P179: 0 | Q179: Global automotive manufacturer | R179: USD | S179: Investment Grade | T179: BB+ | U179: BB+
A180: XS2577136109 | B180: Hold | C180: Saudi International Bond | D180: 5 | E180: Sr Unsecured | F180: 18.01.2053 | G180: Saudi Arabia | H180: Government | I180: 200 | J180: 85.497 | K180: 6.09301 | L180: -0.011407 | M180: -0.131991 | N180: 124.34286 | O180: 13.861385 | P180: 80 | Q180: Kingdom of Saudia sovereign bond | R180: USD | S180: Investment Grade | T180: A+ | U180: A+
A181: USA08163AA41 | B181: Hold | C181: Brf Gmbh | D181: 4.35 | E181: Sr Unsecured | F181: 29.09.2026 | G181: Brazil | H181: Consumer, Non-cyclical | I181: 200 | J181: 98.994 | K181: 5.202403 | L181: 0.151768 | M181: -0.092815 | N181: 123.31307 | O181: 1.5069403 | P181: 25 | Q181: Distributes food products | R181: USD | S181: Latin America | T181: BB | U181: BB
A182: USU4328RAG93 | B182: Hold | C182: Hilton Domestic Operatin | D182: 4 | E182: Sr Unsecured | F182: 01.05.2031 | G182: United states | H182: Consumer, Cyclical | I182: 2 | J182: 93.527 | K182: 5.307317 | L182: 0.086196 | M182: -0.179767 | N182: 121.32703 | O182: 5.2912434 | P182: 15 | Q182: Owns and operates hotels and motels | R182: USD | S182: High Yield | T182: BB | U182: BB
A183: US71647NBH17 | B183: Hold | C183: Petrobras Global Finance | D183: 5.6 | E183: Sr Unsecured | F183: 03.01.2031 | G183: Brazil | H183: Energy | I183: 2 | J183: 101.744 | K183: 5.21638 | L183: -0.110675 | M183: -0.382248 | N183: 121.23822 | O183: 4.8968429 | P183: 0 | Q183: Largest oil company in Latin America | R183: USD | S183: Latin America | T183: BB | U183: BB
A184: USU1851TAB71 | B184: Hold | C184: Clearway Energy Op Llc | D184: 4.75 | E184: Sr Unsecured | F184: 15.03.2028 | G184: United states | H184: Utilities | I184: 2 | J184: 98.703 | K184: 5.271453 | L184: 0.018855 | M184: -0.160178 | N184: 120.79557 | O184: 2.7490966 | P184: 25 | Q184: Provides power generation services | R184: USD | S184: High Yield | T184: BB | U184: BB
A185: USN29505AB53 | B185: Hold | C185: Embraer Netherlands Fina | D185: 7 | E185: Sr Unsecured | F185: 28.07.2030 | G185: Brazil | H185: Industrial | I185: 200 | J185: 107.856 | K185: 5.135328 | L185: -0.067903 | M185: -0.254073 | N185: 119.88717 | O185: 4.3207858 | P185: 50 | Q185: Leading manufacturer of regional jet airplanes | R185: USD | S185: Latin America | T185: BBB- | U185: BBB-
A186: USP56236AB16 | B186: Hold | C186: Inretail Consumer | D186: 3.25 | E186: 1St Lien | F186: 22.03.2028 | G186: Peru | H186: Consumer, Cyclical | I186: 200 | J186: 95.546 | K186: 5.029619 | L186: -0.246748 | M186: -0.531654 | N186: 119.74419 | O186: 2.8334197 | P186: 25 | Q186: Operates as a multi-format retailer company | R186: USD | S186: Latin America | T186: BB+ | U186: BB+
A187: FR001400F2R8 | B187: Hold | C187: Air France-Klm | D187: 8.125 | E187: Sr Unsecured | F187: 31.05.2028 | G187: France | H187: Consumer, Cyclical | I187: 100 | J187: 112.431 | K187: 3.146846 | L187: -0.093518 | M187: -0.107586 | N187: 118.87985 | O187: 2.573871 | P187: 25 | Q187: Offers air transportation services | R187: EUR | S187: High Yield | T187: BB+ | U187: BB+
A188: US91911TAR41 | B188: Hold | C188: Vale Overseas Limited | D188: 6.125 | E188: Sr Unsecured | F188: 12.06.2033 | G188: Brazil | H188: Basic Materials | I188: 2 | J188: 104.544 | K188: 5.394606 | L188: -0.003529 | M188: -0.184086 | N188: 118.84471 | O188: 6.2478781 | P188: 0 | Q188: leader in iron ore and second largest producer in nickel | R188: USD | S188: Latin America | T188: BBB- | U188: BBB-
A189: USP75744AM75 | B189: Hold | C189: Republic Of Paraguay | D189: 5.85 | E189: Sr Unsecured | F189: 21.08.2033 | G189: Paraguay | H189: Government | I189: 200 | J189: 102.917 | K189: 5.390083 | L189: -0.063426 | M189: -0.35026 | N189: 118.71722 | O189: 6.3701048 | P189: 15 | Q189: Paraguay Government bond | R189: USD | S189: Latin America | T189: BB+ | U189: BB+
A190: CH1357852800 | B190: Top pick | C190: Vonovia Se | D190: 2 | E190: Sr Unsecured | F190: 26.08.2031 | G190: Germany | H190: Financial | I190: 5 | J190: 103.471 | K190: 1.396982 | L190: -0.008729 | M190: 0.077225 | N190: 118.39812 | O190: 5.9506502 | P190: 0 | Q190: Germany's largest residential real estate owner | R190: CHF | S190: Investment Grade | T190: BBB+ | U190: BBB+
... A332: CH1325807886 | B332: Hold | C332: Caixabank Sa | D332: 2.175 | E332: Sr Preferred | F332: 19.03.2030 | G332: Spain | H332: Financial | I332: 200 | J332: 104.409 | K332: 0.952794 | L332: 0.045513 | M332: 0.209935 | N332: 83.50549 | O332: 3.8245141 | P332: 80 | Q332: One of the largest Spanish banks | R332: CHF | S332: Investment Grade | T332: A | U332: A
A333: XS1991188548 | B333: Hold | C333: Maf Sukuk Ltd | D333: 4.638 | E333: Sr Unsecured | F333: 14.05.2029 | G333: U.A.E | H333: Financial | I333: 200 | J333: 99.725 | K333: 4.715208 | L333: 0.048483 | M333: -0.13285 | N333: 83.454317 | O333: 3.7301012 | P333: 60 | R333: USD | S333: Investment Grade | T333: BBB | U333: BBB
A334: CH1251998220 | B334: Hold | C334: Grande Dixence | D334: 2.35 | E334: Sr Unsecured | F334: 06.06.2030 | G334: Switzerland | H334: Utilities | I334: 5 | J334: 106.636 | K334: 0.959166 | L334: 0.026474 | M334: 0.154214 | N334: 83.345784 | O334: 4.9073088 | P334: 0 | Q334: provides hydroelectric power generation services through several dams in Switzerland | R334: CHF | S334: Investment Grade | T334: #N/A N/A | U334: #N/A N/A
A335: FR0014004EF7 | B335: Hold | C335: Caisse Nat Reassurance | D335: 0.75 | E335: Subordinated | F335: 07.07.2028 | G335: France | H335: Financial | I335: 100 | J335: 94.129 | K335: 2.821539 | L335: -0.086613 | M335: -0.110166 | N335: 83.132746 | O335: 3.2183337 | P335: 75 | Q335: French Global Insurer | R335: EUR | S335: Investment Grade | T335: NR | U335: NR
A336: CH1242301286 | B336: Hold | C336: Swiss Life Holding Ag | D336: 2.61 | E336: Sr Unsecured | F336: 26.01.2032 | G336: Switzerland | H336: Financial | I336: 5 | J336: 109.381 | K336: 1.061798 | L336: 0.060661 | M336: 0.227674 | N336: 83.086709 | O336: 6.1560745 | P336: 80 | Q336: Provides life and property insurance | R336: CHF | S336: Investment Grade | T336: NR | U336: NR
A337: XS2328823104 | B337: Top Pick | C337: Heathrow Funding Ltd | D337: 1.125 | E337: 1St Lien | F337: 08.10.2030 | G337: United Kingdom | H337: Industrial | I337: 100 | J337: 90.21 | K337: 3.178651 | L337: -0.103663 | M337: -0.089014 | N337: 83.002879 | O337: 5.2686027 | P337: 60 | Q337: UK's largest airport | R337: EUR | S337: Investment Grade | T337: BBB+ | U337: BBB+
A338: US37045XEH52 | B338: Hold | C338: General Motors Finl Co | D338: 5.8 | E338: Sr Unsecured | F338: 23.06.2028 | G338: United states | H338: Consumer, Cyclical | I338: 2 | J338: 103.019 | K338: 4.666292 | L338: -0.069421 | M338: -0.367617 | N338: 82.911307 | O338: 2.915605 | P338: 0 | Q338: World's third largest automaker owning Chevrolet, Buick and Cadillac | R338: USD | S338: Investment Grade | T338: BBB | U338: BBB
A339: CH0469273541 | B339: Hold | C339: Clariant Ag | D339: 1.125 | E339: Sr Unsecured | F339: 15.04.2026 | G339: Switzerland | H339: Basic Materials | I339: 5 | J339: 100.28 | K339: 0.755695 | L339: -0.042687 | M339: 0.094577 | N339: 82.885982 | O339: 1.1194853 | P339: 80 | Q339: Global specialty chemicals company | R339: CHF | S339: Investment Grade | T339: NR | U339: NR
A340: CH1251030123 | B340: Top Pick | C340: Alpiq Holding Ag | D340: 3.125 | E340: Sr Unsecured | F340: 29.04.2027 | G340: Switzerland | H340: Utilities | I340: 5 | J340: 104.229 | K340: 0.75713 | L340: 0.015018 | M340: 0.124577 | N340: 82.815572 | O340: 2.0718606 | P340: 0 | Q340: Generates, transmits and distributes electricity throughout Europe | R340: CHF | S340: High Yield | T340: #N/A N/A | U340: #N/A N/A
A341: US30216KAF93 | B341: Top pick | C341: Export-Import Bk India | D341: 2.25 | E341: Sr Unsecured | F341: 13.01.2031 | G341: India | H341: Government | I341: 200 | J341: 87.668 | K341: 4.823882 | L341: 0.093268 | M341: -0.102625 | N341: 82.772709 | O341: 5.3639553 | P341: 60 | Q341: Operates as a bank to exporters and importers, 100% state-owned | R341: USD | S341: Investment Grade | T341: BBB- | U341: BBB-
A342: FR001400FDB0 | B342: Hold | C342: Electricite De France Sa | D342: 4.25 | E342: Sr Unsecured | F342: 25.01.2032 | G342: France | H342: Utilities | I342: 100 | J342: 105.172 | K342: 3.324923 | L342: -0.058748 | M342: 0.03679 | N342: 82.513814 | O342: 5.7522981 | P342: 60 | Q342: French utility company fully owned by the State | R342: EUR | S342: Investment Grade | T342: BBB | U342: BBB
A343: XS2583205906 | B343: Top Pick | C343: A2A Spa | D343: 4.375 | E343: Sr Unsecured | F343: 03.02.2034 | G343: Italy | H343: Utilities | I343: 100 | J343: 105.979 | K343: 3.532035 | L343: -0.047044 | M343: -0.005365 | N343: 82.50327 | O343: 7.1829663 | P343: 60 | Q343: Italian diversified utility in electricity, renewables, gas, water, waste management | R343: EUR | S343: Investment Grade | T343: BBB | U343: BBB
A344: XS2441259137 | B344: Hold | C344: Sage Group Plc (The) | D344: 2.875 | E344: Sr Unsecured | F344: 08.02.2034 | G344: United Kingdom | H344: Technology | I344: 100 | J344: 83.749 | K344: 5.207217 | L344: 0.019942 | M344: -0.193511 | N344: 81.94304 | O344: 7.4821401 | P344: 50 | Q344: Software publishing company | R344: GBP | S344: Investment Grade | T344: NR | U344: NR
A345: FR001400KHH8 | B345: Hold | C345: Engie Sa | D345: 4.25 | E345: Sr Unsecured | F345: 06.09.2034 | G345: France | H345: Utilities | I345: 100 | J345: 104.971 | K345: 3.588477 | L345: -0.007347 | M345: -0.007195 | N345: 81.833998 | O345: 7.501259 | P345: 60 | Q345: French utility company specialised in renewables | R345: EUR | S345: Investment Grade | T345: BBB+ | U345: BBB+
... A431: US91087BAU44 | B431: Hold | C431: United Mexican States | D431: 5.4 | E431: Sr Unsecured | F431: 09.02.2028 | G431: Mexico | H431: Government | I431: 200 | J431: 102.014 | K431: 4.539179 | L431: 0.049674 | M431: -0.084503 | N431: 68.257594 | O431: 2.6347312 | P431: 60 | Q431: Mexican Government | R431: USD | S431: Latin America | T431: BBB- | U431: BBB-
A432: USG3925DAD24 | B432: Hold | C432: Gerdau Trade Inc | D432: 4.875 | E432: Sr Unsecured | F432: 24.10.2027 | G432: Brazil | H432: Basic Materials | I432: 200 | J432: 100.737 | K432: 4.530123 | L432: #VALUE! | M432: 0.003387 | N432: 68.135714 | O432: 2.4402828 | P432: 60 | Q432: Leading producer of steel in the Americas | R432: USD | S432: Latin America | T432: BBB | U432: BBB
A433: XS2747766090 | B433: Top Pick | C433: Edp Servicios Fin Esp Sa | D433: 3.5 | E433: Sr Unsecured | F433: 16.07.2030 | G433: Portugal | H433: Utilities | I433: 100 | J433: 102.306 | K433: 2.975739 | L433: -0.052177 | M433: 0.005443 | N433: 67.789857 | O433: 4.5572057 | P433: 60 | Q433: Portugal's largest utility company | R433: EUR | S433: Investment Grade | T433: BBB | U433: BBB
A434: US882508BM50 | B434: Hold | C434: Texas Instruments Inc | D434: 2.7 | E434: Sr Unsecured | F434: 15.09.2051 | G434: United states | H434: Technology | I434: 2 | J434: 60.504 | K434: 5.589561 | L434: -0.036495 | M434: -0.094639 | N434: 67.693796 | O434: 16.032087 | P434: 55 | Q434: Worldwide semiconductor design and manufacturing company | R434: USD | S434: Investment Grade | T434: A+ | U434: A+
A435: US11135FCD15 | B435: Top pick | C435: Broadcom Inc | D435: 4.8 | E435: Sr Unsecured | F435: 15.10.2034 | G435: United states | H435: Technology | I435: 2 | J435: 98.55 | K435: 4.996417 | L435: -0.010227 | M435: -0.157102 | N435: 67.653943 | O435: 7.4568459 | P435: 85 | Q435: Diversified semi-conductor company | R435: USD | S435: Investment Grade | T435: BBB | U435: BBB
A436: XS1716248197 | B436: Not accumulate | C436: Hsbc Holdings Plc | D436: 2.256 | E436: Sr Unsecured | F436: 13.11.2026 | G436: United Kingdom | H436: Financial | I436: 100 | J436: 99.137 | K436: 4.707651 | L436: -0.032222 | M436: -0.184601 | N436: 67.650964 | O436: 0.69323658 | P436: 80 | Q436: UK largest banking and financial services group | R436: GBP | S436: Investment Grade | T436: A- | U436: A-
A437: XS2056491587 | B437: Hold | C437: Generali | D437: 2.124 | E437: Subordinated | F437: 01.10.2030 | G437: Italy | H437: Financial | I437: 100 | J437: 95.754 | K437: 3.012436 | L437: -0.100563 | M437: -0.177466 | N437: 67.58163 | O437: 5.1241685 | P437: 60 | Q437: Largest insurer group in Italy | R437: EUR | S437: Investment Grade | T437: BBB | U437: BBB
A438: XS2104968404 | B438: Hold | C438: Unicredit Spa | D438: 1.8 | E438: Sr Non Preferred | F438: 20.01.2030 | G438: Italy | H438: Financial | I438: 250 | J438: 95.349 | K438: 2.908279 | L438: -0.067815 | M438: -0.129335 | N438: 67.287552 | O438: 4.5817489 | P438: 60 | Q438: One of the largest bank in italy | R438: EUR | S438: Investment Grade | T438: BBB- | U438: BBB-
A439: XS1577961862 | B439: Top Pick | C439: Prologis Lp | D439: 2.25 | E439: Sr Unsecured | F439: 30.06.2029 | G439: United states | H439: Financial | I439: 100 | J439: 91.828 | K439: 4.492599 | L439: -0.006021 | M439: -0.209658 | N439: 67.077886 | O439: 3.9319679 | P439: 0 | Q439: Global leading logistic real estate owner | R439: GBP | S439: Investment Grade | T439: A | U439: A-
A440: US054989AA67 | B440: Hold | C440: Bat Capital Corp | D440: 6.343 | E440: Sr Unsecured | F440: 02.08.2030 | G440: United Kingdom | H440: Consumer, Non-cyclical | I440: 2 | J440: 107.537 | K440: 4.60761 | L440: -0.003091 | M440: -0.223607 | N440: 66.996037 | O440: 4.4635012 | P440: 60 | Q440: Tobacco company | R440: USD | S440: Investment Grade | T440: BBB+ | U440: BBB+
A441: CH0330938876 | B441: Hold | C441: Ubs Group Ag | D441: 2.75 | E441: Sr Unsecured | F441: 08.08.2025 | G441: Switzerland | H441: Financial | I441: 100 | J441: 99.849 | K441: 4.486802 | L441: -0.180188 | M441: -0.383869 | N441: 66.984344 | O441: 0.44323302 | P441: 80 | Q441: Largest bank in Switzerland | R441: GBP | S441: Investment Grade | T441: A- | U441: A-
A442: XS2985139356 | B442: Hold | C442: Bmw Intl Investment Bv | D442: 5 | E442: Sr Unsecured | F442: 24.01.2028 | G442: Germany | H442: Consumer, Cyclical | I442: 100 | J442: 101.282 | K442: 4.396635 | L442: -0.000731 | M442: -0.22795 | N442: 66.888955 | O442: 2.6474375 | P442: 0 | Q442: European car manufacturer focused entirely on the premium segment | R442: GBP | S442: Investment Grade | T442: A | U442: A
A443: FR0014006ND8 | B443: Hold | C443: Accor Sa | D443: 2.375 | E443: Sr Unsecured | F443: 29.11.2028 | G443: France | H443: Consumer, Cyclical | I443: 100 | J443: 98.829 | K443: 2.738998 | L443: -0.07652 | M443: -0.168264 | N443: 66.873982 | O443: 3.5170749 | P443: 15 | Q443: operates managed and franchised hotels, resort and vacation facility | R443: EUR | S443: Investment Grade | T443: BBB- | U443: BBB-
A444: XS1345415472 | B444: Hold | C444: Santander Uk Group Hldgs | D444: 3.625 | E444: Sr Unsecured | F444: 14.01.2026 | G444: United Kingdom | H444: Financial | I444: 100 | J444: 99.548 | K444: 4.524786 | L444: -0.072494 | M444: -0.344025 | N444: 66.832088 | O444: 0.85726526 | P444: 80 | Q444: One of the largest bank in the Eurozone by market value | R444: GBP | S444: Investment Grade | T444: BBB+ | U444: BBB+
... A470: XS2405871570 | B470: Hold | C470: Singapore Airlines Ltd | D470: 3.375 | E470: Sr Unsecured | F470: 19.01.2029 | G470: Singapore | H470: Consumer, Cyclical | I470: 200 | J470: 96.312 | K470: 4.517359 | L470: 0.126756 | M470: -0.021927 | N470: 64.046486 | O470: 3.5874812 | P470: 0 | Q470: Flag carrier airline of Singapore | R470: USD | S470: High Yield | T470: #N/A N/A | U470: #N/A N/A
A471: XS2578939527 | B471: Hold | C471: Royal Bank Of Canada | D471: 5 | E471: Sr Unsecured | F471: 24.01.2028 | G471: Canada | H471: Financial | I471: 100 | J471: 101.352 | K471: 4.368341 | L471: -0.038376 | M471: -0.271049 | N471: 63.996157 | O471: 2.6505927 | P471: 80 | R471: GBP | S471: Investment Grade | T471: A+ | U471: A+
A472: PTBSSLOM0002 | B472: Hold | C472: Brisa Concessao Rodov Sa | D472: 2.375 | E472: 1St Lien | F472: 10.05.2027 | G472: Portugal | H472: Consumer, Non-cyclical | I472: 100 | J472: 99.769 | K472: 2.503056 | L472: -0.025385 | M472: -0.005595 | N472: 63.847135 | O472: 2.0797298 | P472: 70 | Q472: Operates network of motorways in Portugal | R472: EUR | S472: Investment Grade | T472: A- | U472: A-
A473: CH1227937716 | B473: Hold | C473: Bnp Paribas | D473: 2.4125 | E473: Sr Preferred | F473: 13.01.2028 | G473: France | H473: Financial | I473: 200 | J473: 104.484 | K473: 0.607043 | L473: 0.01916 | M473: 0.132654 | N473: 63.64684 | O473: 2.7930562 | P473: 80 | Q473: France's largest bank with a world leading position | R473: CHF | S473: Investment Grade | T473: A+ | U473: A+
A474: XS2353182293 | B474: Hold | C474: Enel Finance Intl Nv | D474: 0.75 | E474: Sr Unsecured | F474: 17.06.2030 | G474: Italy | H474: Utilities | I474: 100 | J474: 90.102 | K474: 2.931136 | L474: -0.042686 | M474: -0.046118 | N474: 63.632466 | O474: 5.0339029 | P474: 60 | Q474: Italian utility company | R474: EUR | S474: Investment Grade | T474: BBB | U474: BBB
A475: XS2997425637 | B475: Hold | C475: Central American Bank | D475: 4.625 | E475: Sr Unsecured | F475: 14.02.2028 | G475: Supranational | H475: Government | I475: 100 | J475: 100.488 | K475: 4.365092 | L475: 0.010547 | M475: -0.136279 | N475: 63.598611 | O475: 2.7119671 | P475: 0 | Q475: A development bank | R475: GBP | S475: Investment Grade | T475: AA- | U475: AA-
A476: US571903BR30 | B476: Top Pick | C476: Marriott International | D476: 4.8 | E476: Sr Unsecured | F476: 15.03.2030 | G476: United states | H476: Consumer, Cyclical | I476: 2 | J476: 100.975 | K476: 4.561961 | L476: -0.035045 | M476: -0.210946 | N476: 63.517418 | O476: 4.3331692 | P476: 0 | Q476: Worldwide operator and franchisor of hotels | R476: USD | S476: Investment Grade | T476: BBB | U476: BBB
A477: US713448FT00 | B477: Hold | C477: Pepsico Inc | D477: 4.65 | E477: Sr Unsecured | F477: 15.02.2053 | G477: United states | H477: Consumer, Non-cyclical | I477: 2 | J477: 87.83 | K477: 5.512944 | L477: -0.026482 | M477: -0.118385 | N477: 63.364016 | O477: 14.72037 | P477: 80 | Q477: One of the world leaders in snack foods and beverages | R477: USD | S477: Investment Grade | T477: A+ | U477: A+
A478: XS2594990892 | B478: Hold | C478: Mizuho Financial Group | D478: 5.628 | E478: Sr Unsecured | F478: 13.06.2028 | G478: Japan | H478: Financial | I478: 100 | J478: 103.24 | K478: 4.373877 | L478: -0.074587 | M478: -0.364168 | N478: 63.332814 | O478: 2.8556495 | P478: 85 | Q478: One of the largest banks in Japan | R478: GBP | S478: Investment Grade | T478: A | U478: A
A479: XS2826616596 | B479: Hold | C479: Cellnex Finance Co Sa | D479: 3.625 | E479: Sr Unsecured | F479: 24.01.2029 | G479: Spain | H479: Industrial | I479: 100 | J479: 102.848 | K479: 2.708553 | L479: -0.139399 | M479: -0.138962 | N479: 63.326184 | O479: 3.3846271 | P479: 85 | Q479: Europe's largest telecom tower operator | R479: EUR | S479: Investment Grade | T479: BBB- | U479: BBB-
A480: XS2592301365 | B480: Hold | C480: Tesco Corp Treasury Serv | D480: 4.25 | E480: Sr Unsecured | F480: 27.02.2031 | G480: United Kingdom | H480: Consumer, Non-cyclical | I480: 100 | J480: 106.084 | K480: 3.00861 | L480: -0.071271 | M480: -0.143728 | N480: 62.881239 | O480: 4.874524 | P480: 60 | Q480: Largest player in the UK grocery industry | R480: EUR | S480: Investment Grade | T480: BBB- | U480: BBB-
A481: CH1236363425 | B481: Hold | C481: Cooperatieve Rabobank Ua | D481: 2.4875 | E481: Sr Non Preferred | F481: 25.01.2029 | G481: Netherlands | H481: Financial | I481: 200 | J481: 104.584 | K481: 0.663884 | L481: 0.027156 | M481: 0.145351 | N481: 62.506344 | O481: 2.8205832 | P481: 80 | Q481: Largest bank in the Netherlands | R481: CHF | S481: Investment Grade | T481: A- | U481: A-
A482: XS2600248335 | B482: Hold | C482: Abu Dhabi National Energ | D482: 4.696 | E482: Sr Unsecured | F482: 24.04.2033 | G482: U.A.E | H482: Utilities | I482: 200 | J482: 99.196 | K482: 4.819864 | L482: 0.020622 | M482: -0.131972 | N482: 62.489247 | O482: 6.5728887 | P482: 85 | Q482: Abu Dhabi majority state-owned energy company | R482: USD | S482: Investment Grade | T482: AA- | U482: AA-
A483: XS1992985694 | B483: Hold | C483: Saudi Telecom Co | D483: 3.89 | E483: Sr Unsecured | F483: 13.05.2029 | G483: Saudi Arabia | H483: Communications | I483: 200 | J483: 97.85 | K483: 4.503705 | L483: -0.022459 | M483: -0.059528 | N483: 62.318497 | O483: 3.7907809 | P483: 80 | Q483: Majority state-owned telecom | R483: USD | S483: Investment Grade | T483: A+ | U483: A+
... A736: XS2364593579 | B736: Hold | C736: Jaguar Land Rover Automo | D736: 4.5 | E736: Sr Unsecured | F736: 15.07.2028 | G736: United Kingdom | H736: Consumer, Cyclical | I736: 100 | J736: 101.313 | K736: -3.754922 | L736: -7.190807 | M736: -6.180514 | N736: -567.44225 | O736: 0.38758424 | P736: 25 | Q736: designs, develops, and manufactures automobiles | R736: EUR | S736: High Yield | T736: BB+ | U736: BB+
A737: USU04354AF00 | B737: Hold | C737: Ascent Resources/Aru Fin | D737: 8.25 | E737: Sr Unsecured | F737: 31.12.2028 | G737: United states | H737: Energy | I737: 2 | J737: 102.228 | K737: #N/A N/A | L737: #VALUE! | M737: #VALUE! | N737: #N/A N/A | O737: 0.085782107 | P737: 25 | Q737: A natural gas company | R737: USD | S737: High Yield | T737: B+ | U737: B+
A738: XS2361342889 | B738: Hold | C738: Picard Groupe Sa | D738: 3.875 | E738: Secured | F738: 01.07.2026 | G738: France | H738: Consumer, Non-cyclical | I738: 100 | J738: 100.066 | K738: #N/A N/A | L738: #VALUE! | M738: #VALUE! | N738: #N/A N/A | O738: 0.34744193 | P738: 25 | Q738: French distributor of Frozen food products | R738: EUR | S738: High Yield | T738: NR | U738: NR
A739: US46590XAZ96 | B739: Hold | C739: Jbs Usa Hold/Food/Lux Co | D739: 5.125 | E739: Sr Unsecured | F739: 01.02.2028 | G739: United states | H739: Consumer, Non-cyclical | I739: 2 | J739: 102.487 | K739: #N/A N/A | L739: #VALUE! | M739: #VALUE! | N739: #N/A N/A | O739: 2.6247608 | P739: 0 | Q739: Largest protein company in Latin America | R739: USD | S739: Latin America | T739: BBB- | U739: BBB-
A740: US80282KBB17 | B740: Hold | C740: Santander Holdings Usa | D740: 3.45 | E740: Sr Unsecured | F740: 02.06.2025 | G740: United states | H740: Financial | I740: 2 | J740: #N/A N/A | K740: #N/A N/A | L740: #VALUE! | M740: #VALUE! | N740: #N/A N/A | O740: 0.27701178 | P740: 80 | Q740: One of the largest bank in the Eurozone by market value | R740: USD | S740: Investment Grade | T740: NR | U740: BBB+
A741: ES00000126Z1 | B741: Hold | C741: Bonos Y Oblig Del Estado | D741: 1.6 | E741: Sr Unsecured | F741: 30.04.2025 | G741: Spain | H741: Government | I741: 1 | J741: #N/A N/A | K741: #N/A N/A | L741: #VALUE! | M741: #VALUE! | N741: #N/A N/A | O741: 0.17388204 | P741: 80 | Q741: Spanish Government | R741: EUR | S741: Investment Grade | T741: NR | U741: BBB+
A742: XS1405766897 | B742: Hold | C742: Verizon Communications | D742: 0.875 | E742: Sr Unsecured | F742: 02.04.2025 | G742: United states | H742: Communications | I742: 100 | J742: #N/A N/A | K742: #N/A N/A | L742: #VALUE! | M742: #VALUE! | N742: #N/A N/A | O742: 0.10112497 | P742: 80 | Q742: Second largest telecommunications provider in the United States | R742: EUR | S742: Investment Grade | T742: NR | U742: BBB+
A743: USL20041AD89 | B743: Hold | C743: Cosan Luxembourg Sa | D743: 7 | E743: Sr Unsecured | F743: 20.01.2027 | G743: Brazil | H743: Energy | I743: 200 | J743: #N/A N/A | K743: #N/A N/A | L743: #VALUE! | M743: #VALUE! | N743: #N/A N/A | O743: 0.063633952 | P743: 25 | Q743: Brazilian producer in bioethanol, sugar and energy | R743: USD | S743: Latin America | T743: NR | U743: BB
A744: USP3631MAA38 | B744: Hold | C744: Electricidad Firme De Me | D744: 4.9 | E744: Secured | F744: 20.11.2026 | G744: Mexico | H744: Utilities | I744: 200 | J744: #N/A N/A | K744: #N/A N/A | L744: #VALUE! | M744: #VALUE! | N744: #N/A N/A | O744: 0.058089307 | P744: 25 | Q744: Utility holding company | R744: USD | S744: Latin America | T744: NR | U744: BB
A745: DE000DB7XJP9 | B745: Hold | C745: Deutsche Bank Ag | D745: 1.125 | E745: Sr Non Preferred | F745: 17.03.2025 | G745: Germany | H745: Financial | I745: 100 | J745: #N/A N/A | K745: #N/A N/A | L745: #VALUE! | M745: #VALUE! | N745: #N/A N/A | O745: 0.057446216 | P745: 80 | Q745: Germany's largest universal bank | R745: EUR | S745: Investment Grade | T745: NR | U745: BBB+
A746: XS1959498244 | B746: Hold | C746: Ford Motor Credit Co Llc | D746: 4.535 | E746: Sr Unsecured | F746: 06.03.2025 | G746: United states | H746: Consumer, Cyclical | I746: 100 | J746: #N/A N/A | K746: #N/A N/A | L746: #VALUE! | M746: #VALUE! | N746: #N/A N/A | O746: 0.02736889 | P746: 20 | Q746: Global automotive manufacturer | R746: GBP | S746: Investment Grade | T746: NR | U746: BB+
A747: XS1813724603 | B747: Hold | C747: Teva Pharm Fnc Nl Ii | D747: 4.5 | E747: Sr Unsecured | F747: 01.03.2025 | G747: Israel | H747: Consumer, Non-cyclical | I747: 100 | J747: #N/A N/A | K747: #N/A N/A | L747: #VALUE! | M747: #VALUE! | N747: #N/A N/A | O747: 0.019480101 | P747: 25 | Q747: Largest manufacturer of pharmaceutical generics | R747: EUR | S747: High Yield | T747: NR | U747: BB

Sheet ReadMe
A1: Bond spread variation since 14.07.2026
A3: SHEETS
A4: Spread Monitor | B4: One row per bond (763 ISINs). Every column except A is a formula. Filter and sort with the arrows on row 6 - no macro involved.
A5: Top & Bottom | B5: Top 10 wideners and Top 10 tighteners per currency (USD, EUR, GBP, CHF), pulled live from Spread Monitor with INDEX/MATCH on the hidden ranking keys (columns V:Y).
A6: Company_desc | B6: Input data: the ISIN -> company-description library carried over from the original workbook.
A7: SYZ_static | B7: Input data: the SYZ-internal fields (SYZ view, Ind LV., Bond Classification, Tax Group, rating) that are not available on Bloomberg, carried over from the original workbook.
A9: HOW TO USE
A10: 1 | B10: Open with the Bloomberg add-in connected, then Ctrl+Alt+F9 to force a full recalculation.
A11: 2 | B11: Change the anchor date in Spread Monitor!B2 (blue on yellow) to re-base everything. The four "since" headers rewrite themselves.
A12: 3 | B12: Add bonds by pasting ISINs at the bottom of column A - all formulas already run to row 850.
A14: BLOOMBERG FIELDS
A15: Company | B15: PROPER(BDP(ISIN & " Corp","NAME"))
A16: Sector | B16: BDP("INDUSTRY_SECTOR")
A17: Country | B17: PROPER(BDP("COUNTRY_FULL_NAME"))
A18: Ccy | B18: BDP("CRNCY")
A19: Structure | B19: BDP("PAYMENT_RANK")
A20: Coupon / Maturity | B20: BDP("CPN") / BDP("MATURITY")
A21: Den. (k) | B21: BDP("MIN_PIECE")/1000
A22: Price | B22: BDP("PX_LAST")
A23: YTW (%) | B23: BDP("YAS_BOND_YLD","YAS_YLD_FLAG=15")
A24: Mod. dur. | B24: BDP("YAS_MOD_DUR")
A25: Spread today (bp) | B25: BDP("YAS_OAS_SPRD")
A26: Spread on anchor (bp) | B26: BDP("YAS_OAS_SPRD","SETTLE_DT",$B$2)
... A30: Company description / SYZ view / Classification | B30: INDEX/MATCH on Company_desc and SYZ_static by ISIN.
A32: NOTES
A33: Not recalculated offline | B33: Every value comes from the Bloomberg add-in (_xll.BDP), which resolves only on a terminal-connected machine. Cells read as 0 or blank until you refresh in Excel.
A34: Blank-guarded | B34: Every formula is wrapped in IF($A="","",...), so the unused rows below the last ISIN stay empty instead of filling the sheet with errors.
A35: Ranking columns | B35: V:Y on Spread Monitor are grouped and hidden. Rank = COUNTIFS within currency, with a running COUNTIFS tie-break so two bonds with the same move never share a rank.
A36: ISIN universe | B36: The 746 bonds from the original Sheet1 plus the 17 newer ISINs that were sitting on the original Formulas sheet = 763 in total.
